Workbook
Name celpeCEE: '[1]@Referência'!$K$16:$K$18
Name ListaSimNao: '[1]@Referência'!$A$30:$A$31
Name Modalidade: '[1]@Referência'!$J$2:$J$6
Name tipoCELPE: '[1]@Referência'!$N$14:$N$18

Sheet Tabela de Transferência
A1: Campo | B1: Página | C1: Endereço.tex | D1: chave | E1: valor
A2: Inserir Mome do RT | B2: Capa | C2: TCC_Final_CCEE.tex | D2: <<nomeRt>> | E2: =IFERROR(IF(UC_DADOS!B28="","",UC_DADOS!B28),"") -> Luiz Carlos Alves Lima
A3: NOME DA UNIDADE CONSUMIDORA DA PMS | B3: Capa | C3: TCC_Final_CCEE.tex | D3: <<nomeUc>> | E3: =IFERROR(IF(UC_DADOS!B1="","",UC_DADOS!B1),"")
A4: Data | B4: Capa | C4: TCC_Final_CCEE.tex | D4: <<data>> | E4: =IFERROR(IF(UC_DADOS!B8="","",UC_DADOS!B8),"")
A5: Inserir Mome do RT | B5: Contra Capa | C5: TCC_Final_CCEE.tex | D5: <<nomeRt>> | E5: =IFERROR(IF(E2="","",E2),"") -> Luiz Carlos Alves Lima
A6: NOME DA UNIDADE CONSUMIDORA DA PMS | B6: Contra Capa | C6: TCC_Final_CCEE.tex | D6: <<nomeUc>> | E6: =IFERROR(IF(E3="","",E3),"")
A7: Nome da UC | B7: Contra Capa | C7: TCC_Final_CCEE.tex | D7: <<nomeUc>> | E7: =IFERROR(IF(E6="","",E6),"")
A8: Data | B8: Contra Capa | C8: TCC_Final_CCEE.tex | D8: <<data>> | E8: =IFERROR(IF(E4="","",E4),"")
A9: Nome da Unidade | B9: 6 | C9: capitulo1.tex | D9: <<nomeUc>> | E9: =IFERROR(IF(E3="","",E3),"")
A10: Código da UC | B10: 6 | C10: capitulo1.tex | D10: <<codigoUc>> | E10: =IFERROR(IF(UC_DADOS!B2="","",UC_DADOS!B2),"")
A11: Tipo de Atividade | B11: 6 | C11: capitulo1.tex | D11: <<tipoAtividade>> | E11: =IFERROR(IF(UC_DADOS!B3="","",UC_DADOS!B3),"")
A12: Endereço Completo | B12: 6 | C12: capitulo1.tex | D12: <<endereco>> | E12: =IFERROR(IF(UC_DADOS!B4="","",UC_DADOS!B4),"")
A13: Responsável / Cargo | B13: 6 | C13: capitulo1.tex | D13: <<responsavel>> | E13: =IFERROR(IF(UC_DADOS!B6="","",UC_DADOS!B6),"")
A14: Telefone para Contato | B14: 6 | C14: capitulo1.tex | D14: <<telefone>> | E14: =IFERROR(IF(UC_DADOS!B7="","",UC_DADOS!B7),"")
A15: E-mail Institucional | B15: 6 | C15: capitulo1.tex | D15: <<email>> | E15: =IFERROR(IF(UC_DADOS!B9="","",UC_DADOS!B9),"")
A16: Adcionar Localidade | B16: 8 | C16: capitulo3.tex | D16: <<localidade>> | E16: =IFERROR(IF(UC_DADOS!B5="","",UC_DADOS!B5),"")
A17: Iluminação / Medida Proposta | B17: 11 | C17: capitulo4.tex | D17: <<propIluminacao>> | E17: =IFERROR(IF(TABELAS_RESUMO!B12="","",TABELAS_RESUMO!B12),"") -> Substituição por LED e sensores
A18: Climatização / Medida Proposta | B18: 11 | C18: capitulo4.tex | D18: <<propClimatizacao>> | E18: =IFERROR(IF(TABELAS_RESUMO!B13="","",TABELAS_RESUMO!B13),"") -> Troca de aparelhos de ar-condicionado e automação
A19: Motores / Medida Proposta | B19: 11 | C19: capitulo4.tex | D19: <<propMotores>> | E19: =IFERROR(IF(TABELAS_RESUMO!B14="","",TABELAS_RESUMO!B14),"") -> Substituição por motores de alto rendimento
A20: Refrigeração / Medida Proposta | B20: 11 | C20: capitulo4.tex | D20: <<propRefrigeracao>> | E20: =IFERROR(IF(TABELAS_RESUMO!B15="","",TABELAS_RESUMO!B15),"") -> Troca de refrigeradores comerciais ineficientes
A21: Fotovoltaico / Medida Proposta | B21: 11 | C21: capitulo4.tex | D21: <<propFotovoltaico>> | E21: =IFERROR(IF(TABELAS_RESUMO!B16="","",TABELAS_RESUMO!B16),"") -> Sistema conectado à rede (GD)
A22: Iluminação / Economia (MWh/ano) | B22: 11 | C22: capitulo4.tex | D22: <<iluEconomia>> | E22: =IFERROR(IF(TABELAS_RESUMO!C12="","",TABELAS_RESUMO!C12),"")
A23: Climatização / Economia (MWh/ano) | B23: 11 | C23: capitulo4.tex | D23: <<cliEconomia>> | E23: =IFERROR(IF(TABELAS_RESUMO!C13="","",TABELAS_RESUMO!C13),"")
A24: Motores / Economia (MWh/ano) | B24: 11 | C24: capitulo4.tex | D24: <<motEconomia>> | E24: =IFERROR(IF(TABELAS_RESUMO!C14="","",TABELAS_RESUMO!C14),"")
A25: Refrigeração / Economia (MWh/ano) | B25: 11 | C25: capitulo4.tex | D25: <<refEconomia>> | E25: =IFERROR(IF(TABELAS_RESUMO!C15="","",TABELAS_RESUMO!C15),"")
A26: Fotovoltaico / Economia (MWh/ano) | B26: 11 | C26: capitulo4.tex | D26: <<fotEconomia>> | E26: =IFERROR(IF(TABELAS_RESUMO!C16="","",TABELAS_RESUMO!C16),"")
A27: Total / Economia (MWh/ano) | B27: 11 | C27: capitulo4.tex | D27: <<totEconomia>> | E27: =IFERROR(IF(TABELAS_RESUMO!C17="","",TABELAS_RESUMO!C17),"")
A28: Iluminação / Invest. Total (R$) | B28: 11 | C28: capitulo4.tex | D28: <<iluInvestimento>> | E28: =IFERROR(IF(TABELAS_RESUMO!D12="","",TABELAS_RESUMO!D12),"")
A29: Climatização / Invest. Total (R$) | B29: 11 | C29: capitulo4.tex | D29: <<cliInvestimento>> | E29: =IFERROR(IF(TABELAS_RESUMO!D13="","",TABELAS_RESUMO!D13),"")
A30: Motores / Invest. Total (R$) | B30: 11 | C30: capitulo4.tex | D30: <<motInvestimento>> | E30: =IFERROR(IF(TABELAS_RESUMO!D14="","",TABELAS_RESUMO!D14),"")
A31: Refrigeração / Invest. Total (R$) | B31: 11 | C31: capitulo4.tex | D31: <<refInvestimento>> | E31: =IFERROR(IF(TABELAS_RESUMO!D15="","",TABELAS_RESUMO!D15),"")
A32: Fotovoltaico / Invest. Total (R$) | B32: 11 | C32: capitulo4.tex | D32: <<fotInvestimento>> | E32: =IFERROR(IF(TABELAS_RESUMO!D16="","",TABELAS_RESUMO!D16),"")
A33: Total / Invest. Total (R$) | B33: 11 | C33: capitulo4.tex | D33: <<totInvestimento>> | E33: =IFERROR(IF(TABELAS_RESUMO!D17="","",TABELAS_RESUMO!D17),"")
A34: Iluminação / PB | B34: 11 | C34: capitulo4.tex | D34: <<iluPayBack>> | E34: =IFERROR(IF(TABELAS_RESUMO!E12="","",TABELAS_RESUMO!E12),"")
A35: Climatização / PB | B35: 11 | C35: capitulo4.tex | D35: <<cliPayBack>> | E35: =IFERROR(IF(TABELAS_RESUMO!E13="","",TABELAS_RESUMO!E13),"")
A36: Motores / PB | B36: 11 | C36: capitulo4.tex | D36: <<motPayBack>> | E36: =IFERROR(IF(TABELAS_RESUMO!E14="","",TABELAS_RESUMO!E14),"")
A37: Refrigeração / PB | B37: 11 | C37: capitulo4.tex | D37: <<refPayBack>> | E37: =IFERROR(IF(TABELAS_RESUMO!E15="","",TABELAS_RESUMO!E15),"")
A38: Fotovoltaico / PB | B38: 11 | C38: capitulo4.tex | D38: <<fotPayBack>> | E38: =IFERROR(IF(TABELAS_RESUMO!E16="","",TABELAS_RESUMO!E16),"")
A39: Total / PB | B39: 11 | C39: capitulo4.tex | D39: <<totPayBack>> | E39: =IFERROR(IF(TABELAS_RESUMO!E17="","",TABELAS_RESUMO!E17),"")
A40: Nome da Unidade | B40: 12 | C40: capitulo5.tex | D40: <<nomeUc>> | E40: =IFERROR(IF(E3="","",E3),"")
A41: Gurpo de Tensão | B41: 20 | C41: capitulo6.tex | D41: <<grupoTensao>> | E41: =IFERROR(IF(UC_DADOS!B29="","",UC_DADOS!B29),"")
A42: Modalidade tarifária | B42: 20 | C42: capitulo6.tex | D42: <<modalidadeTarifaria>> | E42: =IFERROR(IF(UC_DADOS!B18="","",UC_DADOS!B18),"")
A43: Demanda contratada | B43: 20 | C43: capitulo6.tex | D43: <<demandaContratada>> | E43: =IFERROR(IF(UC_DADOS!B19="","",UC_DADOS!B19),"")
A44: Número da instalação na distribuidora | B44: 20 | C44: capitulo6.tex | D44: <<codInstalacao>> | E44: =IFERROR(IF(UC_DADOS!B20="","",UC_DADOS!B20),"")
A45: Código da unidade consumidora | B45: 20 | C45: capitulo6.tex | D45: <<codigoUc>> | E45: =IFERROR(IF(UC_DADOS!B21="","",UC_DADOS!B21),"")
A46: Classe de consumo | B46: 20 | C46: capitulo6.tex | D46: <<classeConsumo>> | E46: =IFERROR(IF(UC_DADOS!B22="","",UC_DADOS!B22),"")
A47: Consumo/Iluminação kWh | B47: 21 | C47: capitulo6.tex | D47: <<consumoIluminacao>> | E47: =IFERROR(IF(CONSUMO_EQP!$C$2="","",CONSUMO_EQP!$C$2),"") | F47: Grafico 1
A48: Consumo/Climatização kWh | B48: 21 | C48: capitulo6.tex | D48: <<consumoClimatizacao>> | E48: =IFERROR(IF(CONSUMO_EQP!$C$3="","",CONSUMO_EQP!$C$3),"")
A49: Consumo/Sistema Motrizes kWh | B49: 21 | C49: capitulo6.tex | D49: <<consumoMotores>> | E49: =IFERROR(IF(CONSUMO_EQP!$C$4="","",CONSUMO_EQP!$C$4),"")
A50: Consumo/Refrigeração kWh | B50: 21 | C50: capitulo6.tex | D50: <<consumoRefrigeracao>> | E50: =IFERROR(IF(CONSUMO_EQP!$C$5="","",CONSUMO_EQP!$C$5),"")
A51: Consumo/Outros kWh | B51: 21 | C51: capitulo6.tex | D51: <<consumoOutros>> | E51: =IFERROR(IF(CONSUMO_EQP!$C$6="","",CONSUMO_EQP!$C$6),"")
A52: Consumo/Total kWh | B52: 21 | C52: capitulo6.tex | D52: <<consumoTotal>> | E52: =IFERROR(IF(CONSUMO_EQP!$C$7="","",CONSUMO_EQP!$C$7),"")
A53: Grafico Perfil de Consumo | B53: 21 | C53: capitulo6.tex | D53: Grafico 1.png | E53: Grafico 1
A54: Parâmetro | B54: 22 | C54: capitulo7.tex | D54: <<parametro>> | E54: =IFERROR(IF(UC_DADOS!A12="","",UC_DADOS!A12),"") -> Alunos
A55: Dado do Parâmetro | B55: 22 | C55: capitulo7.tex | D55: <<dadoParametro>> | E55: =IFERROR(IF(UC_DADOS!B12="","",UC_DADOS!B12),"")
A56: Consumo médio mensal | B56: 22 | C56: capitulo7.tex | D56: <<consMedio>> | E56: =IFERROR(IF(UC_DADOS!B13="","",UC_DADOS!B13),"")
A57: Consumo específico estimado | B57: 22 | C57: capitulo7.tex | D57: <<dadoConsEspecifico>> | E57: =IFERROR(IF(UC_DADOS!B14="","",UC_DADOS!B14),"")
A58: Grupo A ou B | B58: 23 | C58: capitulo8.tex | D58: <<grupoTensao>> | E58: =IFERROR(IF(UC_DADOS!B29="","",UC_DADOS!B29),"")
A59: Modalidade tarifária | B59: 23 | C59: capitulo8.tex | D59: <<modalidadeTarifaria>> | E59: =IFERROR(IF(E42="","",E42),"")
A60: Demanda contratada vigente | B60: 23 | C60: capitulo8.tex | D60: <<demandaContratada>> | E60: =IFERROR(IF(E43="","",E43),"")
A61: Primeiro mês analisado | B61: 23 | C61: capitulo8.tex | D61: <<mesInicial>> | E61: =IFERROR(IF(UC_DADOS!D37="","",UC_DADOS!D37),"")
A62: Ultimo mês analisado | B62: 23 | C62: capitulo8.tex | D62: <<mesFinal>> | E62: =IFERROR(IF(UC_DADOS!D48="","",UC_DADOS!D48),"")
A63: Distribuidora | B63: 23 | C63: capitulo8.tex | D63: <<distribuidora>> | E63: =IFERROR(IF(UC_DADOS!B33="","",UC_DADOS!B33),"") -> 0
A64: Preço da energia no ultimo mês | B64: 23 | C64: capitulo8.tex | D64: <<precoRecente>> | E64: =IFERROR(IF(UC_DADOS!B32="","",UC_DADOS!B32),"") -> 0
A65: Mês / Ano | B65: 23 | C65: capitulo8.tex | D65: <<mesUm>> | E65: =IFERROR(IF(UC_DADOS!D37="","",UC_DADOS!D37),"")
A66: Mês / Ano | B66: 23 | C66: capitulo8.tex | D66: <<mesDois>> | E66: =IFERROR(IF(UC_DADOS!D38="","",UC_DADOS!D38),"")
A67: Mês / Ano | B67: 23 | C67: capitulo8.tex | D67: <<mesTres>> | E67: =IFERROR(IF(UC_DADOS!D39="","",UC_DADOS!D39),"")
A68: Mês / Ano | B68: 23 | C68: capitulo8.tex | D68: <<mesQuatro>> | E68: =IFERROR(IF(UC_DADOS!D40="","",UC_DADOS!D40),"")
A69: Mês / Ano | B69: 23 | C69: capitulo8.tex | D69: <<mesCinco>> | E69: =IFERROR(IF(UC_DADOS!D41="","",UC_DADOS!D41),"")
A70: Mês / Ano | B70: 23 | C70: capitulo8.tex | D70: <<mesSeis>> | E70: =IFERROR(IF(UC_DADOS!D42="","",UC_DADOS!D42),"")
A71: Mês / Ano | B71: 23 | C71: capitulo8.tex | D71: <<mesSete>> | E71: =IFERROR(IF(UC_DADOS!D43="","",UC_DADOS!D43),"")
A72: Mês / Ano | B72: 23 | C72: capitulo8.tex | D72: <<mesOito>> | E72: =IFERROR(IF(UC_DADOS!D44="","",UC_DADOS!D44),"")
A73: Mês / Ano | B73: 23 | C73: capitulo8.tex | D73: <<mesNove>> | E73: =IFERROR(IF(UC_DADOS!D45="","",UC_DADOS!D45),"")
A74: Mês / Ano | B74: 23 | C74: capitulo8.tex | D74: <<mesDez>> | E74: =IFERROR(IF(UC_DADOS!D46="","",UC_DADOS!D46),"")
A75: Mês / Ano | B75: 23 | C75: capitulo8.tex | D75: <<mesOnze>> | E75: =IFERROR(IF(UC_DADOS!D47="","",UC_DADOS!D47),"")
A76: Mês / Ano | B76: 23 | C76: capitulo8.tex | D76: <<mesDoze>> | E76: =IFERROR(IF(UC_DADOS!D48="","",UC_DADOS!D48),"")
A77: Consumo Ponta 1 | B77: 23 | C77: capitulo8.tex | D77: <<ConsumoPontaUm>> | E77: =IFERROR(IF(UC_DADOS!E37="","",UC_DADOS!E37),"") -> 0 | F77: Grafico 3
A78: Consumo Ponta 2 | B78: 23 | C78: capitulo8.tex | D78: <<ConsumoPontaDois>> | E78: =IFERROR(IF(UC_DADOS!E38="","",UC_DADOS!E38),"") -> 0
A79: Consumo Ponta 3 | B79: 23 | C79: capitulo8.tex | D79: <<ConsumoPontaTres>> | E79: =IFERROR(IF(UC_DADOS!E39="","",UC_DADOS!E39),"") -> 0
A80: Consumo Ponta 4 | B80: 23 | C80: capitulo8.tex | D80: <<ConsumoPontaQuatro>> | E80: =IFERROR(IF(UC_DADOS!E40="","",UC_DADOS!E40),"") -> 0
A81: Consumo Ponta 5 | B81: 23 | C81: capitulo8.tex | D81: <<ConsumoPontaCinco>> | E81: =IFERROR(IF(UC_DADOS!E41="","",UC_DADOS!E41),"") -> 0
A82: Consumo Ponta 6 | B82: 23 | C82: capitulo8.tex | D82: <<ConsumoPontaSeis>> | E82: =IFERROR(IF(UC_DADOS!E42="","",UC_DADOS!E42),"") -> 0
A83: Consumo Ponta 7 | B83: 23 | C83: capitulo8.tex | D83: <<ConsumoPontaSete>> | E83: =IFERROR(IF(UC_DADOS!E43="","",UC_DADOS!E43),"") -> 0
A84: Consumo Ponta 8 | B84: 23 | C84: capitulo8.tex | D84: <<ConsumoPontaOito>> | E84: =IFERROR(IF(UC_DADOS!E44="","",UC_DADOS!E44),"") -> 0
A85: Consumo Ponta 9 | B85: 23 | C85: capitulo8.tex | D85: <<ConsumoPontaNove>> | E85: =IFERROR(IF(UC_DADOS!E45="","",UC_DADOS!E45),"") -> 0
A86: Consumo Ponta 10 | B86: 23 | C86: capitulo8.tex | D86: <<ConsumoPontaDez>> | E86: =IFERROR(IF(UC_DADOS!E46="","",UC_DADOS!E46),"") -> 0
A87: Consumo Ponta 11 | B87: 23 | C87: capitulo8.tex | D87: <<ConsumoPontaOnze>> | E87: =IFERROR(IF(UC_DADOS!E47="","",UC_DADOS!E47),"") -> 0
A88: Consumo Ponta 12 | B88: 23 | C88: capitulo8.tex | D88: <<ConsumoPontaDoze>> | E88: =IFERROR(IF(UC_DADOS!E48="","",UC_DADOS!E48),"") -> 0
A89: Consumo Fora Ponta 1 | B89: 23 | C89: capitulo8.tex | D89: <<ConsumoForaPontaUm>> | E89: =IFERROR(IF(UC_DADOS!F37="","",UC_DADOS!F37),"") -> 0
A90: Consumo Fora Ponta 2 | B90: 23 | C90: capitulo8.tex | D90: <<ConsumoForaPontaDois>> | E90: =IFERROR(IF(UC_DADOS!F38="","",UC_DADOS!F38),"") -> 0
A91: Consumo Fora Ponta 3 | B91: 23 | C91: capitulo8.tex | D91: <<ConsumoForaPontaTres>> | E91: =IFERROR(IF(UC_DADOS!F39="","",UC_DADOS!F39),"") -> 0
A92: Consumo Fora Ponta 4 | B92: 23 | C92: capitulo8.tex | D92: <<ConsumoForaPontaQuatro>> | E92: =IFERROR(IF(UC_DADOS!F40="","",UC_DADOS!F40),"") -> 0
A93: Consumo Fora Ponta 5 | B93: 23 | C93: capitulo8.tex | D93: <<ConsumoForaPontaCinco>> | E93: =IFERROR(IF(UC_DADOS!F41="","",UC_DADOS!F41),"") -> 0
A94: Consumo Fora Ponta 6 | B94: 23 | C94: capitulo8.tex | D94: <<ConsumoForaPontaSeis>> | E94: =IFERROR(IF(UC_DADOS!F42="","",UC_DADOS!F42),"") -> 0
A95: Consumo Fora Ponta 7 | B95: 23 | C95: capitulo8.tex | D95: <<ConsumoForaPontaSete>> | E95: =IFERROR(IF(UC_DADOS!F43="","",UC_DADOS!F43),"") -> 0
A96: Consumo Fora Ponta 8 | B96: 23 | C96: capitulo8.tex | D96: <<ConsumoForaPontaOito>> | E96: =IFERROR(IF(UC_DADOS!F44="","",UC_DADOS!F44),"") -> 0
A97: Consumo Fora Ponta 9 | B97: 23 | C97: capitulo8.tex | D97: <<ConsumoForaPontaNove>> | E97: =IFERROR(IF(UC_DADOS!F45="","",UC_DADOS!F45),"") -> 0
A98: Consumo Fora Ponta 10 | B98: 23 | C98: capitulo8.tex | D98: <<ConsumoForaPontaDez>> | E98: =IFERROR(IF(UC_DADOS!F46="","",UC_DADOS!F46),"") -> 0
A99: Consumo Fora Ponta 11 | B99: 23 | C99: capitulo8.tex | D99: <<ConsumoForaPontaOnze>> | E99: =IFERROR(IF(UC_DADOS!F47="","",UC_DADOS!F47),"") -> 0
A100: Consumo Fora Ponta 12 | B100: 23 | C100: capitulo8.tex | D100: <<ConsumoForaPontaDoze>> | E100: =IFERROR(IF(UC_DADOS!F48="","",UC_DADOS!F48),"") -> 0
...

Sheet UC_DADOS
A1: Nome da Unidade | B1: =_xlfn.XLOOKUP(MAX(FATURAS!M:M), FATURAS!M:M, FATURAS!F:F,,-1) -> #N/A
A2: Código da UC | B2: =_xlfn.XLOOKUP(MAX(FATURAS!M:M), FATURAS!M:M, FATURAS!AA:AA,,-1) -> #N/A
A3: Tipo de Atividade
A4: Endereço Completo
A5: Localidade
A6: Responsável / Cargo
A7: Telefone para Contato
A8: Data
A9: E-mail institucional
A12: Alunos
A13: Consumo médio mensal (kWh/mês) | B13: =AVERAGE(FATURAS!AF:AF) -> #DIV/0!
A14: Consumo específico estimado | B14: =(B13/B12) -> #DIV/0!
A15: Consumo específico Típico | B15: =IF(A12="Alunos","4 a 8 kWh/Alunos/mês",IF(A12="Pacientes","10 a 18 kWh/Pacientes/mês",IF(A12="Leitos","250 a 400 kWh/Leito/mês",IF(A12="Funcionários","8 a 12 kWh/Funcionários/mês",IF(A12="Visitantes","3 a 7 kWh/Visitantes/mês",""))))) -> 4 a 8 kWh/Alunos/mês
A16: Tipo de Edificação | B16: =IF(A12="Alunos","Escola pública (fundamental)",IF(A12="Pacientes","Unidade básica de saúde",IF(A12="Leitos","Hospital de médio porte",IF(A12="Funcionários","Prédio administrativo",IF(A12="Visitantes","Unidade esportiva / ginásio",""))))) -> Escola pública (fundamental)
A18: Modalidade tarifária | B18: =_xlfn.TEXTBEFORE(_xlfn.XLOOKUP(MAX(FATURAS!M:M),FATURAS!M:M,FATURAS!Y:Y,,-1)," ",3) -> #N/A
A19: Demanda contratada | B19: =IF(ISNUMBER(_xlfn.XLOOKUP(MAX(FATURAS!M:M),FATURAS!M:M,FATURAS!U:U,,-1)),_xlfn.XLOOKUP(MAX(FATURAS!M:M),FATURAS!M:M,FATURAS!U:U,,-1),_xlfn.XLOOKUP(MAX(FATURAS!M:M),FATURAS!M:M,FATURAS!V:V,,-1)&" NP e "&_xlfn.XLOOKUP(MAX(FATURAS!M:M),FATURAS!M:M,FATURAS!W:W,,-1)&" FP") -> #N/A
A20: Número da instalação na distribuidora | B20: =_xlfn.XLOOKUP(MAX(FATURAS!M:M),FATURAS!M:M,FATURAS!AB:AB) -> #N/A
A21: Código da unidade consumidora | B21: =B2 -> #N/A
A22: Classe de consumo | B22: =_xlfn.TEXTAFTER(_xlfn.XLOOKUP(MAX(FATURAS!M:M),FATURAS!M:M,FATURAS!Y:Y,,-1)," ",3) -> #N/A
A28: Resnposável Técnico | B28: Luiz Carlos Alves Lima
A29: Grupo | B29: =IF(LEFT(FATURAS!X2,1)="A","Grupo A",IF(LEFT(FATURAS!X2,1)="B","Grupo B",""))
A32: Preço da Energia do Ultimo Mês | B32: =SUMIF(FATURAS!M:M,MAX(FATURAS!M:M),FATURAS!E:E) -> 0
A33: Distribuidora de Energia | B33: =FATURAS!J2 -> 0
A34: Maior Consumo Registrado (kWh) | B34: =MAX(G37:G48) -> 0
A35: Mês/Ano do Maior Consumo | B35: =INDEX(D37:D48,MATCH(MAX(G37:G48),G37:G48,0))
A36: Mês/Ano do Menor Consumo | B36: =INDEX(D37:D48,MATCH(MIN(G37:G48),G37:G48,0)) | D36: Mês / Ano | E36: Consumo Ponta (kWh) | F36: Consumo Fora Ponta (kWh) | G36: Consumo Total (kW) | H36: Demanda Ponta (kW) | I36: Demanda Fora Ponta (kW) | J36: Despesa C/ Energia
A37: Custo anual de energia elétrica (R$) | B37: =SUMIFS(FATURAS!E:E,FATURAS!M:M,">="&DATE(YEAR(TODAY()),1,1),FATURAS!M:M,"<="&DATE(YEAR(TODAY()),12,31)) -> 0 | D37: =IFERROR(TEXT(SMALL(_xlfn.UNIQUE(FATURAS!M:M),1),"MMM/AA"),"") | E37: =SUMIFS(FATURAS!AQ:AQ, FATURAS!M:M, SMALL(_xlfn.UNIQUE(FATURAS!M:M),1)) -> 0 | F37: =SUMIFS(FATURAS!AR:AR, FATURAS!M:M, SMALL(_xlfn.UNIQUE(FATURAS!M:M),1)) -> 0 | G37: =SUM(E37+F37) -> 0 | H37: {=SUMPRODUCT( (FATURAS!M2:M5000=SMALL(_xlfn.UNIQUE(FATURAS!M2:M5000),1))* FATURAS!AU2:AU5000* IF(ISNUMBER(FATURAS!BN2:BN5000),1+(FATURAS!BN2:BN5000/100),1))} -> #NUM! | I37: {=SUMPRODUCT((FATURAS!M2:M5000=SMALL(_xlfn.UNIQUE(FATURAS!M2:M5000),1))*FATURAS!AV2:AV5000*IF(ISNUMBER(FATURAS!BN2:BN5000),1+(FATURAS!BN2:BN5000/100),1))} -> #NUM! | J37: =SUMIFS(FATURAS!E:E, FATURAS!M:M, SMALL(_xlfn.UNIQUE(FATURAS!M:M),1)) -> 0
A38: Fator de carga médio estimado | B38: {=IFERROR(SUMPRODUCT(IFERROR(FATURAS!AD2:AD13/(FATURAS!AV2:AV13*FATURAS!Q2:Q13*24),0))/SUMPRODUCT((FATURAS!AV2:AV13<>0)*(FATURAS!Q2:Q13<>0)),0)} -> 0 | D38: =IFERROR(TEXT(SMALL(_xlfn.UNIQUE(FATURAS!M:M),2),"MMM/AA"),"") | E38: =SUMIFS(FATURAS!AQ:AQ, FATURAS!M:M, SMALL(_xlfn.UNIQUE(FATURAS!M:M),2)) -> 0 | F38: =SUMIFS(FATURAS!AR:AR, FATURAS!M:M, SMALL(_xlfn.UNIQUE(FATURAS!M:M),2)) -> 0 | G38: =SUM(E38+F38) -> 0 | H38: {=SUMPRODUCT( (FATURAS!M2:M5000=SMALL(_xlfn.UNIQUE(FATURAS!M2:M5000),2))* FATURAS!AU2:AU5000* IF(ISNUMBER(FATURAS!BN2:BN5000),1+(FATURAS!BN2:BN5000/100),1))} -> #NUM! | I38: {=SUMPRODUCT((FATURAS!M2:M5000=SMALL(_xlfn.UNIQUE(FATURAS!M2:M5000),2))*FATURAS!AV2:AV5000*IF(ISNUMBER(FATURAS!BN2:BN5000),1+(FATURAS!BN2:BN5000/100),1))} -> #NUM! | J38: =SUMIFS(FATURAS!E:E, FATURAS!M:M, SMALL(_xlfn.UNIQUE(FATURAS!M:M),2)) -> 0
A39: Faturas Disponíveis | B39: Todas as faturas disponíveis no histórico de análise dos últimos 12 meses. | D39: =IFERROR(TEXT(SMALL(_xlfn.UNIQUE(FATURAS!M:M),3),"MMM/AA"),"") | E39: =SUMIFS(FATURAS!AQ:AQ, FATURAS!M:M, SMALL(_xlfn.UNIQUE(FATURAS!M:M),3)) -> 0 | F39: =SUMIFS(FATURAS!AR:AR, FATURAS!M:M, SMALL(_xlfn.UNIQUE(FATURAS!M:M),3)) -> 0 | G39: =SUM(E39+F39) -> 0 | H39: {=SUMPRODUCT( (FATURAS!M2:M5000=SMALL(_xlfn.UNIQUE(FATURAS!M2:M5000),3))* FATURAS!AU2:AU5000* IF(ISNUMBER(FATURAS!BN2:BN5000),1+(FATURAS!BN2:BN5000/100),1))} -> #NUM! | I39: {=SUMPRODUCT((FATURAS!M2:M5000=SMALL(_xlfn.UNIQUE(FATURAS!M2:M5000),3))*FATURAS!AV2:AV5000*IF(ISNUMBER(FATURAS!BN2:BN5000),1+(FATURAS!BN2:BN5000/100),1))} -> #NUM! | J39: =SUMIFS(FATURAS!E:E, FATURAS!M:M, SMALL(_xlfn.UNIQUE(FATURAS!M:M),3)) -> 0
A40: Fator de carga Ponta | B40: =AVERAGEIFS(FATURAS!BL:BL,FATURAS!M:M,">="&DATE(YEAR(TODAY()),1,1),FATURAS!M:M,"<="&DATE(YEAR(TODAY()),12,31)) -> #DIV/0! | D40: =IFERROR(TEXT(SMALL(_xlfn.UNIQUE(FATURAS!M:M),4),"MMM/AA"),"") | E40: =SUMIFS(FATURAS!AQ:AQ, FATURAS!M:M, SMALL(_xlfn.UNIQUE(FATURAS!M:M),4)) -> 0 | F40: =SUMIFS(FATURAS!AR:AR, FATURAS!M:M, SMALL(_xlfn.UNIQUE(FATURAS!M:M),4)) -> 0 | G40: =SUM(E40+F40) -> 0 | H40: {=SUMPRODUCT( (FATURAS!M2:M5000=SMALL(_xlfn.UNIQUE(FATURAS!M2:M5000),4))* FATURAS!AU2:AU5000* IF(ISNUMBER(FATURAS!BN2:BN5000),1+(FATURAS!BN2:BN5000/100),1))} -> #NUM! | I40: {=SUMPRODUCT((FATURAS!M2:M5000=SMALL(_xlfn.UNIQUE(FATURAS!M2:M5000),4))*FATURAS!AV2:AV5000*IF(ISNUMBER(FATURAS!BN2:BN5000),1+(FATURAS!BN2:BN5000/100),1))} -> #NUM! | J40: =SUMIFS(FATURAS!E:E, FATURAS!M:M, SMALL(_xlfn.UNIQUE(FATURAS!M:M),4)) -> 0
A41: Fator de carga Fora Ponta | B41: =AVERAGEIFS(FATURAS!BM:BM,FATURAS!M:M,">="&DATE(YEAR(TODAY()),1,1),FATURAS!M:M,"<="&DATE(YEAR(TODAY()),12,31)) -> #DIV/0! | D41: =IFERROR(TEXT(SMALL(_xlfn.UNIQUE(FATURAS!M:M),5),"MMM/AA"),"") | E41: =SUMIFS(FATURAS!AQ:AQ, FATURAS!M:M, SMALL(_xlfn.UNIQUE(FATURAS!M:M),5)) -> 0 | F41: =SUMIFS(FATURAS!AR:AR, FATURAS!M:M, SMALL(_xlfn.UNIQUE(FATURAS!M:M),5)) -> 0 | G41: =SUM(E41+F41) -> 0 | H41: {=SUMPRODUCT( (FATURAS!M2:M5000=SMALL(_xlfn.UNIQUE(FATURAS!M2:M5000),5))* FATURAS!AU2:AU5000* IF(ISNUMBER(FATURAS!BN2:BN5000),1+(FATURAS!BN2:BN5000/100),1))} -> #NUM! | I41: {=SUMPRODUCT((FATURAS!M2:M5000=SMALL(_xlfn.UNIQUE(FATURAS!M2:M5000),5))*FATURAS!AV2:AV5000*IF(ISNUMBER(FATURAS!BN2:BN5000),1+(FATURAS!BN2:BN5000/100),1))} -> #NUM! | J41: =SUMIFS(FATURAS!E:E, FATURAS!M:M, SMALL(_xlfn.UNIQUE(FATURAS!M:M),5)) -> 0
A42: Fator de Potencia | B42: {=SUMPRODUCT((YEAR(FATURAS!M2:M13)=YEAR(TODAY()))*FATURAS!AD2:AD13)/SQRT(SUMPRODUCT((YEAR(FATURAS!M2:M13)=YEAR(TODAY()))*FATURAS!AD2:AD13)^2+SUMPRODUCT((YEAR(FATURAS!M2:M13)=YEAR(TODAY()))*FATURAS!BC2:BC13)^2)} -> #DIV/0! | D42: =IFERROR(TEXT(SMALL(_xlfn.UNIQUE(FATURAS!M:M),6),"MMM/AA"),"") | E42: =SUMIFS(FATURAS!AQ:AQ, FATURAS!M:M, SMALL(_xlfn.UNIQUE(FATURAS!M:M),6)) -> 0 | F42: =SUMIFS(FATURAS!AR:AR, FATURAS!M:M, SMALL(_xlfn.UNIQUE(FATURAS!M:M),6)) -> 0 | G42: =SUM(E42+F42) -> 0 | H42: {=SUMPRODUCT( (FATURAS!M2:M5000=SMALL(_xlfn.UNIQUE(FATURAS!M2:M5000),6))* FATURAS!AU2:AU5000* IF(ISNUMBER(FATURAS!BN2:BN5000),1+(FATURAS!BN2:BN5000/100),1))} -> #NUM! | I42: {=SUMPRODUCT((FATURAS!M2:M5000=SMALL(_xlfn.UNIQUE(FATURAS!M2:M5000),6))*FATURAS!AV2:AV5000*IF(ISNUMBER(FATURAS!BN2:BN5000),1+(FATURAS!BN2:BN5000/100),1))} -> #NUM! | J42: =SUMIFS(FATURAS!E:E, FATURAS!M:M, SMALL(_xlfn.UNIQUE(FATURAS!M:M),6)) -> 0
A43: Custo Médio Unitário (R$/kWh) | B43: {=SUMPRODUCT((YEAR(FATURAS!M2:M13)=YEAR(TODAY()))*FATURAS!AF2:AF13)/SUMPRODUCT((YEAR(FATURAS!M2:M13)=YEAR(TODAY()))*FATURAS!E2:E13)} -> #DIV/0! | D43: =IFERROR(TEXT(SMALL(_xlfn.UNIQUE(FATURAS!M:M),7),"MMM/AA"),"") | E43: =SUMIFS(FATURAS!AQ:AQ, FATURAS!M:M, SMALL(_xlfn.UNIQUE(FATURAS!M:M),7)) -> 0 | F43: =SUMIFS(FATURAS!AR:AR, FATURAS!M:M, SMALL(_xlfn.UNIQUE(FATURAS!M:M),7)) -> 0 | G43: =SUM(E43+F43) -> 0 | H43: {=SUMPRODUCT( (FATURAS!M2:M5000=SMALL(_xlfn.UNIQUE(FATURAS!M2:M5000),7))* FATURAS!AU2:AU5000* IF(ISNUMBER(FATURAS!BN2:BN5000),1+(FATURAS!BN2:BN5000/100),1))} -> #NUM! | I43: {=SUMPRODUCT((FATURAS!M2:M5000=SMALL(_xlfn.UNIQUE(FATURAS!M2:M5000),7))*FATURAS!AV2:AV5000*IF(ISNUMBER(FATURAS!BN2:BN5000),1+(FATURAS!BN2:BN5000/100),1))} -> #NUM! | J43: =SUMIFS(FATURAS!E:E, FATURAS!M:M, SMALL(_xlfn.UNIQUE(FATURAS!M:M),7)) -> 0
A44: ="Consumo por " & A12 & " (kWh/mês)" -> Consumo por Alunos (kWh/mês) | B44: {=SUMPRODUCT((YEAR(FATURAS!M2:M13)=YEAR(TODAY()))*FATURAS!AD2:AD13)/(12*B12)} -> #DIV/0! | D44: =IFERROR(TEXT(SMALL(_xlfn.UNIQUE(FATURAS!M:M),8),"MMM/AA"),"") | E44: =SUMIFS(FATURAS!AQ:AQ, FATURAS!M:M, SMALL(_xlfn.UNIQUE(FATURAS!M:M),8)) -> 0 | F44: =SUMIFS(FATURAS!AR:AR, FATURAS!M:M, SMALL(_xlfn.UNIQUE(FATURAS!M:M),8)) -> 0 | G44: =SUM(E44+F44) -> 0 | H44: {=SUMPRODUCT( (FATURAS!M2:M5000=SMALL(_xlfn.UNIQUE(FATURAS!M2:M5000),8))* FATURAS!AU2:AU5000* IF(ISNUMBER(FATURAS!BN2:BN5000),1+(FATURAS!BN2:BN5000/100),1))} -> #NUM! | I44: {=SUMPRODUCT((FATURAS!M2:M5000=SMALL(_xlfn.UNIQUE(FATURAS!M2:M5000),8))*FATURAS!AV2:AV5000*IF(ISNUMBER(FATURAS!BN2:BN5000),1+(FATURAS!BN2:BN5000/100),1))} -> #NUM! | J44: =SUMIFS(FATURAS!E:E, FATURAS!M:M, SMALL(_xlfn.UNIQUE(FATURAS!M:M),8)) -> 0
D45: =IFERROR(TEXT(SMALL(_xlfn.UNIQUE(FATURAS!M:M),9),"MMM/AA"),"") | E45: =SUMIFS(FATURAS!AQ:AQ, FATURAS!M:M, SMALL(_xlfn.UNIQUE(FATURAS!M:M),9)) -> 0 | F45: =SUMIFS(FATURAS!AR:AR, FATURAS!M:M, SMALL(_xlfn.UNIQUE(FATURAS!M:M),9)) -> 0 | G45: =SUM(E45+F45) -> 0 | H45: {=SUMPRODUCT( (FATURAS!M2:M5000=SMALL(_xlfn.UNIQUE(FATURAS!M2:M5000),9))* FATURAS!AU2:AU5000* IF(ISNUMBER(FATURAS!BN2:BN5000),1+(FATURAS!BN2:BN5000/100),1))} -> #NUM! | I45: {=SUMPRODUCT((FATURAS!M2:M5000=SMALL(_xlfn.UNIQUE(FATURAS!M2:M5000),9))*FATURAS!AV2:AV5000*IF(ISNUMBER(FATURAS!BN2:BN5000),1+(FATURAS!BN2:BN5000/100),1))} -> #NUM! | J45: =SUMIFS(FATURAS!E:E, FATURAS!M:M, SMALL(_xlfn.UNIQUE(FATURAS!M:M),9)) -> 0
D46: =IFERROR(TEXT(SMALL(_xlfn.UNIQUE(FATURAS!M:M),10),"MMM/AA"),"") | E46: =SUMIFS(FATURAS!AQ:AQ, FATURAS!M:M, SMALL(_xlfn.UNIQUE(FATURAS!M:M),10)) -> 0 | F46: =SUMIFS(FATURAS!AR:AR, FATURAS!M:M, SMALL(_xlfn.UNIQUE(FATURAS!M:M),10)) -> 0 | G46: =SUM(E46+F46) -> 0 | H46: {=SUMPRODUCT( (FATURAS!M2:M5000=SMALL(_xlfn.UNIQUE(FATURAS!M2:M5000),10))* FATURAS!AU2:AU5000* IF(ISNUMBER(FATURAS!BN2:BN5000),1+(FATURAS!BN2:BN5000/100),1))} -> #NUM! | I46: {=SUMPRODUCT((FATURAS!M2:M5000=SMALL(_xlfn.UNIQUE(FATURAS!M2:M5000),10))*FATURAS!AV2:AV5000*IF(ISNUMBER(FATURAS!BN2:BN5000),1+(FATURAS!BN2:BN5000/100),1))} -> #NUM! | J46: =SUMIFS(FATURAS!E:E, FATURAS!M:M, SMALL(_xlfn.UNIQUE(FATURAS!M:M),10)) -> 0
D47: =IFERROR(TEXT(SMALL(_xlfn.UNIQUE(FATURAS!M:M),11),"MMM/AA"),"") | E47: =SUMIFS(FATURAS!AQ:AQ, FATURAS!M:M, SMALL(_xlfn.UNIQUE(FATURAS!M:M),11)) -> 0 | F47: =SUMIFS(FATURAS!AR:AR, FATURAS!M:M, SMALL(_xlfn.UNIQUE(FATURAS!M:M),11)) -> 0 | G47: =SUM(E47+F47) -> 0 | H47: {=SUMPRODUCT( (FATURAS!M2:M5000=SMALL(_xlfn.UNIQUE(FATURAS!M2:M5000),11))* FATURAS!AU2:AU5000* IF(ISNUMBER(FATURAS!BN2:BN5000),1+(FATURAS!BN2:BN5000/100),1))} -> #NUM! | I47: {=SUMPRODUCT((FATURAS!M2:M5000=SMALL(_xlfn.UNIQUE(FATURAS!M2:M5000),11))*FATURAS!AV2:AV5000*IF(ISNUMBER(FATURAS!BN2:BN5000),1+(FATURAS!BN2:BN5000/100),1))} -> #NUM! | J47: =SUMIFS(FATURAS!E:E, FATURAS!M:M, SMALL(_xlfn.UNIQUE(FATURAS!M:M),11)) -> 0
D48: =IFERROR(TEXT(SMALL(_xlfn.UNIQUE(FATURAS!M:M),12),"MMM/AA"),"") | E48: =SUMIFS(FATURAS!AQ:AQ, FATURAS!M:M, SMALL(_xlfn.UNIQUE(FATURAS!M:M),12)) -> 0 | F48: =SUMIFS(FATURAS!AR:AR, FATURAS!M:M, SMALL(_xlfn.UNIQUE(FATURAS!M:M),12)) -> 0 | G48: =SUM(E48+F48) -> 0 | H48: {=SUMPRODUCT( (FATURAS!M2:M5000=SMALL(_xlfn.UNIQUE(FATURAS!M2:M5000),12))* FATURAS!AU2:AU5000* IF(ISNUMBER(FATURAS!BN2:BN5000),1+(FATURAS!BN2:BN5000/100),1))} -> #NUM! | I48: {=SUMPRODUCT((FATURAS!M2:M5000=SMALL(_xlfn.UNIQUE(FATURAS!M2:M5000),12))*FATURAS!AV2:AV5000*IF(ISNUMBER(FATURAS!BN2:BN5000),1+(FATURAS!BN2:BN5000/100),1))} -> #NUM! | J48: =SUMIFS(FATURAS!E:E, FATURAS!M:M, SMALL(_xlfn.UNIQUE(FATURAS!M:M),12)) -> 0
D49: TOTAIS | G49: =SUM(G37:G48) -> 0
G50: =G49/1000 -> 0

Sheet FATURAS
A1: id_fatura | B1: status_pagamento | C1: status_leitura | D1: nome_empresa_cliente | E1: valor_total_em_reais | F1: nome_uc | G1: tipo_uc | H1: nome_grupo_uc | I1: tipo_instalacao | J1: nome_distribuidora_energia | K1: data_emissao | L1: data_vencimento | M1: periodo_referencia | N1: proxima_leitura_fatura | O1: leitura_atual_fatura | P1: ultima_leitura_fatura | Q1: numero_dias | R1: consumo_minimo | S1: id_ultima_fatura | T1: periodo_referencia_ultima_fatura | U1: demanda_contratada | V1: demanda_contratada_ponta | W1: demanda_contratada_fora_ponta | X1: nome_classe | Y1: descricao_classe | Z1: tipo_fornecimento | AA1: codigo_cliente | AB1: codigo_instalacao | AC1: consumo_total | AD1: consumo_total_com_perda_transformacao | AE1: consumo_compensado_total | AF1: consumo_faturado_total | AG1: energia_total_injetada | AH1: consumo_ponta | AI1: consumo_ponta_com_perda_transformacao | AJ1: consumo_fora_ponta | AK1: consumo_fora_ponta_com_perda_transformacao | AL1: consumo_intermediario | AM1: consumo_intermediario_com_perda_transformacao | AN1: consumo_compensado_ponta | AO1: consumo_compensado_fora_ponta | AP1: consumo_compensado_intermediário | AQ1: consumo_faturado_ponta | AR1: consumo_faturado_fora_ponta | AS1: consumo_faturado_intermediario | AT1: demanda_maxima | AU1: demanda_maxima_ponta | AV1: demanda_maxima_fora_ponta | AW1: demanda_de_ultrapassagem | AX1: demanda_de_ultrapassagem_ponta | AY1: demanda_de_ultrapassagem_fora_ponta | AZ1: demanda_faturada | BA1: demanda_faturada_ponta | BB1: demanda_faturada_fora_ponta | BC1: consumo_reativo_total | BD1: consumo_reativo_ponta | BE1: consumo_reativo_fora_ponta | BF1: consumo_reativo_excedente_total | BG1: consumo_reativo_excedente_ponta | BH1: consumo_reativo_excedente_fora_ponta | BI1: demanda_reativa_excedente | BJ1: demanda_reativa_excedente_ponta | BK1: demanda_reativa_excedente_fora_ponta | BL1: fator_carga_ponta | BM1: fator_carga_fora_ponta | BN1: percentual_perda_transformacao | BO1: creditos_acumulados_anterior | BP1: creditos_acumulados | BQ1: movimentacao_creditos_mes | BR1: tarifa_consumo_ponta | BS1: tarifa_consumo_fora_ponta | BT1: tarifa_consumo_intermediario | BU1: tarifa_consumo_convencional | BV1: tarifa_demanda_maxima | BW1: tarifa_demanda_de_ultrapassagem | BX1: tarifa_demanda_de_ultrapassagem_ponta | BY1: tarifa_demanda_de_ultrapassagem_fora_ponta | BZ1: tarifa_demanda_maxima_ponta | CA1: tarifa_demanda_maxima_fora_ponta | CB1: tarifa_consumo_reativo_excedente | CC1: tarifa_demanda_reativa_excedente | CD1: tarifa_calculada_demanda_ultrapassada | CE1: tarifa_calculada_demanda_de_ultrapassagem_ponta | CF1: tarifa_calculada_demanda_de_ultrapassagem_fora_ponta | CG1: tarifa_efetiva_de_consumo | CH1: valor_total_icms | CI1: base_calculo_icms | CJ1: aliquota_icms | CK1: valor_total_pis | CL1: base_calculo_pis | CM1: aliquota_pis | CN1: valor_total_cofins | CO1: base_calculo_cofins | CP1: aliquota_cofins | CQ1: numero_nota_fiscal | CR1: url_nota_fiscal | CS1: chave_acesso_nota_fiscal | CT1: arquivo_anexo | CU1: potencial_de_economia_mensal | CV1: potencial_de_economia_anual | CW1: potencial_de_economia_12_meses

Sheet Sistemas de Cond. Ambiental
A1: UNIDADE CONSUMIDORA | D1: SITUAÇÃO ATUAL | V1: SISTEMA PROPOSTO | AN1: RESULTADOS ESPERADOS | AQ1: RESULTADO AUTOMAÇÃO (10%) | AR1: AUTOMAÇÃO + TROCA DE EQUIPAMENTO
A2: Unidade consumidora (Número da conta contrato) | B2: Pavimento | C2: Ambiente | D2: Descrição do sistema | E2: Tipo de equipamento / tecnologia | F2: Classificação Inmetro | G2: Potência nominal de refrigeração (BTU/h) | H2: Coefiente de eficiência energética (W/W) | I2: Quantidade | J2: Potência instalada (kW) | K2: Fator de utilização | L2: Potência média utilizada (kW) | M2: Funcionamento (h/dia) | N2: Funcionamento (h/ano) | O2: Meses no ano, de utilização do Sistema | P2: Dias no mês, de utilização do Sistema | Q2: Dias úteis no mês, de utilização do Sistema | R2: Horas por dia, de utilização do Sistema no horário de Ponta (horas) | S2: Fator de coincidência na ponta | T2: Energia consumida (MWh/ano) | U2: Demanda média na ponta (kW) | V2: Tipo de equipamento / tecnologia | W2: Classificação Inmetro | X2: Potência nominal de refrigeração (BTU/h) | Y2: Coefiente de eficiência energética (W/W) | Z2: Preço Unitário (R$) | AA2: Quantidade | AB2: Potência instalada (kW) | AC2: Fator de utilização | AD2: Potência média utilizada (kW) | AE2: Funcionamento (h/dia) | AF2: Funcionamento (h/ano) | AG2: Meses no ano, de utilização do Sistema no horário de Ponta (meses) | AH2: Dias úteis no mês, de utilização do Sistema no horário de Ponta (dia) | AI2: Horas por dia, de utilização do Sistema no horário de Ponta (horas) | AJ2: Fator de coincidência na ponta | AK2: Energia consumida (MWh/ano) | AL2: Demanda média na ponta (kW) | AM2: Redução de demanda na ponta (kW) | AN2: Energia economizada (MWh/ano) | AO2: Investimento (R$) | AP2: Redução de consumo proposto em relação ao consumo total da UC (%) | AQ2: Energia economizada (MWh/ano) | AR2: Energia economizada (MWh/ano)
A3: =IF(UC_DADOS!$B$2=0,"",UC_DADOS!$B$2) -> #N/A | J3: =IF(H3=0,0,((G3*0.293*I3)/(1000*H3))) -> 0 | K3: 0.7 | L3: =J3*K3 -> 0 | N3: =M3*O3*P3 -> 0 | Q3: 21.25 | S3: =O3*Q3*R3/765 -> 0 | T3: =N3*L3/1000 -> 0 | U3: =S3*L3 -> 0 | V3: {=IF(F3="A",E3,IFERROR(INDEX('EQUIPAMENTOS_EFICIENTES (BDD)'!G:G,MATCH(1,('EQUIPAMENTOS_EFICIENTES (BDD)'!G:G=E3)*('EQUIPAMENTOS_EFICIENTES (BDD)'!I:I=_xlfn.MINIFS('EQUIPAMENTOS_EFICIENTES (BDD)'!I:I,'EQUIPAMENTOS_EFICIENTES (BDD)'!G:G,E3,'EQUIPAMENTOS_EFICIENTES (BDD)'!I:I,">="&G3)),0)),"Substituição não encontrada"))} -> 0 | W3: {=IF(F3="A",F3,IFERROR(INDEX('EQUIPAMENTOS_EFICIENTES (BDD)'!H:H,MATCH(1,('EQUIPAMENTOS_EFICIENTES (BDD)'!G:G=E3)*('EQUIPAMENTOS_EFICIENTES (BDD)'!I:I=_xlfn.MINIFS('EQUIPAMENTOS_EFICIENTES (BDD)'!I:I,'EQUIPAMENTOS_EFICIENTES (BDD)'!G:G,E3,'EQUIPAMENTOS_EFICIENTES (BDD)'!I:I,">="&G3)),0)),"Substituição não encontrada"))} -> 0 | X3: {=IF(F3="A",G3,IFERROR(INDEX('EQUIPAMENTOS_EFICIENTES (BDD)'!I:I,MATCH(1,('EQUIPAMENTOS_EFICIENTES (BDD)'!G:G=E3)*('EQUIPAMENTOS_EFICIENTES (BDD)'!I:I=_xlfn.MINIFS('EQUIPAMENTOS_EFICIENTES (BDD)'!I:I,'EQUIPAMENTOS_EFICIENTES (BDD)'!G:G,E3,'EQUIPAMENTOS_EFICIENTES (BDD)'!I:I,">="&G3)),0)),"Substituição não encontrada"))} -> 0 | Y3: {=IF(F3="A",H3,IFERROR(INDEX('EQUIPAMENTOS_EFICIENTES (BDD)'!J:J,MATCH(1,('EQUIPAMENTOS_EFICIENTES (BDD)'!G:G=E3)*('EQUIPAMENTOS_EFICIENTES (BDD)'!I:I=_xlfn.MINIFS('EQUIPAMENTOS_EFICIENTES (BDD)'!I:I,'EQUIPAMENTOS_EFICIENTES (BDD)'!G:G,E3,'EQUIPAMENTOS_EFICIENTES (BDD)'!I:I,">="&G3)),0)),"Substituição não encontrada"))} -> 0 | Z3: {=IFERROR(INDEX('EQUIPAMENTOS_EFICIENTES (BDD)'!K:K,MATCH(1,('EQUIPAMENTOS_EFICIENTES (BDD)'!G:G=E3)*('EQUIPAMENTOS_EFICIENTES (BDD)'!I:I=_xlfn.MINIFS('EQUIPAMENTOS_EFICIENTES (BDD)'!I:I,'EQUIPAMENTOS_EFICIENTES (BDD)'!G:G,E3,'EQUIPAMENTOS_EFICIENTES (BDD)'!I:I,">="&G3)),0)),"")} -> 0 | AA3: =I3 -> 0 | AB3: =IF(Y3=0,0,((X3*0.293*AA3)/(1000*Y3))) -> 0 | AC3: =K3 -> 0.7 | AD3: =AB3*AC3 -> 0 | AE3: =M3 -> 0 | AF3: =N3 -> 0 | AG3: =O3 -> 0 | AH3: =Q3 -> 21.25 | AI3: =R3 -> 0 | AJ3: =S3 -> 0 | AK3: =AD3*AF3/1000 -> 0 | AL3: =AJ3*AD3 -> 0 | AM3: =U3-AL3 -> 0 | AN3: =T3-AK3 -> 0 | AO3: =IF(AN3<>0,Z3*AA3,0) -> 0 | AP3: =AN3/478.332 -> 0 | AQ3: =T3*0.9 -> 0 | AR3: =AK3*0.9 -> 0
A4: =IF(UC_DADOS!$B$2=0,"",UC_DADOS!$B$2) -> #N/A | J4: =IF(H4=0,0,((G4*0.293*I4)/(1000*H4))) -> 0 | K4: 0.7 | L4: =J4*K4 -> 0 | N4: =M4*O4*Q4 -> 0 | Q4: 21.25 | S4: =O4*Q4*R4/765 -> 0 | T4: =N4*L4/1000 -> 0 | U4: =S4*L4 -> 0 | V4: {=IF(F4="A",E4,IFERROR(INDEX('EQUIPAMENTOS_EFICIENTES (BDD)'!G:G,MATCH(1,('EQUIPAMENTOS_EFICIENTES (BDD)'!G:G=E4)*('EQUIPAMENTOS_EFICIENTES (BDD)'!I:I=_xlfn.MINIFS('EQUIPAMENTOS_EFICIENTES (BDD)'!I:I,'EQUIPAMENTOS_EFICIENTES (BDD)'!G:G,E4,'EQUIPAMENTOS_EFICIENTES (BDD)'!I:I,">="&G4)),0)),"Substituição não encontrada"))} -> 0 | W4: {=IF(F4="A",F4,IFERROR(INDEX('EQUIPAMENTOS_EFICIENTES (BDD)'!H:H,MATCH(1,('EQUIPAMENTOS_EFICIENTES (BDD)'!G:G=E4)*('EQUIPAMENTOS_EFICIENTES (BDD)'!I:I=_xlfn.MINIFS('EQUIPAMENTOS_EFICIENTES (BDD)'!I:I,'EQUIPAMENTOS_EFICIENTES (BDD)'!G:G,E4,'EQUIPAMENTOS_EFICIENTES (BDD)'!I:I,">="&G4)),0)),"Substituição não encontrada"))} -> 0 | X4: {=IF(F4="A",G4,IFERROR(INDEX('EQUIPAMENTOS_EFICIENTES (BDD)'!I:I,MATCH(1,('EQUIPAMENTOS_EFICIENTES (BDD)'!G:G=E4)*('EQUIPAMENTOS_EFICIENTES (BDD)'!I:I=_xlfn.MINIFS('EQUIPAMENTOS_EFICIENTES (BDD)'!I:I,'EQUIPAMENTOS_EFICIENTES (BDD)'!G:G,E4,'EQUIPAMENTOS_EFICIENTES (BDD)'!I:I,">="&G4)),0)),"Substituição não encontrada"))} -> 0 | Y4: {=IF(F4="A",H4,IFERROR(INDEX('EQUIPAMENTOS_EFICIENTES (BDD)'!J:J,MATCH(1,('EQUIPAMENTOS_EFICIENTES (BDD)'!G:G=E4)*('EQUIPAMENTOS_EFICIENTES (BDD)'!I:I=_xlfn.MINIFS('EQUIPAMENTOS_EFICIENTES (BDD)'!I:I,'EQUIPAMENTOS_EFICIENTES (BDD)'!G:G,E4,'EQUIPAMENTOS_EFICIENTES (BDD)'!I:I,">="&G4)),0)),"Substituição não encontrada"))} -> 0 | Z4: {=IFERROR(INDEX('EQUIPAMENTOS_EFICIENTES (BDD)'!K:K,MATCH(1,('EQUIPAMENTOS_EFICIENTES (BDD)'!G:G=E4)*('EQUIPAMENTOS_EFICIENTES (BDD)'!I:I=_xlfn.MINIFS('EQUIPAMENTOS_EFICIENTES (BDD)'!I:I,'EQUIPAMENTOS_EFICIENTES (BDD)'!G:G,E4,'EQUIPAMENTOS_EFICIENTES (BDD)'!I:I,">="&G4)),0)),"")} -> 0 | AA4: =I4 -> 0 | AB4: =IF(Y4=0,0,((X4*0.293*AA4)/(1000*Y4))) -> 0 | AC4: =K4 -> 0.7 | AD4: =AB4*AC4 -> 0 | AE4: =M4 -> 0 | AF4: =N4 -> 0 | AG4: =O4 -> 0 | AH4: =Q4 -> 21.25 | AI4: =R4 -> 0 | AJ4: =S4 -> 0 | AK4: =AD4*AF4/1000 -> 0 | AL4: =AJ4*AD4 -> 0 | AM4: =U4-AL4 -> 0 | AN4: =T4-AK4 -> 0 | AO4: =IF(AN4<>0,Z4*AA4,0) -> 0 | AP4: =AN4/478.332 -> 0 | AQ4: =T4*0.9 -> 0 | AR4: =AK4*0.9 -> 0
A5: =IF(UC_DADOS!$B$2=0,"",UC_DADOS!$B$2) -> #N/A | J5: =IF(H5=0,0,((G5*0.293*I5)/(1000*H5))) -> 0 | K5: 0.7 | L5: =J5*K5 -> 0 | N5: =M5*O5*Q5 -> 0 | Q5: 21.25 | S5: =O5*Q5*R5/765 -> 0 | T5: =N5*L5/1000 -> 0 | U5: =S5*L5 -> 0 | V5: {=IF(F5="A",E5,IFERROR(INDEX('EQUIPAMENTOS_EFICIENTES (BDD)'!G:G,MATCH(1,('EQUIPAMENTOS_EFICIENTES (BDD)'!G:G=E5)*('EQUIPAMENTOS_EFICIENTES (BDD)'!I:I=_xlfn.MINIFS('EQUIPAMENTOS_EFICIENTES (BDD)'!I:I,'EQUIPAMENTOS_EFICIENTES (BDD)'!G:G,E5,'EQUIPAMENTOS_EFICIENTES (BDD)'!I:I,">="&G5)),0)),"Substituição não encontrada"))} -> 0 | W5: {=IF(F5="A",F5,IFERROR(INDEX('EQUIPAMENTOS_EFICIENTES (BDD)'!H:H,MATCH(1,('EQUIPAMENTOS_EFICIENTES (BDD)'!G:G=E5)*('EQUIPAMENTOS_EFICIENTES (BDD)'!I:I=_xlfn.MINIFS('EQUIPAMENTOS_EFICIENTES (BDD)'!I:I,'EQUIPAMENTOS_EFICIENTES (BDD)'!G:G,E5,'EQUIPAMENTOS_EFICIENTES (BDD)'!I:I,">="&G5)),0)),"Substituição não encontrada"))} -> 0 | X5: {=IF(F5="A",G5,IFERROR(INDEX('EQUIPAMENTOS_EFICIENTES (BDD)'!I:I,MATCH(1,('EQUIPAMENTOS_EFICIENTES (BDD)'!G:G=E5)*('EQUIPAMENTOS_EFICIENTES (BDD)'!I:I=_xlfn.MINIFS('EQUIPAMENTOS_EFICIENTES (BDD)'!I:I,'EQUIPAMENTOS_EFICIENTES (BDD)'!G:G,E5,'EQUIPAMENTOS_EFICIENTES (BDD)'!I:I,">="&G5)),0)),"Substituição não encontrada"))} -> 0 | Y5: {=IF(F5="A",H5,IFERROR(INDEX('EQUIPAMENTOS_EFICIENTES (BDD)'!J:J,MATCH(1,('EQUIPAMENTOS_EFICIENTES (BDD)'!G:G=E5)*('EQUIPAMENTOS_EFICIENTES (BDD)'!I:I=_xlfn.MINIFS('EQUIPAMENTOS_EFICIENTES (BDD)'!I:I,'EQUIPAMENTOS_EFICIENTES (BDD)'!G:G,E5,'EQUIPAMENTOS_EFICIENTES (BDD)'!I:I,">="&G5)),0)),"Substituição não encontrada"))} -> 0 | Z5: {=IFERROR(INDEX('EQUIPAMENTOS_EFICIENTES (BDD)'!K:K,MATCH(1,('EQUIPAMENTOS_EFICIENTES (BDD)'!G:G=E5)*('EQUIPAMENTOS_EFICIENTES (BDD)'!I:I=_xlfn.MINIFS('EQUIPAMENTOS_EFICIENTES (BDD)'!I:I,'EQUIPAMENTOS_EFICIENTES (BDD)'!G:G,E5,'EQUIPAMENTOS_EFICIENTES (BDD)'!I:I,">="&G5)),0)),"")} -> 0 | AA5: =I5 -> 0 | AB5: =IF(Y5=0,0,((X5*0.293*AA5)/(1000*Y5))) -> 0 | AC5: =K5 -> 0.7 | AD5: =AB5*AC5 -> 0 | AE5: =M5 -> 0 | AF5: =N5 -> 0 | AG5: =O5 -> 0 | AH5: =Q5 -> 21.25 | AI5: =R5 -> 0 | AJ5: =S5 -> 0 | AK5: =AD5*AF5/1000 -> 0 | AL5: =AJ5*AD5 -> 0 | AM5: =U5-AL5 -> 0 | AN5: =T5-AK5 -> 0 | AO5: =IF(AN5<>0,Z5*AA5,0) -> 0 | AP5: =AN5/478.332 -> 0 | AQ5: =T5*0.9 -> 0 | AR5: =AK5*0.9 -> 0
A6: =IF(UC_DADOS!$B$2=0,"",UC_DADOS!$B$2) -> #N/A | J6: =IF(H6=0,0,((G6*0.293*I6)/(1000*H6))) -> 0 | K6: 0.7 | L6: =J6*K6 -> 0 | N6: =M6*O6*Q6 -> 0 | Q6: 21.25 | S6: =O6*Q6*R6/765 -> 0 | T6: =N6*L6/1000 -> 0 | U6: =S6*L6 -> 0 | V6: {=IF(F6="A",E6,IFERROR(INDEX('EQUIPAMENTOS_EFICIENTES (BDD)'!G:G,MATCH(1,('EQUIPAMENTOS_EFICIENTES (BDD)'!G:G=E6)*('EQUIPAMENTOS_EFICIENTES (BDD)'!I:I=_xlfn.MINIFS('EQUIPAMENTOS_EFICIENTES (BDD)'!I:I,'EQUIPAMENTOS_EFICIENTES (BDD)'!G:G,E6,'EQUIPAMENTOS_EFICIENTES (BDD)'!I:I,">="&G6)),0)),"Substituição não encontrada"))} -> 0 | W6: {=IF(F6="A",F6,IFERROR(INDEX('EQUIPAMENTOS_EFICIENTES (BDD)'!H:H,MATCH(1,('EQUIPAMENTOS_EFICIENTES (BDD)'!G:G=E6)*('EQUIPAMENTOS_EFICIENTES (BDD)'!I:I=_xlfn.MINIFS('EQUIPAMENTOS_EFICIENTES (BDD)'!I:I,'EQUIPAMENTOS_EFICIENTES (BDD)'!G:G,E6,'EQUIPAMENTOS_EFICIENTES (BDD)'!I:I,">="&G6)),0)),"Substituição não encontrada"))} -> 0 | X6: {=IF(F6="A",G6,IFERROR(INDEX('EQUIPAMENTOS_EFICIENTES (BDD)'!I:I,MATCH(1,('EQUIPAMENTOS_EFICIENTES (BDD)'!G:G=E6)*('EQUIPAMENTOS_EFICIENTES (BDD)'!I:I=_xlfn.MINIFS('EQUIPAMENTOS_EFICIENTES (BDD)'!I:I,'EQUIPAMENTOS_EFICIENTES (BDD)'!G:G,E6,'EQUIPAMENTOS_EFICIENTES (BDD)'!I:I,">="&G6)),0)),"Substituição não encontrada"))} -> 0 | Y6: {=IF(F6="A",H6,IFERROR(INDEX('EQUIPAMENTOS_EFICIENTES (BDD)'!J:J,MATCH(1,('EQUIPAMENTOS_EFICIENTES (BDD)'!G:G=E6)*('EQUIPAMENTOS_EFICIENTES (BDD)'!I:I=_xlfn.MINIFS('EQUIPAMENTOS_EFICIENTES (BDD)'!I:I,'EQUIPAMENTOS_EFICIENTES (BDD)'!G:G,E6,'EQUIPAMENTOS_EFICIENTES (BDD)'!I:I,">="&G6)),0)),"Substituição não encontrada"))} -> 0 | Z6: {=IFERROR(INDEX('EQUIPAMENTOS_EFICIENTES (BDD)'!K:K,MATCH(1,('EQUIPAMENTOS_EFICIENTES (BDD)'!G:G=E6)*('EQUIPAMENTOS_EFICIENTES (BDD)'!I:I=_xlfn.MINIFS('EQUIPAMENTOS_EFICIENTES (BDD)'!I:I,'EQUIPAMENTOS_EFICIENTES (BDD)'!G:G,E6,'EQUIPAMENTOS_EFICIENTES (BDD)'!I:I,">="&G6)),0)),"")} -> 0 | AA6: =I6 -> 0 | AB6: =IF(Y6=0,0,((X6*0.293*AA6)/(1000*Y6))) -> 0 | AC6: =K6 -> 0.7 | AD6: =AB6*AC6 -> 0 | AE6: =M6 -> 0 | AF6: =N6 -> 0 | AG6: =O6 -> 0 | AH6: =Q6 -> 21.25 | AI6: =R6 -> 0 | AJ6: =S6 -> 0 | AK6: =AD6*AF6/1000 -> 0 | AL6: =AJ6*AD6 -> 0 | AM6: =U6-AL6 -> 0 | AN6: =T6-AK6 -> 0 | AO6: =IF(AN6<>0,Z6*AA6,0) -> 0 | AP6: =AN6/478.332 -> 0 | AQ6: =T6*0.9 -> 0 | AR6: =AK6*0.9 -> 0
A7: =IF(UC_DADOS!$B$2=0,"",UC_DADOS!$B$2) -> #N/A | J7: =IF(H7=0,0,((G7*0.293*I7)/(1000*H7))) -> 0 | K7: 0.7 | L7: =J7*K7 -> 0 | N7: =M7*O7*Q7 -> 0 | Q7: 21.25 | S7: =O7*Q7*R7/765 -> 0 | T7: =N7*L7/1000 -> 0 | U7: =S7*L7 -> 0 | V7: {=IF(F7="A",E7,IFERROR(INDEX('EQUIPAMENTOS_EFICIENTES (BDD)'!G:G,MATCH(1,('EQUIPAMENTOS_EFICIENTES (BDD)'!G:G=E7)*('EQUIPAMENTOS_EFICIENTES (BDD)'!I:I=_xlfn.MINIFS('EQUIPAMENTOS_EFICIENTES (BDD)'!I:I,'EQUIPAMENTOS_EFICIENTES (BDD)'!G:G,E7,'EQUIPAMENTOS_EFICIENTES (BDD)'!I:I,">="&G7)),0)),"Substituição não encontrada"))} -> 0 | W7: {=IF(F7="A",F7,IFERROR(INDEX('EQUIPAMENTOS_EFICIENTES (BDD)'!H:H,MATCH(1,('EQUIPAMENTOS_EFICIENTES (BDD)'!G:G=E7)*('EQUIPAMENTOS_EFICIENTES (BDD)'!I:I=_xlfn.MINIFS('EQUIPAMENTOS_EFICIENTES (BDD)'!I:I,'EQUIPAMENTOS_EFICIENTES (BDD)'!G:G,E7,'EQUIPAMENTOS_EFICIENTES (BDD)'!I:I,">="&G7)),0)),"Substituição não encontrada"))} -> 0 | X7: {=IF(F7="A",G7,IFERROR(INDEX('EQUIPAMENTOS_EFICIENTES (BDD)'!I:I,MATCH(1,('EQUIPAMENTOS_EFICIENTES (BDD)'!G:G=E7)*('EQUIPAMENTOS_EFICIENTES (BDD)'!I:I=_xlfn.MINIFS('EQUIPAMENTOS_EFICIENTES (BDD)'!I:I,'EQUIPAMENTOS_EFICIENTES (BDD)'!G:G,E7,'EQUIPAMENTOS_EFICIENTES (BDD)'!I:I,">="&G7)),0)),"Substituição não encontrada"))} -> 0 | Y7: {=IF(F7="A",H7,IFERROR(INDEX('EQUIPAMENTOS_EFICIENTES (BDD)'!J:J,MATCH(1,('EQUIPAMENTOS_EFICIENTES (BDD)'!G:G=E7)*('EQUIPAMENTOS_EFICIENTES (BDD)'!I:I=_xlfn.MINIFS('EQUIPAMENTOS_EFICIENTES (BDD)'!I:I,'EQUIPAMENTOS_EFICIENTES (BDD)'!G:G,E7,'EQUIPAMENTOS_EFICIENTES (BDD)'!I:I,">="&G7)),0)),"Substituição não encontrada"))} -> 0 | Z7: {=IFERROR(INDEX('EQUIPAMENTOS_EFICIENTES (BDD)'!K:K,MATCH(1,('EQUIPAMENTOS_EFICIENTES (BDD)'!G:G=E7)*('EQUIPAMENTOS_EFICIENTES (BDD)'!I:I=_xlfn.MINIFS('EQUIPAMENTOS_EFICIENTES (BDD)'!I:I,'EQUIPAMENTOS_EFICIENTES (BDD)'!G:G,E7,'EQUIPAMENTOS_EFICIENTES (BDD)'!I:I,">="&G7)),0)),"")} -> 0 | AA7: =I7 -> 0 | AB7: =IF(Y7=0,0,((X7*0.293*AA7)/(1000*Y7))) -> 0 | AC7: =K7 -> 0.7 | AD7: =AB7*AC7 -> 0 | AE7: =M7 -> 0 | AF7: =N7 -> 0 | AG7: =O7 -> 0 | AH7: =Q7 -> 21.25 | AI7: =R7 -> 0 | AJ7: =S7 -> 0 | AK7: =AD7*AF7/1000 -> 0 | AL7: =AJ7*AD7 -> 0 | AM7: =U7-AL7 -> 0 | AN7: =T7-AK7 -> 0 | AO7: =IF(AN7<>0,Z7*AA7,0) -> 0 | AP7: =AN7/478.332 -> 0 | AQ7: =T7*0.9 -> 0 | AR7: =AK7*0.9 -> 0
A8: =IF(UC_DADOS!$B$2=0,"",UC_DADOS!$B$2) -> #N/A | J8: =IF(H8=0,0,((G8*0.293*I8)/(1000*H8))) -> 0 | K8: 0.7 | L8: =J8*K8 -> 0 | N8: =M8*O8*Q8 -> 0 | Q8: 21.25 | S8: =O8*Q8*R8/765 -> 0 | T8: =N8*L8/1000 -> 0 | U8: =S8*L8 -> 0 | V8: {=IF(F8="A",E8,IFERROR(INDEX('EQUIPAMENTOS_EFICIENTES (BDD)'!G:G,MATCH(1,('EQUIPAMENTOS_EFICIENTES (BDD)'!G:G=E8)*('EQUIPAMENTOS_EFICIENTES (BDD)'!I:I=_xlfn.MINIFS('EQUIPAMENTOS_EFICIENTES (BDD)'!I:I,'EQUIPAMENTOS_EFICIENTES (BDD)'!G:G,E8,'EQUIPAMENTOS_EFICIENTES (BDD)'!I:I,">="&G8)),0)),"Substituição não encontrada"))} -> 0 | W8: {=IF(F8="A",F8,IFERROR(INDEX('EQUIPAMENTOS_EFICIENTES (BDD)'!H:H,MATCH(1,('EQUIPAMENTOS_EFICIENTES (BDD)'!G:G=E8)*('EQUIPAMENTOS_EFICIENTES (BDD)'!I:I=_xlfn.MINIFS('EQUIPAMENTOS_EFICIENTES (BDD)'!I:I,'EQUIPAMENTOS_EFICIENTES (BDD)'!G:G,E8,'EQUIPAMENTOS_EFICIENTES (BDD)'!I:I,">="&G8)),0)),"Substituição não encontrada"))} -> 0 | X8: {=IF(F8="A",G8,IFERROR(INDEX('EQUIPAMENTOS_EFICIENTES (BDD)'!I:I,MATCH(1,('EQUIPAMENTOS_EFICIENTES (BDD)'!G:G=E8)*('EQUIPAMENTOS_EFICIENTES (BDD)'!I:I=_xlfn.MINIFS('EQUIPAMENTOS_EFICIENTES (BDD)'!I:I,'EQUIPAMENTOS_EFICIENTES (BDD)'!G:G,E8,'EQUIPAMENTOS_EFICIENTES (BDD)'!I:I,">="&G8)),0)),"Substituição não encontrada"))} -> 0 | Y8: {=IF(F8="A",H8,IFERROR(INDEX('EQUIPAMENTOS_EFICIENTES (BDD)'!J:J,MATCH(1,('EQUIPAMENTOS_EFICIENTES (BDD)'!G:G=E8)*('EQUIPAMENTOS_EFICIENTES (BDD)'!I:I=_xlfn.MINIFS('EQUIPAMENTOS_EFICIENTES (BDD)'!I:I,'EQUIPAMENTOS_EFICIENTES (BDD)'!G:G,E8,'EQUIPAMENTOS_EFICIENTES (BDD)'!I:I,">="&G8)),0)),"Substituição não encontrada"))} -> 0 | Z8: {=IFERROR(INDEX('EQUIPAMENTOS_EFICIENTES (BDD)'!K:K,MATCH(1,('EQUIPAMENTOS_EFICIENTES (BDD)'!G:G=E8)*('EQUIPAMENTOS_EFICIENTES (BDD)'!I:I=_xlfn.MINIFS('EQUIPAMENTOS_EFICIENTES (BDD)'!I:I,'EQUIPAMENTOS_EFICIENTES (BDD)'!G:G,E8,'EQUIPAMENTOS_EFICIENTES (BDD)'!I:I,">="&G8)),0)),"")} -> 0 | AA8: =I8 -> 0 | AB8: =IF(Y8=0,0,((X8*0.293*AA8)/(1000*Y8))) -> 0 | AC8: =K8 -> 0.7 | AD8: =AB8*AC8 -> 0 | AE8: =M8 -> 0 | AF8: =N8 -> 0 | AG8: =O8 -> 0 | AH8: =Q8 -> 21.25 | AI8: =R8 -> 0 | AJ8: =S8 -> 0 | AK8: =AD8*AF8/1000 -> 0 | AL8: =AJ8*AD8 -> 0 | AM8: =U8-AL8 -> 0 | AN8: =T8-AK8 -> 0 | AO8: =IF(AN8<>0,Z8*AA8,0) -> 0 | AP8: =AN8/478.332 -> 0 | AQ8: =T8*0.9 -> 0 | AR8: =AK8*0.9 -> 0
A9: =IF(UC_DADOS!$B$2=0,"",UC_DADOS!$B$2) -> #N/A | J9: =IF(H9=0,0,((G9*0.293*I9)/(1000*H9))) -> 0 | K9: 0.7 | L9: =J9*K9 -> 0 | N9: =M9*O9*Q9 -> 0 | Q9: 21.25 | S9: =O9*Q9*R9/765 -> 0 | T9: =N9*L9/1000 -> 0 | U9: =S9*L9 -> 0 | V9: {=IF(F9="A",E9,IFERROR(INDEX('EQUIPAMENTOS_EFICIENTES (BDD)'!G:G,MATCH(1,('EQUIPAMENTOS_EFICIENTES (BDD)'!G:G=E9)*('EQUIPAMENTOS_EFICIENTES (BDD)'!I:I=_xlfn.MINIFS('EQUIPAMENTOS_EFICIENTES (BDD)'!I:I,'EQUIPAMENTOS_EFICIENTES (BDD)'!G:G,E9,'EQUIPAMENTOS_EFICIENTES (BDD)'!I:I,">="&G9)),0)),"Substituição não encontrada"))} -> 0 | W9: {=IF(F9="A",F9,IFERROR(INDEX('EQUIPAMENTOS_EFICIENTES (BDD)'!H:H,MATCH(1,('EQUIPAMENTOS_EFICIENTES (BDD)'!G:G=E9)*('EQUIPAMENTOS_EFICIENTES (BDD)'!I:I=_xlfn.MINIFS('EQUIPAMENTOS_EFICIENTES (BDD)'!I:I,'EQUIPAMENTOS_EFICIENTES (BDD)'!G:G,E9,'EQUIPAMENTOS_EFICIENTES (BDD)'!I:I,">="&G9)),0)),"Substituição não encontrada"))} -> 0 | X9: {=IF(F9="A",G9,IFERROR(INDEX('EQUIPAMENTOS_EFICIENTES (BDD)'!I:I,MATCH(1,('EQUIPAMENTOS_EFICIENTES (BDD)'!G:G=E9)*('EQUIPAMENTOS_EFICIENTES (BDD)'!I:I=_xlfn.MINIFS('EQUIPAMENTOS_EFICIENTES (BDD)'!I:I,'EQUIPAMENTOS_EFICIENTES (BDD)'!G:G,E9,'EQUIPAMENTOS_EFICIENTES (BDD)'!I:I,">="&G9)),0)),"Substituição não encontrada"))} -> 0 | Y9: {=IF(F9="A",H9,IFERROR(INDEX('EQUIPAMENTOS_EFICIENTES (BDD)'!J:J,MATCH(1,('EQUIPAMENTOS_EFICIENTES (BDD)'!G:G=E9)*('EQUIPAMENTOS_EFICIENTES (BDD)'!I:I=_xlfn.MINIFS('EQUIPAMENTOS_EFICIENTES (BDD)'!I:I,'EQUIPAMENTOS_EFICIENTES (BDD)'!G:G,E9,'EQUIPAMENTOS_EFICIENTES (BDD)'!I:I,">="&G9)),0)),"Substituição não encontrada"))} -> 0 | Z9: {=IFERROR(INDEX('EQUIPAMENTOS_EFICIENTES (BDD)'!K:K,MATCH(1,('EQUIPAMENTOS_EFICIENTES (BDD)'!G:G=E9)*('EQUIPAMENTOS_EFICIENTES (BDD)'!I:I=_xlfn.MINIFS('EQUIPAMENTOS_EFICIENTES (BDD)'!I:I,'EQUIPAMENTOS_EFICIENTES (BDD)'!G:G,E9,'EQUIPAMENTOS_EFICIENTES (BDD)'!I:I,">="&G9)),0)),"")} -> 0 | AA9: =I9 -> 0 | AB9: =IF(Y9=0,0,((X9*0.293*AA9)/(1000*Y9))) -> 0 | AC9: =K9 -> 0.7 | AD9: =AB9*AC9 -> 0 | AE9: =M9 -> 0 | AF9: =N9 -> 0 | AG9: =O9 -> 0 | AH9: =Q9 -> 21.25 | AI9: =R9 -> 0 | AJ9: =S9 -> 0 | AK9: =AD9*AF9/1000 -> 0 | AL9: =AJ9*AD9 -> 0 | AM9: =U9-AL9 -> 0 | AN9: =T9-AK9 -> 0 | AO9: =IF(AN9<>0,Z9*AA9,0) -> 0 | AP9: =AN9/478.332 -> 0 | AQ9: =T9*0.9 -> 0 | AR9: =AK9*0.9 -> 0
A10: =IF(UC_DADOS!$B$2=0,"",UC_DADOS!$B$2) -> #N/A | J10: =IF(H10=0,0,((G10*0.293*I10)/(1000*H10))) -> 0 | K10: 0.7 | L10: =J10*K10 -> 0 | N10: =M10*O10*Q10 -> 0 | Q10: 21.25 | S10: =O10*Q10*R10/765 -> 0 | T10: =N10*L10/1000 -> 0 | U10: =S10*L10 -> 0 | V10: {=IF(F10="A",E10,IFERROR(INDEX('EQUIPAMENTOS_EFICIENTES (BDD)'!G:G,MATCH(1,('EQUIPAMENTOS_EFICIENTES (BDD)'!G:G=E10)*('EQUIPAMENTOS_EFICIENTES (BDD)'!I:I=_xlfn.MINIFS('EQUIPAMENTOS_EFICIENTES (BDD)'!I:I,'EQUIPAMENTOS_EFICIENTES (BDD)'!G:G,E10,'EQUIPAMENTOS_EFICIENTES (BDD)'!I:I,">="&G10)),0)),"Substituição não encontrada"))} -> 0 | W10: {=IF(F10="A",F10,IFERROR(INDEX('EQUIPAMENTOS_EFICIENTES (BDD)'!H:H,MATCH(1,('EQUIPAMENTOS_EFICIENTES (BDD)'!G:G=E10)*('EQUIPAMENTOS_EFICIENTES (BDD)'!I:I=_xlfn.MINIFS('EQUIPAMENTOS_EFICIENTES (BDD)'!I:I,'EQUIPAMENTOS_EFICIENTES (BDD)'!G:G,E10,'EQUIPAMENTOS_EFICIENTES (BDD)'!I:I,">="&G10)),0)),"Substituição não encontrada"))} -> 0 | X10: {=IF(F10="A",G10,IFERROR(INDEX('EQUIPAMENTOS_EFICIENTES (BDD)'!I:I,MATCH(1,('EQUIPAMENTOS_EFICIENTES (BDD)'!G:G=E10)*('EQUIPAMENTOS_EFICIENTES (BDD)'!I:I=_xlfn.MINIFS('EQUIPAMENTOS_EFICIENTES (BDD)'!I:I,'EQUIPAMENTOS_EFICIENTES (BDD)'!G:G,E10,'EQUIPAMENTOS_EFICIENTES (BDD)'!I:I,">="&G10)),0)),"Substituição não encontrada"))} -> 0 | Y10: {=IF(F10="A",H10,IFERROR(INDEX('EQUIPAMENTOS_EFICIENTES (BDD)'!J:J,MATCH(1,('EQUIPAMENTOS_EFICIENTES (BDD)'!G:G=E10)*('EQUIPAMENTOS_EFICIENTES (BDD)'!I:I=_xlfn.MINIFS('EQUIPAMENTOS_EFICIENTES (BDD)'!I:I,'EQUIPAMENTOS_EFICIENTES (BDD)'!G:G,E10,'EQUIPAMENTOS_EFICIENTES (BDD)'!I:I,">="&G10)),0)),"Substituição não encontrada"))} -> 0 | Z10: {=IFERROR(INDEX('EQUIPAMENTOS_EFICIENTES (BDD)'!K:K,MATCH(1,('EQUIPAMENTOS_EFICIENTES (BDD)'!G:G=E10)*('EQUIPAMENTOS_EFICIENTES (BDD)'!I:I=_xlfn.MINIFS('EQUIPAMENTOS_EFICIENTES (BDD)'!I:I,'EQUIPAMENTOS_EFICIENTES (BDD)'!G:G,E10,'EQUIPAMENTOS_EFICIENTES (BDD)'!I:I,">="&G10)),0)),"")} -> 0 | AA10: =I10 -> 0 | AB10: =IF(Y10=0,0,((X10*0.293*AA10)/(1000*Y10))) -> 0 | AC10: =K10 -> 0.7 | AD10: =AB10*AC10 -> 0 | AE10: =M10 -> 0 | AF10: =N10 -> 0 | AG10: =O10 -> 0 | AH10: =Q10 -> 21.25 | AI10: =R10 -> 0 | AJ10: =S10 -> 0 | AK10: =AD10*AF10/1000 -> 0 | AL10: =AJ10*AD10 -> 0 | AM10: =U10-AL10 -> 0 | AN10: =T10-AK10 -> 0 | AO10: =IF(AN10<>0,Z10*AA10,0) -> 0 | AP10: =AN10/478.332 -> 0 | AQ10: =T10*0.9 -> 0 | AR10: =AK10*0.9 -> 0
A11: =IF(UC_DADOS!$B$2=0,"",UC_DADOS!$B$2) -> #N/A | J11: =IF(H11=0,0,((G11*0.293*I11)/(1000*H11))) -> 0 | K11: 0.7 | L11: =J11*K11 -> 0 | N11: =M11*O11*Q11 -> 0 | Q11: 21.25 | S11: =O11*Q11*R11/765 -> 0 | T11: =N11*L11/1000 -> 0 | U11: =S11*L11 -> 0 | V11: {=IF(F11="A",E11,IFERROR(INDEX('EQUIPAMENTOS_EFICIENTES (BDD)'!G:G,MATCH(1,('EQUIPAMENTOS_EFICIENTES (BDD)'!G:G=E11)*('EQUIPAMENTOS_EFICIENTES (BDD)'!I:I=_xlfn.MINIFS('EQUIPAMENTOS_EFICIENTES (BDD)'!I:I,'EQUIPAMENTOS_EFICIENTES (BDD)'!G:G,E11,'EQUIPAMENTOS_EFICIENTES (BDD)'!I:I,">="&G11)),0)),"Substituição não encontrada"))} -> 0 | W11: {=IF(F11="A",F11,IFERROR(INDEX('EQUIPAMENTOS_EFICIENTES (BDD)'!H:H,MATCH(1,('EQUIPAMENTOS_EFICIENTES (BDD)'!G:G=E11)*('EQUIPAMENTOS_EFICIENTES (BDD)'!I:I=_xlfn.MINIFS('EQUIPAMENTOS_EFICIENTES (BDD)'!I:I,'EQUIPAMENTOS_EFICIENTES (BDD)'!G:G,E11,'EQUIPAMENTOS_EFICIENTES (BDD)'!I:I,">="&G11)),0)),"Substituição não encontrada"))} -> 0 | X11: {=IF(F11="A",G11,IFERROR(INDEX('EQUIPAMENTOS_EFICIENTES (BDD)'!I:I,MATCH(1,('EQUIPAMENTOS_EFICIENTES (BDD)'!G:G=E11)*('EQUIPAMENTOS_EFICIENTES (BDD)'!I:I=_xlfn.MINIFS('EQUIPAMENTOS_EFICIENTES (BDD)'!I:I,'EQUIPAMENTOS_EFICIENTES (BDD)'!G:G,E11,'EQUIPAMENTOS_EFICIENTES (BDD)'!I:I,">="&G11)),0)),"Substituição não encontrada"))} -> 0 | Y11: {=IF(F11="A",H11,IFERROR(INDEX('EQUIPAMENTOS_EFICIENTES (BDD)'!J:J,MATCH(1,('EQUIPAMENTOS_EFICIENTES (BDD)'!G:G=E11)*('EQUIPAMENTOS_EFICIENTES (BDD)'!I:I=_xlfn.MINIFS('EQUIPAMENTOS_EFICIENTES (BDD)'!I:I,'EQUIPAMENTOS_EFICIENTES (BDD)'!G:G,E11,'EQUIPAMENTOS_EFICIENTES (BDD)'!I:I,">="&G11)),0)),"Substituição não encontrada"))} -> 0 | Z11: {=IFERROR(INDEX('EQUIPAMENTOS_EFICIENTES (BDD)'!K:K,MATCH(1,('EQUIPAMENTOS_EFICIENTES (BDD)'!G:G=E11)*('EQUIPAMENTOS_EFICIENTES (BDD)'!I:I=_xlfn.MINIFS('EQUIPAMENTOS_EFICIENTES (BDD)'!I:I,'EQUIPAMENTOS_EFICIENTES (BDD)'!G:G,E11,'EQUIPAMENTOS_EFICIENTES (BDD)'!I:I,">="&G11)),0)),"")} -> 0 | AA11: =I11 -> 0 | AB11: =IF(Y11=0,0,((X11*0.293*AA11)/(1000*Y11))) -> 0 | AC11: =K11 -> 0.7 | AD11: =AB11*AC11 -> 0 | AE11: =M11 -> 0 | AF11: =N11 -> 0 | AG11: =O11 -> 0 | AH11: =Q11 -> 21.25 | AI11: =R11 -> 0 | AJ11: =S11 -> 0 | AK11: =AD11*AF11/1000 -> 0 | AL11: =AJ11*AD11 -> 0 | AM11: =U11-AL11 -> 0 | AN11: =T11-AK11 -> 0 | AO11: =IF(AN11<>0,Z11*AA11,0) -> 0 | AP11: =AN11/478.332 -> 0 | AQ11: =T11*0.9 -> 0 | AR11: =AK11*0.9 -> 0
A12: =IF(UC_DADOS!$B$2=0,"",UC_DADOS!$B$2) -> #N/A | J12: =IF(H12=0,0,((G12*0.293*I12)/(1000*H12))) -> 0 | K12: 0.7 | L12: =J12*K12 -> 0 | N12: =M12*O12*Q12 -> 0 | Q12: 21.25 | S12: =O12*Q12*R12/765 -> 0 | T12: =N12*L12/1000 -> 0 | U12: =S12*L12 -> 0 | V12: {=IF(F12="A",E12,IFERROR(INDEX('EQUIPAMENTOS_EFICIENTES (BDD)'!G:G,MATCH(1,('EQUIPAMENTOS_EFICIENTES (BDD)'!G:G=E12)*('EQUIPAMENTOS_EFICIENTES (BDD)'!I:I=_xlfn.MINIFS('EQUIPAMENTOS_EFICIENTES (BDD)'!I:I,'EQUIPAMENTOS_EFICIENTES (BDD)'!G:G,E12,'EQUIPAMENTOS_EFICIENTES (BDD)'!I:I,">="&G12)),0)),"Substituição não encontrada"))} -> 0 | W12: {=IF(F12="A",F12,IFERROR(INDEX('EQUIPAMENTOS_EFICIENTES (BDD)'!H:H,MATCH(1,('EQUIPAMENTOS_EFICIENTES (BDD)'!G:G=E12)*('EQUIPAMENTOS_EFICIENTES (BDD)'!I:I=_xlfn.MINIFS('EQUIPAMENTOS_EFICIENTES (BDD)'!I:I,'EQUIPAMENTOS_EFICIENTES (BDD)'!G:G,E12,'EQUIPAMENTOS_EFICIENTES (BDD)'!I:I,">="&G12)),0)),"Substituição não encontrada"))} -> 0 | X12: {=IF(F12="A",G12,IFERROR(INDEX('EQUIPAMENTOS_EFICIENTES (BDD)'!I:I,MATCH(1,('EQUIPAMENTOS_EFICIENTES (BDD)'!G:G=E12)*('EQUIPAMENTOS_EFICIENTES (BDD)'!I:I=_xlfn.MINIFS('EQUIPAMENTOS_EFICIENTES (BDD)'!I:I,'EQUIPAMENTOS_EFICIENTES (BDD)'!G:G,E12,'EQUIPAMENTOS_EFICIENTES (BDD)'!I:I,">="&G12)),0)),"Substituição não encontrada"))} -> 0 | Y12: {=IF(F12="A",H12,IFERROR(INDEX('EQUIPAMENTOS_EFICIENTES (BDD)'!J:J,MATCH(1,('EQUIPAMENTOS_EFICIENTES (BDD)'!G:G=E12)*('EQUIPAMENTOS_EFICIENTES (BDD)'!I:I=_xlfn.MINIFS('EQUIPAMENTOS_EFICIENTES (BDD)'!I:I,'EQUIPAMENTOS_EFICIENTES (BDD)'!G:G,E12,'EQUIPAMENTOS_EFICIENTES (BDD)'!I:I,">="&G12)),0)),"Substituição não encontrada"))} -> 0 | Z12: {=IFERROR(INDEX('EQUIPAMENTOS_EFICIENTES (BDD)'!K:K,MATCH(1,('EQUIPAMENTOS_EFICIENTES (BDD)'!G:G=E12)*('EQUIPAMENTOS_EFICIENTES (BDD)'!I:I=_xlfn.MINIFS('EQUIPAMENTOS_EFICIENTES (BDD)'!I:I,'EQUIPAMENTOS_EFICIENTES (BDD)'!G:G,E12,'EQUIPAMENTOS_EFICIENTES (BDD)'!I:I,">="&G12)),0)),"")} -> 0 | AA12: =I12 -> 0 | AB12: =IF(Y12=0,0,((X12*0.293*AA12)/(1000*Y12))) -> 0 | AC12: =K12 -> 0.7 | AD12: =AB12*AC12 -> 0 | AE12: =M12 -> 0 | AF12: =N12 -> 0 | AG12: =O12 -> 0 | AH12: =Q12 -> 21.25 | AI12: =R12 -> 0 | AJ12: =S12 -> 0 | AK12: =AD12*AF12/1000 -> 0 | AL12: =AJ12*AD12 -> 0 | AM12: =U12-AL12 -> 0 | AN12: =T12-AK12 -> 0 | AO12: =IF(AN12<>0,Z12*AA12,0) -> 0 | AP12: =AN12/478.332 -> 0 | AQ12: =T12*0.9 -> 0 | AR12: =AK12*0.9 -> 0
A13: =IF(UC_DADOS!$B$2=0,"",UC_DADOS!$B$2) -> #N/A | J13: =IF(H13=0,0,((G13*0.293*I13)/(1000*H13))) -> 0 | K13: 0.7 | L13: =J13*K13 -> 0 | N13: =M13*O13*Q13 -> 0 | Q13: 21.25 | S13: =O13*Q13*R13/765 -> 0 | T13: =N13*L13/1000 -> 0 | U13: =S13*L13 -> 0 | V13: {=IF(F13="A",E13,IFERROR(INDEX('EQUIPAMENTOS_EFICIENTES (BDD)'!G:G,MATCH(1,('EQUIPAMENTOS_EFICIENTES (BDD)'!G:G=E13)*('EQUIPAMENTOS_EFICIENTES (BDD)'!I:I=_xlfn.MINIFS('EQUIPAMENTOS_EFICIENTES (BDD)'!I:I,'EQUIPAMENTOS_EFICIENTES (BDD)'!G:G,E13,'EQUIPAMENTOS_EFICIENTES (BDD)'!I:I,">="&G13)),0)),"Substituição não encontrada"))} -> 0 | W13: {=IF(F13="A",F13,IFERROR(INDEX('EQUIPAMENTOS_EFICIENTES (BDD)'!H:H,MATCH(1,('EQUIPAMENTOS_EFICIENTES (BDD)'!G:G=E13)*('EQUIPAMENTOS_EFICIENTES (BDD)'!I:I=_xlfn.MINIFS('EQUIPAMENTOS_EFICIENTES (BDD)'!I:I,'EQUIPAMENTOS_EFICIENTES (BDD)'!G:G,E13,'EQUIPAMENTOS_EFICIENTES (BDD)'!I:I,">="&G13)),0)),"Substituição não encontrada"))} -> 0 | X13: {=IF(F13="A",G13,IFERROR(INDEX('EQUIPAMENTOS_EFICIENTES (BDD)'!I:I,MATCH(1,('EQUIPAMENTOS_EFICIENTES (BDD)'!G:G=E13)*('EQUIPAMENTOS_EFICIENTES (BDD)'!I:I=_xlfn.MINIFS('EQUIPAMENTOS_EFICIENTES (BDD)'!I:I,'EQUIPAMENTOS_EFICIENTES (BDD)'!G:G,E13,'EQUIPAMENTOS_EFICIENTES (BDD)'!I:I,">="&G13)),0)),"Substituição não encontrada"))} -> 0 | Y13: {=IF(F13="A",H13,IFERROR(INDEX('EQUIPAMENTOS_EFICIENTES (BDD)'!J:J,MATCH(1,('EQUIPAMENTOS_EFICIENTES (BDD)'!G:G=E13)*('EQUIPAMENTOS_EFICIENTES (BDD)'!I:I=_xlfn.MINIFS('EQUIPAMENTOS_EFICIENTES (BDD)'!I:I,'EQUIPAMENTOS_EFICIENTES (BDD)'!G:G,E13,'EQUIPAMENTOS_EFICIENTES (BDD)'!I:I,">="&G13)),0)),"Substituição não encontrada"))} -> 0 | Z13: {=IFERROR(INDEX('EQUIPAMENTOS_EFICIENTES (BDD)'!K:K,MATCH(1,('EQUIPAMENTOS_EFICIENTES (BDD)'!G:G=E13)*('EQUIPAMENTOS_EFICIENTES (BDD)'!I:I=_xlfn.MINIFS('EQUIPAMENTOS_EFICIENTES (BDD)'!I:I,'EQUIPAMENTOS_EFICIENTES (BDD)'!G:G,E13,'EQUIPAMENTOS_EFICIENTES (BDD)'!I:I,">="&G13)),0)),"")} -> 0 | AA13: =I13 -> 0 | AB13: =IF(Y13=0,0,((X13*0.293*AA13)/(1000*Y13))) -> 0 | AC13: =K13 -> 0.7 | AD13: =AB13*AC13 -> 0 | AE13: =M13 -> 0 | AF13: =N13 -> 0 | AG13: =O13 -> 0 | AH13: =Q13 -> 21.25 | AI13: =R13 -> 0 | AJ13: =S13 -> 0 | AK13: =AD13*AF13/1000 -> 0 | AL13: =AJ13*AD13 -> 0 | AM13: =U13-AL13 -> 0 | AN13: =T13-AK13 -> 0 | AO13: =IF(AN13<>0,Z13*AA13,0) -> 0 | AP13: =AN13/478.332 -> 0 | AQ13: =T13*0.9 -> 0 | AR13: =AK13*0.9 -> 0
A14: =IF(UC_DADOS!$B$2=0,"",UC_DADOS!$B$2) -> #N/A | J14: =IF(H14=0,0,((G14*0.293*I14)/(1000*H14))) -> 0 | K14: 0.7 | L14: =J14*K14 -> 0 | N14: =M14*O14*Q14 -> 0 | Q14: 21.25 | S14: =O14*Q14*R14/765 -> 0 | T14: =N14*L14/1000 -> 0 | U14: =S14*L14 -> 0 | V14: {=IF(F14="A",E14,IFERROR(INDEX('EQUIPAMENTOS_EFICIENTES (BDD)'!G:G,MATCH(1,('EQUIPAMENTOS_EFICIENTES (BDD)'!G:G=E14)*('EQUIPAMENTOS_EFICIENTES (BDD)'!I:I=_xlfn.MINIFS('EQUIPAMENTOS_EFICIENTES (BDD)'!I:I,'EQUIPAMENTOS_EFICIENTES (BDD)'!G:G,E14,'EQUIPAMENTOS_EFICIENTES (BDD)'!I:I,">="&G14)),0)),"Substituição não encontrada"))} -> 0 | W14: {=IF(F14="A",F14,IFERROR(INDEX('EQUIPAMENTOS_EFICIENTES (BDD)'!H:H,MATCH(1,('EQUIPAMENTOS_EFICIENTES (BDD)'!G:G=E14)*('EQUIPAMENTOS_EFICIENTES (BDD)'!I:I=_xlfn.MINIFS('EQUIPAMENTOS_EFICIENTES (BDD)'!I:I,'EQUIPAMENTOS_EFICIENTES (BDD)'!G:G,E14,'EQUIPAMENTOS_EFICIENTES (BDD)'!I:I,">="&G14)),0)),"Substituição não encontrada"))} -> 0 | X14: {=IF(F14="A",G14,IFERROR(INDEX('EQUIPAMENTOS_EFICIENTES (BDD)'!I:I,MATCH(1,('EQUIPAMENTOS_EFICIENTES (BDD)'!G:G=E14)*('EQUIPAMENTOS_EFICIENTES (BDD)'!I:I=_xlfn.MINIFS('EQUIPAMENTOS_EFICIENTES (BDD)'!I:I,'EQUIPAMENTOS_EFICIENTES (BDD)'!G:G,E14,'EQUIPAMENTOS_EFICIENTES (BDD)'!I:I,">="&G14)),0)),"Substituição não encontrada"))} -> 0 | Y14: {=IF(F14="A",H14,IFERROR(INDEX('EQUIPAMENTOS_EFICIENTES (BDD)'!J:J,MATCH(1,('EQUIPAMENTOS_EFICIENTES (BDD)'!G:G=E14)*('EQUIPAMENTOS_EFICIENTES (BDD)'!I:I=_xlfn.MINIFS('EQUIPAMENTOS_EFICIENTES (BDD)'!I:I,'EQUIPAMENTOS_EFICIENTES (BDD)'!G:G,E14,'EQUIPAMENTOS_EFICIENTES (BDD)'!I:I,">="&G14)),0)),"Substituição não encontrada"))} -> 0 | Z14: {=IFERROR(INDEX('EQUIPAMENTOS_EFICIENTES (BDD)'!K:K,MATCH(1,('EQUIPAMENTOS_EFICIENTES (BDD)'!G:G=E14)*('EQUIPAMENTOS_EFICIENTES (BDD)'!I:I=_xlfn.MINIFS('EQUIPAMENTOS_EFICIENTES (BDD)'!I:I,'EQUIPAMENTOS_EFICIENTES (BDD)'!G:G,E14,'EQUIPAMENTOS_EFICIENTES (BDD)'!I:I,">="&G14)),0)),"")} -> 0 | AA14: =I14 -> 0 | AB14: =IF(Y14=0,0,((X14*0.293*AA14)/(1000*Y14))) -> 0 | AC14: =K14 -> 0.7 | AD14: =AB14*AC14 -> 0 | AE14: =M14 -> 0 | AF14: =N14 -> 0 | AG14: =O14 -> 0 | AH14: =Q14 -> 21.25 | AI14: =R14 -> 0 | AJ14: =S14 -> 0 | AK14: =AD14*AF14/1000 -> 0 | AL14: =AJ14*AD14 -> 0 | AM14: =U14-AL14 -> 0 | AN14: =T14-AK14 -> 0 | AO14: =IF(AN14<>0,Z14*AA14,0) -> 0 | AP14: =AN14/478.332 -> 0 | AQ14: =T14*0.9 -> 0 | AR14: =AK14*0.9 -> 0
A15: =IF(UC_DADOS!$B$2=0,"",UC_DADOS!$B$2) -> #N/A | J15: =IF(H15=0,0,((G15*0.293*I15)/(1000*H15))) -> 0 | K15: 0.7 | L15: =J15*K15 -> 0 | N15: =M15*O15*Q15 -> 0 | Q15: 21.25 | S15: =O15*Q15*R15/765 -> 0 | T15: =N15*L15/1000 -> 0 | U15: =S15*L15 -> 0 | V15: {=IF(F15="A",E15,IFERROR(INDEX('EQUIPAMENTOS_EFICIENTES (BDD)'!G:G,MATCH(1,('EQUIPAMENTOS_EFICIENTES (BDD)'!G:G=E15)*('EQUIPAMENTOS_EFICIENTES (BDD)'!I:I=_xlfn.MINIFS('EQUIPAMENTOS_EFICIENTES (BDD)'!I:I,'EQUIPAMENTOS_EFICIENTES (BDD)'!G:G,E15,'EQUIPAMENTOS_EFICIENTES (BDD)'!I:I,">="&G15)),0)),"Substituição não encontrada"))} -> 0 | W15: {=IF(F15="A",F15,IFERROR(INDEX('EQUIPAMENTOS_EFICIENTES (BDD)'!H:H,MATCH(1,('EQUIPAMENTOS_EFICIENTES (BDD)'!G:G=E15)*('EQUIPAMENTOS_EFICIENTES (BDD)'!I:I=_xlfn.MINIFS('EQUIPAMENTOS_EFICIENTES (BDD)'!I:I,'EQUIPAMENTOS_EFICIENTES (BDD)'!G:G,E15,'EQUIPAMENTOS_EFICIENTES (BDD)'!I:I,">="&G15)),0)),"Substituição não encontrada"))} -> 0 | X15: {=IF(F15="A",G15,IFERROR(INDEX('EQUIPAMENTOS_EFICIENTES (BDD)'!I:I,MATCH(1,('EQUIPAMENTOS_EFICIENTES (BDD)'!G:G=E15)*('EQUIPAMENTOS_EFICIENTES (BDD)'!I:I=_xlfn.MINIFS('EQUIPAMENTOS_EFICIENTES (BDD)'!I:I,'EQUIPAMENTOS_EFICIENTES (BDD)'!G:G,E15,'EQUIPAMENTOS_EFICIENTES (BDD)'!I:I,">="&G15)),0)),"Substituição não encontrada"))} -> 0 | Y15: {=IF(F15="A",H15,IFERROR(INDEX('EQUIPAMENTOS_EFICIENTES (BDD)'!J:J,MATCH(1,('EQUIPAMENTOS_EFICIENTES (BDD)'!G:G=E15)*('EQUIPAMENTOS_EFICIENTES (BDD)'!I:I=_xlfn.MINIFS('EQUIPAMENTOS_EFICIENTES (BDD)'!I:I,'EQUIPAMENTOS_EFICIENTES (BDD)'!G:G,E15,'EQUIPAMENTOS_EFICIENTES (BDD)'!I:I,">="&G15)),0)),"Substituição não encontrada"))} -> 0 | Z15: {=IFERROR(INDEX('EQUIPAMENTOS_EFICIENTES (BDD)'!K:K,MATCH(1,('EQUIPAMENTOS_EFICIENTES (BDD)'!G:G=E15)*('EQUIPAMENTOS_EFICIENTES (BDD)'!I:I=_xlfn.MINIFS('EQUIPAMENTOS_EFICIENTES (BDD)'!I:I,'EQUIPAMENTOS_EFICIENTES (BDD)'!G:G,E15,'EQUIPAMENTOS_EFICIENTES (BDD)'!I:I,">="&G15)),0)),"")} -> 0 | AA15: =I15 -> 0 | AB15: =IF(Y15=0,0,((X15*0.293*AA15)/(1000*Y15))) -> 0 | AC15: =K15 -> 0.7 | AD15: =AB15*AC15 -> 0 | AE15: =M15 -> 0 | AF15: =N15 -> 0 | AG15: =O15 -> 0 | AH15: =Q15 -> 21.25 | AI15: =R15 -> 0 | AJ15: =S15 -> 0 | AK15: =AD15*AF15/1000 -> 0 | AL15: =AJ15*AD15 -> 0 | AM15: =U15-AL15 -> 0 | AN15: =T15-AK15 -> 0 | AO15: =IF(AN15<>0,Z15*AA15,0) -> 0 | AP15: =AN15/478.332 -> 0 | AQ15: =T15*0.9 -> 0 | AR15: =AK15*0.9 -> 0
... A44: =IF(UC_DADOS!$B$2=0,"",UC_DADOS!$B$2) -> #N/A | J44: =IF(H44=0,0,((G44*0.293*I44)/(1000*H44))) -> 0 | K44: 0.7 | L44: =J44*K44 -> 0 | N44: =M44*O44*Q44 -> 0 | Q44: 21.25 | S44: =O44*Q44*R44/765 -> 0 | T44: =N44*L44/1000 -> 0 | U44: =S44*L44 -> 0 | V44: {=IF(F44="A",E44,IFERROR(INDEX('EQUIPAMENTOS_EFICIENTES (BDD)'!G:G,MATCH(1,('EQUIPAMENTOS_EFICIENTES (BDD)'!G:G=E44)*('EQUIPAMENTOS_EFICIENTES (BDD)'!I:I=_xlfn.MINIFS('EQUIPAMENTOS_EFICIENTES (BDD)'!I:I,'EQUIPAMENTOS_EFICIENTES (BDD)'!G:G,E44,'EQUIPAMENTOS_EFICIENTES (BDD)'!I:I,">="&G44)),0)),"Substituição não encontrada"))} -> 0 | W44: {=IF(F44="A",F44,IFERROR(INDEX('EQUIPAMENTOS_EFICIENTES (BDD)'!H:H,MATCH(1,('EQUIPAMENTOS_EFICIENTES (BDD)'!G:G=E44)*('EQUIPAMENTOS_EFICIENTES (BDD)'!I:I=_xlfn.MINIFS('EQUIPAMENTOS_EFICIENTES (BDD)'!I:I,'EQUIPAMENTOS_EFICIENTES (BDD)'!G:G,E44,'EQUIPAMENTOS_EFICIENTES (BDD)'!I:I,">="&G44)),0)),"Substituição não encontrada"))} -> 0 | X44: {=IF(F44="A",G44,IFERROR(INDEX('EQUIPAMENTOS_EFICIENTES (BDD)'!I:I,MATCH(1,('EQUIPAMENTOS_EFICIENTES (BDD)'!G:G=E44)*('EQUIPAMENTOS_EFICIENTES (BDD)'!I:I=_xlfn.MINIFS('EQUIPAMENTOS_EFICIENTES (BDD)'!I:I,'EQUIPAMENTOS_EFICIENTES (BDD)'!G:G,E44,'EQUIPAMENTOS_EFICIENTES (BDD)'!I:I,">="&G44)),0)),"Substituição não encontrada"))} -> 0 | Y44: {=IF(F44="A",H44,IFERROR(INDEX('EQUIPAMENTOS_EFICIENTES (BDD)'!J:J,MATCH(1,('EQUIPAMENTOS_EFICIENTES (BDD)'!G:G=E44)*('EQUIPAMENTOS_EFICIENTES (BDD)'!I:I=_xlfn.MINIFS('EQUIPAMENTOS_EFICIENTES (BDD)'!I:I,'EQUIPAMENTOS_EFICIENTES (BDD)'!G:G,E44,'EQUIPAMENTOS_EFICIENTES (BDD)'!I:I,">="&G44)),0)),"Substituição não encontrada"))} -> 0 | Z44: {=IFERROR(INDEX('EQUIPAMENTOS_EFICIENTES (BDD)'!K:K,MATCH(1,('EQUIPAMENTOS_EFICIENTES (BDD)'!G:G=E44)*('EQUIPAMENTOS_EFICIENTES (BDD)'!I:I=_xlfn.MINIFS('EQUIPAMENTOS_EFICIENTES (BDD)'!I:I,'EQUIPAMENTOS_EFICIENTES (BDD)'!G:G,E44,'EQUIPAMENTOS_EFICIENTES (BDD)'!I:I,">="&G44)),0)),"")} -> 0 | AA44: =I44 -> 0 | AB44: =IF(Y44=0,0,((X44*0.293*AA44)/(1000*Y44))) -> 0 | AC44: =K44 -> 0.7 | AD44: =AB44*AC44 -> 0 | AE44: =M44 -> 0 | AF44: =N44 -> 0 | AG44: =O44 -> 0 | AH44: =Q44 -> 21.25 | AI44: =R44 -> 0 | AJ44: =S44 -> 0 | AK44: =AD44*AF44/1000 -> 0 | AL44: =AJ44*AD44 -> 0 | AM44: =U44-AL44 -> 0 | AN44: =T44-AK44 -> 0 | AO44: =IF(AN44<>0,Z44*AA44,0) -> 0 | AP44: =AN44/478.332 -> 0 | AQ44: =T44*0.9 -> 0 | AR44: =AK44*0.9 -> 0
E45: TOTAL | I45: =SUM(I3:I44) -> 0 | J45: =SUM(J3:J44) -> 0 | L45: =SUM(L3:L44) -> 0 | T45: =SUM(T3:T44) -> 0 | U45: =SUM(U3:U44) -> 0 | X45: TOTAL | AA45: =SUM(AA3:AA44) -> 0 | AB45: =SUM(AB3:AB44) -> 0 | AD45: =SUM(AD3:AD44) -> 0 | AK45: =SUM(AK3:AK44) -> 0 | AL45: =SUM(AL3:AL44) -> 0 | AM45: =SUM(AM3:AM44) -> 0 | AN45: =SUM(AN3:AN44) -> 0 | AO45: =SUM(AO3:AO44) -> 0 | AP45: =SUM(AP3:AP44) -> 0 | AQ45: =SUM(AQ3:AQ44) -> 0 | AR45: =SUM(AR3:AR44) -> 0
AM123: TOTAL | AN123: =SUM(AN3:AN122) -> 0 | AP123: =SUM(AP3:AP122) -> 0

Sheet Sistemas de Iluminação
A1: Unidade Consumidora | E1: SITUAÇÃO ATUAL | T1: SISTEMA PROPOSTO | AH1: RESULTADOS ESPERADOS | AJ1: RESULTADO AUTOMAÇÃO (15%)
A2: Unidade consumidora (Número da conta contrato) | B2: Pavimento | C2: Ambiente | D2: Descrição do sistema | E2: Tipo de equipamento / tecnologia | F2: Lâmpadas | H2: Reatores | J2: Potência Instalada (kW) | K2: Funcionamento (h/dia) | L2: Funcionamento (h/ano) | M2: Meses no ano, de utilização do Sistema | N2: Dias no mês, de utilização do Sistema | O2: Dias úteis no mês, de utilização do Sistema | P2: Horas por dia, de utilização do Sistema no horário de Ponta (horas) | Q2: Fator de coincidência na ponta | R2: Energia consumida (MWh/ano) | S2: Demanda média na ponta (kW) | T2: Tipo de equipamento / tecnologia | U2: Lâmpadas | W2: Reatores | Y2: Potência Instalada (kW) | Z2: Funcionamento (h/ano) | AA2: Meses no ano, de utilização do Sistema no horário de Ponta (meses) | AB2: Dias úteis no mês, de utilização do Sistema no horário de Ponta (dias) | AC2: Horas por dia, de utilização do Sistema no horário de Ponta (horas) | AD2: Fator de coincidência na ponta | AE2: Energia consumida (MWh/ano) | AF2: Demanda média na ponta (kW) | AG2: Redução de demanda na ponta (kW) | AH2: Energia economizada (MWh/ano) | AI2: Redução de consumo proposto em relação ao consumo total da UC (%) | AJ2: Energia economizada (MWh/ano)
F3: Potência (W) | G3: Quantidade | H3: Potência (W) | I3: Quantidade | U3: Potência (W) | V3: Quantidade | W3: Potência (W) | X3: Quantidade
A4: =IF(UC_DADOS!$B$2=0,"",UC_DADOS!$B$2) -> #N/A | J4: =(F4*G4+H4*I4)/1000 -> 0 | L4: =K4*M4*N4 -> 0 | O4: 21.25 | Q4: =M4*O4*P4/765 -> 0 | R4: =J4*L4/1000 -> 0 | S4: =J4*Q4 -> 0 | T4: LED | Y4: =(U4*V4+W4*X4)/1000 -> 0 | Z4: =L4 -> 0 | AA4: =M4 -> 0 | AB4: =O4 -> 21.25 | AC4: =P4 -> 0 | AD4: =Q4 -> 0 | AE4: =Y4*Z4/1000 -> 0 | AF4: =Y4*AD4 -> 0 | AG4: =S4-AF4 -> 0 | AH4: =R4-AE4 -> 0 | AI4: =AH4/478.332 -> 0 | AJ4: =R4*0.85 -> 0
A5: =IF(UC_DADOS!$B$2=0,"",UC_DADOS!$B$2) -> #N/A | J5: =(F5*G5+H5*I5)/1000 -> 0 | L5: =K5*M5*O5 -> 0 | O5: 21.25 | Q5: =M5*O5*P5/765 -> 0 | R5: =J5*L5/1000 -> 0 | S5: =J5*Q5 -> 0 | T5: LED | Y5: =(U5*V5+W5*X5)/1000 -> 0 | Z5: =L5 -> 0 | AA5: =M5 -> 0 | AB5: =O5 -> 21.25 | AC5: =P5 -> 0 | AD5: =Q5 -> 0 | AE5: =Y5*Z5/1000 -> 0 | AF5: =Y5*AD5 -> 0 | AG5: =S5-AF5 -> 0 | AH5: =R5-AE5 -> 0 | AI5: =AH5/478.332 -> 0 | AJ5: =R5*0.85 -> 0
A6: =IF(UC_DADOS!$B$2=0,"",UC_DADOS!$B$2) -> #N/A | J6: =(F6*G6+H6*I6)/1000 -> 0 | L6: =K6*M6*O6 -> 0 | O6: 21.25 | Q6: =M6*O6*P6/765 -> 0 | R6: =J6*L6/1000 -> 0 | S6: =J6*Q6 -> 0 | T6: LED | Y6: =(U6*V6+W6*X6)/1000 -> 0 | Z6: =L6 -> 0 | AA6: =M6 -> 0 | AB6: =O6 -> 21.25 | AC6: =P6 -> 0 | AD6: =Q6 -> 0 | AE6: =Y6*Z6/1000 -> 0 | AF6: =Y6*AD6 -> 0 | AG6: =S6-AF6 -> 0 | AH6: =R6-AE6 -> 0 | AI6: =AH6/478.332 -> 0 | AJ6: =R6*0.85 -> 0
A7: =IF(UC_DADOS!$B$2=0,"",UC_DADOS!$B$2) -> #N/A | J7: =(F7*G7+H7*I7)/1000 -> 0 | L7: =K7*M7*O7 -> 0 | O7: 21.25 | Q7: =M7*O7*P7/765 -> 0 | R7: =J7*L7/1000 -> 0 | S7: =J7*Q7 -> 0 | T7: LED | Y7: =(U7*V7+W7*X7)/1000 -> 0 | Z7: =L7 -> 0 | AA7: =M7 -> 0 | AB7: =O7 -> 21.25 | AC7: =P7 -> 0 | AD7: =Q7 -> 0 | AE7: =Y7*Z7/1000 -> 0 | AF7: =Y7*AD7 -> 0 | AG7: =S7-AF7 -> 0 | AH7: =R7-AE7 -> 0 | AI7: =AH7/478.332 -> 0 | AJ7: =R7*0.85 -> 0
A8: =IF(UC_DADOS!$B$2=0,"",UC_DADOS!$B$2) -> #N/A | J8: =(F8*G8+H8*I8)/1000 -> 0 | L8: =K8*M8*O8 -> 0 | O8: 21.25 | Q8: =M8*O8*P8/765 -> 0 | R8: =J8*L8/1000 -> 0 | S8: =J8*Q8 -> 0 | T8: LED | Y8: =(U8*V8+W8*X8)/1000 -> 0 | Z8: =L8 -> 0 | AA8: =M8 -> 0 | AB8: =O8 -> 21.25 | AC8: =P8 -> 0 | AD8: =Q8 -> 0 | AE8: =Y8*Z8/1000 -> 0 | AF8: =Y8*AD8 -> 0 | AG8: =S8-AF8 -> 0 | AH8: =R8-AE8 -> 0 | AI8: =AH8/478.332 -> 0 | AJ8: =R8*0.85 -> 0
A9: =IF(UC_DADOS!$B$2=0,"",UC_DADOS!$B$2) -> #N/A | J9: =(F9*G9+H9*I9)/1000 -> 0 | L9: =K9*M9*O9 -> 0 | O9: 21.25 | Q9: =M9*O9*P9/765 -> 0 | R9: =J9*L9/1000 -> 0 | S9: =J9*Q9 -> 0 | T9: LED | Y9: =(U9*V9+W9*X9)/1000 -> 0 | Z9: =L9 -> 0 | AA9: =M9 -> 0 | AB9: =O9 -> 21.25 | AC9: =P9 -> 0 | AD9: =Q9 -> 0 | AE9: =Y9*Z9/1000 -> 0 | AF9: =Y9*AD9 -> 0 | AG9: =S9-AF9 -> 0 | AH9: =R9-AE9 -> 0 | AI9: =AH9/478.332 -> 0 | AJ9: =R9*0.85 -> 0
A10: =IF(UC_DADOS!$B$2=0,"",UC_DADOS!$B$2) -> #N/A | J10: =(F10*G10+H10*I10)/1000 -> 0 | L10: =K10*M10*O10 -> 0 | O10: 21.25 | Q10: =M10*O10*P10/765 -> 0 | R10: =J10*L10/1000 -> 0 | S10: =J10*Q10 -> 0 | T10: LED | Y10: =(U10*V10+W10*X10)/1000 -> 0 | Z10: =L10 -> 0 | AA10: =M10 -> 0 | AB10: =O10 -> 21.25 | AC10: =P10 -> 0 | AD10: =Q10 -> 0 | AE10: =Y10*Z10/1000 -> 0 | AF10: =Y10*AD10 -> 0 | AG10: =S10-AF10 -> 0 | AH10: =R10-AE10 -> 0 | AI10: =AH10/478.332 -> 0 | AJ10: =R10*0.85 -> 0
A11: =IF(UC_DADOS!$B$2=0,"",UC_DADOS!$B$2) -> #N/A | J11: =(F11*G11+H11*I11)/1000 -> 0 | L11: =K11*M11*O11 -> 0 | O11: 21.25 | Q11: =M11*O11*P11/765 -> 0 | R11: =J11*L11/1000 -> 0 | S11: =J11*Q11 -> 0 | T11: LED | Y11: =(U11*V11+W11*X11)/1000 -> 0 | Z11: =L11 -> 0 | AA11: =M11 -> 0 | AB11: =O11 -> 21.25 | AC11: =P11 -> 0 | AD11: =Q11 -> 0 | AE11: =Y11*Z11/1000 -> 0 | AF11: =Y11*AD11 -> 0 | AG11: =S11-AF11 -> 0 | AH11: =R11-AE11 -> 0 | AI11: =AH11/478.332 -> 0 | AJ11: =R11*0.85 -> 0
A12: =IF(UC_DADOS!$B$2=0,"",UC_DADOS!$B$2) -> #N/A | J12: =(F12*G12+H12*I12)/1000 -> 0 | L12: =K12*M12*O12 -> 0 | O12: 21.25 | Q12: =M12*O12*P12/765 -> 0 | R12: =J12*L12/1000 -> 0 | S12: =J12*Q12 -> 0 | T12: LED | Y12: =(U12*V12+W12*X12)/1000 -> 0 | Z12: =L12 -> 0 | AA12: =M12 -> 0 | AB12: =O12 -> 21.25 | AC12: =P12 -> 0 | AD12: =Q12 -> 0 | AE12: =Y12*Z12/1000 -> 0 | AF12: =Y12*AD12 -> 0 | AG12: =S12-AF12 -> 0 | AH12: =R12-AE12 -> 0 | AI12: =AH12/478.332 -> 0 | AJ12: =R12*0.85 -> 0
A13: =IF(UC_DADOS!$B$2=0,"",UC_DADOS!$B$2) -> #N/A | J13: =(F13*G13+H13*I13)/1000 -> 0 | L13: =K13*M13*O13 -> 0 | O13: 21.25 | Q13: =M13*O13*P13/765 -> 0 | R13: =J13*L13/1000 -> 0 | S13: =J13*Q13 -> 0 | T13: LED | Y13: =(U13*V13+W13*X13)/1000 -> 0 | Z13: =L13 -> 0 | AA13: =M13 -> 0 | AB13: =O13 -> 21.25 | AC13: =P13 -> 0 | AD13: =Q13 -> 0 | AE13: =Y13*Z13/1000 -> 0 | AF13: =Y13*AD13 -> 0 | AG13: =S13-AF13 -> 0 | AH13: =R13-AE13 -> 0 | AI13: =AH13/478.332 -> 0 | AJ13: =R13*0.85 -> 0
A14: =IF(UC_DADOS!$B$2=0,"",UC_DADOS!$B$2) -> #N/A | J14: =(F14*G14+H14*I14)/1000 -> 0 | L14: =K14*M14*O14 -> 0 | O14: 21.25 | Q14: =M14*O14*P14/765 -> 0 | R14: =J14*L14/1000 -> 0 | S14: =J14*Q14 -> 0 | T14: LED | Y14: =(U14*V14+W14*X14)/1000 -> 0 | Z14: =L14 -> 0 | AA14: =M14 -> 0 | AB14: =O14 -> 21.25 | AC14: =P14 -> 0 | AD14: =Q14 -> 0 | AE14: =Y14*Z14/1000 -> 0 | AF14: =Y14*AD14 -> 0 | AG14: =S14-AF14 -> 0 | AH14: =R14-AE14 -> 0 | AI14: =AH14/478.332 -> 0 | AJ14: =R14*0.85 -> 0
A15: =IF(UC_DADOS!$B$2=0,"",UC_DADOS!$B$2) -> #N/A | J15: =(F15*G15+H15*I15)/1000 -> 0 | L15: =K15*M15*O15 -> 0 | O15: 21.25 | Q15: =M15*O15*P15/765 -> 0 | R15: =J15*L15/1000 -> 0 | S15: =J15*Q15 -> 0 | T15: LED | Y15: =(U15*V15+W15*X15)/1000 -> 0 | Z15: =L15 -> 0 | AA15: =M15 -> 0 | AB15: =O15 -> 21.25 | AC15: =P15 -> 0 | AD15: =Q15 -> 0 | AE15: =Y15*Z15/1000 -> 0 | AF15: =Y15*AD15 -> 0 | AG15: =S15-AF15 -> 0 | AH15: =R15-AE15 -> 0 | AI15: =AH15/478.332 -> 0 | AJ15: =R15*0.85 -> 0
A16: =IF(UC_DADOS!$B$2=0,"",UC_DADOS!$B$2) -> #N/A | J16: =(F16*G16+H16*I16)/1000 -> 0 | L16: =K16*M16*O16 -> 0 | O16: 21.25 | Q16: =M16*O16*P16/765 -> 0 | R16: =J16*L16/1000 -> 0 | S16: =J16*Q16 -> 0 | T16: LED | Y16: =(U16*V16+W16*X16)/1000 -> 0 | Z16: =L16 -> 0 | AA16: =M16 -> 0 | AB16: =O16 -> 21.25 | AC16: =P16 -> 0 | AD16: =Q16 -> 0 | AE16: =Y16*Z16/1000 -> 0 | AF16: =Y16*AD16 -> 0 | AG16: =S16-AF16 -> 0 | AH16: =R16-AE16 -> 0 | AI16: =AH16/478.332 -> 0 | AJ16: =R16*0.85 -> 0
... A95: =IF(UC_DADOS!$B$2=0,"",UC_DADOS!$B$2) -> #N/A | J95: =(F95*G95+H95*I95)/1000 -> 0 | L95: =K95*M95*O95 -> 0 | O95: 21.25 | Q95: =M95*O95*P95/765 -> 0 | R95: =J95*L95/1000 -> 0 | S95: =J95*Q95 -> 0 | T95: LED | Y95: =(U95*V95+W95*X95)/1000 -> 0 | Z95: =L95 -> 0 | AA95: =M95 -> 0 | AB95: =O95 -> 21.25 | AC95: =P95 -> 0 | AD95: =Q95 -> 0 | AE95: =Y95*Z95/1000 -> 0 | AF95: =Y95*AD95 -> 0 | AG95: =S95-AF95 -> 0 | AH95: =R95-AE95 -> 0 | AI95: =AH95/478.332 -> 0 | AJ95: =R95*0.85 -> 0
E96: TOTAL | G96: =SUM(G4:G95) -> 0 | J96: =SUM(J4:J95) -> 0 | R96: =SUM(R4:R95) -> 0 | S96: =SUM(S4:S95) -> 0 | V96: =SUM(V4:V95) -> 0 | Y96: =SUM(Y4:Y95) -> 0 | AE96: =SUM(AE4:AE95) -> 0 | AF96: =SUM(AF4:AF95) -> 0 | AG96: =SUM(AG4:AG95) -> 0 | AH96: =SUM(AH4:AH95) -> 0 | AI96: =SUM(AI4:AI95) -> 0 | AJ96: =SUM(AJ4:AJ95) -> 0

Sheet Sistemas de Refrigeração
A1: Unidade Consumidora | D1: SITUAÇÃO ATUAL | U1: SISTEMA PROPOSTO | AI1: RESULTADOS ESPERADOS
A2: Unidade consumidora (Número da conta contrato) | B2: Pavimento | C2: Ambiente | D2: Tipo de equipamento / tecnologia | E2: Porte | F2: Estado de Conservação | G2: Descrição do Sistema | H2: Potência nominal (W) | I2: Fator de utilização | J2: Potência média utilizada (kW) | K2: Quantidade | L2: Funcionamento (h/dia) | M2: Funcionamento (h/ano) | N2: Meses no ano, de utilização do Sistema | O2: Dias no mês, de utilização do Sistema | P2: Dias úteis no mês, de utilização do Sistema | Q2: Horas por dia, de utilização do Sistema no horário de Ponta (horas) | R2: Fator de coincidência na ponta | S2: Energia consumida (MWh/ano) | T2: Demanda média na ponta (kW) | U2: Tipo de equipamento / tecnologia | V2: Porte | W2: Potência nominal (W) | X2: Fator de utilização | Y2: Potência média utilizada (W) | Z2: Quantidade | AA2: Preço Unitário (R$) | AB2: Funcionamento (h/ano) | AC2: Meses no ano, de utilização do Sistema no horário de Ponta (meses) | AD2: Dias úteis no mês, de utilização do Sistema no horário de Ponta (dias) | AE2: Horas por dia, de utilização do Sistema no horário de Ponta (horas) | AF2: Fator de coincidência na ponta | AG2: Energia consumida (MWh/ano) | AH2: Demanda média na ponta (kW) | AI2: Redução de demanda na ponta (kW) | AJ2: Energia economizada (MWh/ano) | AK2: Investimento (R$) | AL2: Redução de consumo proposto em relação ao consumo total da UC (%)
A3: =IF(UC_DADOS!$B$2=0,"",UC_DADOS!$B$2) -> #N/A | J3: =(H3*I3)/1000 -> 0 | M3: =L3*N3*O3 -> 0 | P3: 21.25 | R3: =N3*P3*Q3/765 -> 0 | S3: =(J3*M3)/1000 -> 0 | T3: =J3*R3 -> 0 | U3: {=IF(F3="Ruim",IFERROR(INDEX('EQUIPAMENTOS_EFICIENTES (BDD)'!O:O,MATCH(1,('EQUIPAMENTOS_EFICIENTES (BDD)'!O:O=D3)*('EQUIPAMENTOS_EFICIENTES (BDD)'!T:T=E3),0)),""),D3)} -> 0 | V3: =E3 -> 0 | W3: {=IF(F3="Ruim",IFERROR(INDEX('EQUIPAMENTOS_EFICIENTES (BDD)'!Q:Q,MATCH(1,('EQUIPAMENTOS_EFICIENTES (BDD)'!O:O=D3)*('EQUIPAMENTOS_EFICIENTES (BDD)'!T:T=E3),0)),H3),H3)} -> 0 | X3: {=IF(F3="Ruim",IFERROR(INDEX('EQUIPAMENTOS_EFICIENTES (BDD)'!S:S,MATCH(1,('EQUIPAMENTOS_EFICIENTES (BDD)'!O:O=D3)*('EQUIPAMENTOS_EFICIENTES (BDD)'!T:T=E3),0)),I3),I3)} -> 0 | Y3: =(X3*W3)/1000 -> 0 | Z3: =K3 -> 0 | AA3: {=IF(F3="Ruim",IFERROR(INDEX('EQUIPAMENTOS_EFICIENTES (BDD)'!U:U,MATCH(1,('EQUIPAMENTOS_EFICIENTES (BDD)'!O:O=D3)*('EQUIPAMENTOS_EFICIENTES (BDD)'!T:T=E3),0)),0),0)} -> 0 | AB3: =M3 -> 0 | AC3: =N3 -> 0 | AD3: =P3 -> 21.25 | AE3: =Q3 -> 0 | AF3: =R3 -> 0 | AG3: =(AB3*Y3)/1000 -> 0 | AH3: =AF3*Y3/1000 -> 0 | AI3: =T3-AH3 -> 0 | AJ3: =(S3-AG3) -> 0 | AK3: =IF(AJ3>0,Z3*AA3,0) -> 0 | AL3: =AJ3/478.332 -> 0
A4: =IF(UC_DADOS!$B$2=0,"",UC_DADOS!$B$2) -> #N/A | J4: =(H4*I4)/1000 -> 0 | M4: =L4*N4*O4 -> 0 | P4: 21.25 | R4: =N4*P4*Q4/765 -> 0 | S4: =(J4*M4)/1000 -> 0 | T4: =J4*R4 -> 0 | U4: {=IF(F4="Ruim",IFERROR(INDEX('EQUIPAMENTOS_EFICIENTES (BDD)'!O:O,MATCH(1,('EQUIPAMENTOS_EFICIENTES (BDD)'!O:O=D4)*('EQUIPAMENTOS_EFICIENTES (BDD)'!T:T=E4),0)),""),D4)} -> 0 | V4: =E4 -> 0 | W4: {=IF(F4="Ruim",IFERROR(INDEX('EQUIPAMENTOS_EFICIENTES (BDD)'!Q:Q,MATCH(1,('EQUIPAMENTOS_EFICIENTES (BDD)'!O:O=D4)*('EQUIPAMENTOS_EFICIENTES (BDD)'!T:T=E4),0)),H4),H4)} -> 0 | X4: {=IF(F4="Ruim",IFERROR(INDEX('EQUIPAMENTOS_EFICIENTES (BDD)'!S:S,MATCH(1,('EQUIPAMENTOS_EFICIENTES (BDD)'!O:O=D4)*('EQUIPAMENTOS_EFICIENTES (BDD)'!T:T=E4),0)),I4),I4)} -> 0 | Y4: =(X4*W4)/1000 -> 0 | Z4: =K4 -> 0 | AA4: {=IF(F4="Ruim",IFERROR(INDEX('EQUIPAMENTOS_EFICIENTES (BDD)'!U:U,MATCH(1,('EQUIPAMENTOS_EFICIENTES (BDD)'!O:O=D4)*('EQUIPAMENTOS_EFICIENTES (BDD)'!T:T=E4),0)),0),0)} -> 0 | AB4: =M4 -> 0 | AC4: =N4 -> 0 | AD4: =P4 -> 21.25 | AE4: =Q4 -> 0 | AF4: =R4 -> 0 | AG4: =(AB4*Y4)/1000 -> 0 | AH4: =AF4*Y4/1000 -> 0 | AI4: =T4-AH4 -> 0 | AJ4: =(S4-AG4) -> 0 | AK4: =IF(AJ4>0,Z4*AA4,0) -> 0 | AL4: =AJ4/478.332 -> 0
A5: =IF(UC_DADOS!$B$2=0,"",UC_DADOS!$B$2) -> #N/A | J5: =(H5*I5)/1000 -> 0 | M5: =L5*N5*O5 -> 0 | P5: 21.25 | R5: =N5*P5*Q5/765 -> 0 | S5: =(J5*M5)/1000 -> 0 | T5: =J5*R5 -> 0 | U5: {=IF(F5="Ruim",IFERROR(INDEX('EQUIPAMENTOS_EFICIENTES (BDD)'!O:O,MATCH(1,('EQUIPAMENTOS_EFICIENTES (BDD)'!O:O=D5)*('EQUIPAMENTOS_EFICIENTES (BDD)'!T:T=E5),0)),""),D5)} -> 0 | V5: =E5 -> 0 | W5: {=IF(F5="Ruim",IFERROR(INDEX('EQUIPAMENTOS_EFICIENTES (BDD)'!Q:Q,MATCH(1,('EQUIPAMENTOS_EFICIENTES (BDD)'!O:O=D5)*('EQUIPAMENTOS_EFICIENTES (BDD)'!T:T=E5),0)),H5),H5)} -> 0 | X5: {=IF(F5="Ruim",IFERROR(INDEX('EQUIPAMENTOS_EFICIENTES (BDD)'!S:S,MATCH(1,('EQUIPAMENTOS_EFICIENTES (BDD)'!O:O=D5)*('EQUIPAMENTOS_EFICIENTES (BDD)'!T:T=E5),0)),I5),I5)} -> 0 | Y5: =(X5*W5)/1000 -> 0 | Z5: =K5 -> 0 | AA5: {=IF(F5="Ruim",IFERROR(INDEX('EQUIPAMENTOS_EFICIENTES (BDD)'!U:U,MATCH(1,('EQUIPAMENTOS_EFICIENTES (BDD)'!O:O=D5)*('EQUIPAMENTOS_EFICIENTES (BDD)'!T:T=E5),0)),0),0)} -> 0 | AB5: =M5 -> 0 | AC5: =N5 -> 0 | AD5: =P5 -> 21.25 | AE5: =Q5 -> 0 | AF5: =R5 -> 0 | AG5: =(AB5*Y5)/1000 -> 0 | AH5: =AF5*Y5/1000 -> 0 | AI5: =T5-AH5 -> 0 | AJ5: =(S5-AG5) -> 0 | AK5: =IF(AJ5>0,Z5*AA5,0) -> 0 | AL5: =AJ5/478.332 -> 0
A6: =IF(UC_DADOS!$B$2=0,"",UC_DADOS!$B$2) -> #N/A | J6: =(H6*I6)/1000 -> 0 | M6: =L6*N6*O6 -> 0 | P6: 21.25 | R6: =N6*P6*Q6/765 -> 0 | S6: =(J6*M6)/1000 -> 0 | T6: =J6*R6 -> 0 | U6: {=IF(F6="Ruim",IFERROR(INDEX('EQUIPAMENTOS_EFICIENTES (BDD)'!O:O,MATCH(1,('EQUIPAMENTOS_EFICIENTES (BDD)'!O:O=D6)*('EQUIPAMENTOS_EFICIENTES (BDD)'!T:T=E6),0)),""),D6)} -> 0 | V6: =E6 -> 0 | W6: {=IF(F6="Ruim",IFERROR(INDEX('EQUIPAMENTOS_EFICIENTES (BDD)'!Q:Q,MATCH(1,('EQUIPAMENTOS_EFICIENTES (BDD)'!O:O=D6)*('EQUIPAMENTOS_EFICIENTES (BDD)'!T:T=E6),0)),H6),H6)} -> 0 | X6: {=IF(F6="Ruim",IFERROR(INDEX('EQUIPAMENTOS_EFICIENTES (BDD)'!S:S,MATCH(1,('EQUIPAMENTOS_EFICIENTES (BDD)'!O:O=D6)*('EQUIPAMENTOS_EFICIENTES (BDD)'!T:T=E6),0)),I6),I6)} -> 0 | Y6: =(X6*W6)/1000 -> 0 | Z6: =K6 -> 0 | AA6: {=IF(F6="Ruim",IFERROR(INDEX('EQUIPAMENTOS_EFICIENTES (BDD)'!U:U,MATCH(1,('EQUIPAMENTOS_EFICIENTES (BDD)'!O:O=D6)*('EQUIPAMENTOS_EFICIENTES (BDD)'!T:T=E6),0)),0),0)} -> 0 | AB6: =M6 -> 0 | AC6: =N6 -> 0 | AD6: =P6 -> 21.25 | AE6: =Q6 -> 0 | AF6: =R6 -> 0 | AG6: =(AB6*Y6)/1000 -> 0 | AH6: =AF6*Y6/1000 -> 0 | AI6: =T6-AH6 -> 0 | AJ6: =(S6-AG6) -> 0 | AK6: =IF(AJ6>0,Z6*AA6,0) -> 0 | AL6: =AJ6/478.332 -> 0
A7: =IF(UC_DADOS!$B$2=0,"",UC_DADOS!$B$2) -> #N/A | J7: =(H7*I7)/1000 -> 0 | M7: =L7*N7*O7 -> 0 | P7: 21.25 | R7: =N7*P7*Q7/765 -> 0 | S7: =(J7*M7)/1000 -> 0 | T7: =J7*R7 -> 0 | U7: {=IF(F7="Ruim",IFERROR(INDEX('EQUIPAMENTOS_EFICIENTES (BDD)'!O:O,MATCH(1,('EQUIPAMENTOS_EFICIENTES (BDD)'!O:O=D7)*('EQUIPAMENTOS_EFICIENTES (BDD)'!T:T=E7),0)),""),D7)} -> 0 | V7: =E7 -> 0 | W7: {=IF(F7="Ruim",IFERROR(INDEX('EQUIPAMENTOS_EFICIENTES (BDD)'!Q:Q,MATCH(1,('EQUIPAMENTOS_EFICIENTES (BDD)'!O:O=D7)*('EQUIPAMENTOS_EFICIENTES (BDD)'!T:T=E7),0)),H7),H7)} -> 0 | X7: {=IF(F7="Ruim",IFERROR(INDEX('EQUIPAMENTOS_EFICIENTES (BDD)'!S:S,MATCH(1,('EQUIPAMENTOS_EFICIENTES (BDD)'!O:O=D7)*('EQUIPAMENTOS_EFICIENTES (BDD)'!T:T=E7),0)),I7),I7)} -> 0 | Y7: =(X7*W7)/1000 -> 0 | Z7: =K7 -> 0 | AA7: {=IF(F7="Ruim",IFERROR(INDEX('EQUIPAMENTOS_EFICIENTES (BDD)'!U:U,MATCH(1,('EQUIPAMENTOS_EFICIENTES (BDD)'!O:O=D7)*('EQUIPAMENTOS_EFICIENTES (BDD)'!T:T=E7),0)),0),0)} -> 0 | AB7: =M7 -> 0 | AC7: =N7 -> 0 | AD7: =P7 -> 21.25 | AE7: =Q7 -> 0 | AF7: =R7 -> 0 | AG7: =(AB7*Y7)/1000 -> 0 | AH7: =AF7*Y7/1000 -> 0 | AI7: =T7-AH7 -> 0 | AJ7: =(S7-AG7) -> 0 | AK7: =IF(AJ7>0,Z7*AA7,0) -> 0 | AL7: =AJ7/478.332 -> 0
A8: =IF(UC_DADOS!$B$2=0,"",UC_DADOS!$B$2) -> #N/A | J8: =(H8*I8)/1000 -> 0 | M8: =L8*N8*O8 -> 0 | P8: 21.25 | R8: =N8*P8*Q8/765 -> 0 | S8: =(J8*M8)/1000 -> 0 | T8: =J8*R8 -> 0 | U8: {=IF(F8="Ruim",IFERROR(INDEX('EQUIPAMENTOS_EFICIENTES (BDD)'!O:O,MATCH(1,('EQUIPAMENTOS_EFICIENTES (BDD)'!O:O=D8)*('EQUIPAMENTOS_EFICIENTES (BDD)'!T:T=E8),0)),""),D8)} -> 0 | V8: =E8 -> 0 | W8: {=IF(F8="Ruim",IFERROR(INDEX('EQUIPAMENTOS_EFICIENTES (BDD)'!Q:Q,MATCH(1,('EQUIPAMENTOS_EFICIENTES (BDD)'!O:O=D8)*('EQUIPAMENTOS_EFICIENTES (BDD)'!T:T=E8),0)),H8),H8)} -> 0 | X8: {=IF(F8="Ruim",IFERROR(INDEX('EQUIPAMENTOS_EFICIENTES (BDD)'!S:S,MATCH(1,('EQUIPAMENTOS_EFICIENTES (BDD)'!O:O=D8)*('EQUIPAMENTOS_EFICIENTES (BDD)'!T:T=E8),0)),I8),I8)} -> 0 | Y8: =(X8*W8)/1000 -> 0 | Z8: =K8 -> 0 | AA8: {=IF(F8="Ruim",IFERROR(INDEX('EQUIPAMENTOS_EFICIENTES (BDD)'!U:U,MATCH(1,('EQUIPAMENTOS_EFICIENTES (BDD)'!O:O=D8)*('EQUIPAMENTOS_EFICIENTES (BDD)'!T:T=E8),0)),0),0)} -> 0 | AB8: =M8 -> 0 | AC8: =N8 -> 0 | AD8: =P8 -> 21.25 | AE8: =Q8 -> 0 | AF8: =R8 -> 0 | AG8: =(AB8*Y8)/1000 -> 0 | AH8: =AF8*Y8/1000 -> 0 | AI8: =T8-AH8 -> 0 | AJ8: =(S8-AG8) -> 0 | AK8: =IF(AJ8>0,Z8*AA8,0) -> 0 | AL8: =AJ8/478.332 -> 0
A9: =IF(UC_DADOS!$B$2=0,"",UC_DADOS!$B$2) -> #N/A | J9: =(H9*I9)/1000 -> 0 | M9: =L9*N9*O9 -> 0 | P9: 21.25 | R9: =N9*P9*Q9/765 -> 0 | S9: =(J9*M9)/1000 -> 0 | T9: =J9*R9 -> 0 | U9: {=IF(F9="Ruim",IFERROR(INDEX('EQUIPAMENTOS_EFICIENTES (BDD)'!O:O,MATCH(1,('EQUIPAMENTOS_EFICIENTES (BDD)'!O:O=D9)*('EQUIPAMENTOS_EFICIENTES (BDD)'!T:T=E9),0)),""),D9)} -> 0 | V9: =E9 -> 0 | W9: {=IF(F9="Ruim",IFERROR(INDEX('EQUIPAMENTOS_EFICIENTES (BDD)'!Q:Q,MATCH(1,('EQUIPAMENTOS_EFICIENTES (BDD)'!O:O=D9)*('EQUIPAMENTOS_EFICIENTES (BDD)'!T:T=E9),0)),H9),H9)} -> 0 | X9: {=IF(F9="Ruim",IFERROR(INDEX('EQUIPAMENTOS_EFICIENTES (BDD)'!S:S,MATCH(1,('EQUIPAMENTOS_EFICIENTES (BDD)'!O:O=D9)*('EQUIPAMENTOS_EFICIENTES (BDD)'!T:T=E9),0)),I9),I9)} -> 0 | Y9: =(X9*W9)/1000 -> 0 | Z9: =K9 -> 0 | AA9: {=IF(F9="Ruim",IFERROR(INDEX('EQUIPAMENTOS_EFICIENTES (BDD)'!U:U,MATCH(1,('EQUIPAMENTOS_EFICIENTES (BDD)'!O:O=D9)*('EQUIPAMENTOS_EFICIENTES (BDD)'!T:T=E9),0)),0),0)} -> 0 | AB9: =M9 -> 0 | AC9: =N9 -> 0 | AD9: =P9 -> 21.25 | AE9: =Q9 -> 0 | AF9: =R9 -> 0 | AG9: =(AB9*Y9)/1000 -> 0 | AH9: =AF9*Y9/1000 -> 0 | AI9: =T9-AH9 -> 0 | AJ9: =(S9-AG9) -> 0 | AK9: =IF(AJ9>0,Z9*AA9,0) -> 0 | AL9: =AJ9/478.332 -> 0
A10: =IF(UC_DADOS!$B$2=0,"",UC_DADOS!$B$2) -> #N/A | J10: =(H10*I10)/1000 -> 0 | M10: =L10*N10*O10 -> 0 | P10: 21.25 | R10: =N10*P10*Q10/765 -> 0 | S10: =(J10*M10)/1000 -> 0 | T10: =J10*R10 -> 0 | U10: {=IF(F10="Ruim",IFERROR(INDEX('EQUIPAMENTOS_EFICIENTES (BDD)'!O:O,MATCH(1,('EQUIPAMENTOS_EFICIENTES (BDD)'!O:O=D10)*('EQUIPAMENTOS_EFICIENTES (BDD)'!T:T=E10),0)),""),D10)} -> 0 | V10: =E10 -> 0 | W10: {=IF(F10="Ruim",IFERROR(INDEX('EQUIPAMENTOS_EFICIENTES (BDD)'!Q:Q,MATCH(1,('EQUIPAMENTOS_EFICIENTES (BDD)'!O:O=D10)*('EQUIPAMENTOS_EFICIENTES (BDD)'!T:T=E10),0)),H10),H10)} -> 0 | X10: {=IF(F10="Ruim",IFERROR(INDEX('EQUIPAMENTOS_EFICIENTES (BDD)'!S:S,MATCH(1,('EQUIPAMENTOS_EFICIENTES (BDD)'!O:O=D10)*('EQUIPAMENTOS_EFICIENTES (BDD)'!T:T=E10),0)),I10),I10)} -> 0 | Y10: =(X10*W10)/1000 -> 0 | Z10: =K10 -> 0 | AA10: {=IF(F10="Ruim",IFERROR(INDEX('EQUIPAMENTOS_EFICIENTES (BDD)'!U:U,MATCH(1,('EQUIPAMENTOS_EFICIENTES (BDD)'!O:O=D10)*('EQUIPAMENTOS_EFICIENTES (BDD)'!T:T=E10),0)),0),0)} -> 0 | AB10: =M10 -> 0 | AC10: =N10 -> 0 | AD10: =P10 -> 21.25 | AE10: =Q10 -> 0 | AF10: =R10 -> 0 | AG10: =(AB10*Y10)/1000 -> 0 | AH10: =AF10*Y10/1000 -> 0 | AI10: =T10-AH10 -> 0 | AJ10: =(S10-AG10) -> 0 | AK10: =IF(AJ10>0,Z10*AA10,0) -> 0 | AL10: =AJ10/478.332 -> 0
A11: =IF(UC_DADOS!$B$2=0,"",UC_DADOS!$B$2) -> #N/A | J11: =(H11*I11)/1000 -> 0 | M11: =L11*N11*O11 -> 0 | P11: 21.25 | R11: =N11*P11*Q11/765 -> 0 | S11: =(J11*M11)/1000 -> 0 | T11: =J11*R11 -> 0 | U11: {=IF(F11="Ruim",IFERROR(INDEX('EQUIPAMENTOS_EFICIENTES (BDD)'!O:O,MATCH(1,('EQUIPAMENTOS_EFICIENTES (BDD)'!O:O=D11)*('EQUIPAMENTOS_EFICIENTES (BDD)'!T:T=E11),0)),""),D11)} -> 0 | V11: =E11 -> 0 | W11: {=IF(F11="Ruim",IFERROR(INDEX('EQUIPAMENTOS_EFICIENTES (BDD)'!Q:Q,MATCH(1,('EQUIPAMENTOS_EFICIENTES (BDD)'!O:O=D11)*('EQUIPAMENTOS_EFICIENTES (BDD)'!T:T=E11),0)),H11),H11)} -> 0 | X11: {=IF(F11="Ruim",IFERROR(INDEX('EQUIPAMENTOS_EFICIENTES (BDD)'!S:S,MATCH(1,('EQUIPAMENTOS_EFICIENTES (BDD)'!O:O=D11)*('EQUIPAMENTOS_EFICIENTES (BDD)'!T:T=E11),0)),I11),I11)} -> 0 | Y11: =(X11*W11)/1000 -> 0 | Z11: =K11 -> 0 | AA11: {=IF(F11="Ruim",IFERROR(INDEX('EQUIPAMENTOS_EFICIENTES (BDD)'!U:U,MATCH(1,('EQUIPAMENTOS_EFICIENTES (BDD)'!O:O=D11)*('EQUIPAMENTOS_EFICIENTES (BDD)'!T:T=E11),0)),0),0)} -> 0 | AB11: =M11 -> 0 | AC11: =N11 -> 0 | AD11: =P11 -> 21.25 | AE11: =Q11 -> 0 | AF11: =R11 -> 0 | AG11: =(AB11*Y11)/1000 -> 0 | AH11: =AF11*Y11/1000 -> 0 | AI11: =T11-AH11 -> 0 | AJ11: =(S11-AG11) -> 0 | AK11: =IF(AJ11>0,Z11*AA11,0) -> 0 | AL11: =AJ11/478.332 -> 0
A12: =IF(UC_DADOS!$B$2=0,"",UC_DADOS!$B$2) -> #N/A | J12: =(H12*I12)/1000 -> 0 | M12: =L12*N12*O12 -> 0 | P12: 21.25 | R12: =N12*P12*Q12/765 -> 0 | S12: =(J12*M12)/1000 -> 0 | T12: =J12*R12 -> 0 | U12: {=IF(F12="Ruim",IFERROR(INDEX('EQUIPAMENTOS_EFICIENTES (BDD)'!O:O,MATCH(1,('EQUIPAMENTOS_EFICIENTES (BDD)'!O:O=D12)*('EQUIPAMENTOS_EFICIENTES (BDD)'!T:T=E12),0)),""),D12)} -> 0 | V12: =E12 -> 0 | W12: {=IF(F12="Ruim",IFERROR(INDEX('EQUIPAMENTOS_EFICIENTES (BDD)'!Q:Q,MATCH(1,('EQUIPAMENTOS_EFICIENTES (BDD)'!O:O=D12)*('EQUIPAMENTOS_EFICIENTES (BDD)'!T:T=E12),0)),H12),H12)} -> 0 | X12: {=IF(F12="Ruim",IFERROR(INDEX('EQUIPAMENTOS_EFICIENTES (BDD)'!S:S,MATCH(1,('EQUIPAMENTOS_EFICIENTES (BDD)'!O:O=D12)*('EQUIPAMENTOS_EFICIENTES (BDD)'!T:T=E12),0)),I12),I12)} -> 0 | Y12: =(X12*W12)/1000 -> 0 | Z12: =K12 -> 0 | AA12: {=IF(F12="Ruim",IFERROR(INDEX('EQUIPAMENTOS_EFICIENTES (BDD)'!U:U,MATCH(1,('EQUIPAMENTOS_EFICIENTES (BDD)'!O:O=D12)*('EQUIPAMENTOS_EFICIENTES (BDD)'!T:T=E12),0)),0),0)} -> 0 | AB12: =M12 -> 0 | AC12: =N12 -> 0 | AD12: =P12 -> 21.25 | AE12: =Q12 -> 0 | AF12: =R12 -> 0 | AG12: =(AB12*Y12)/1000 -> 0 | AH12: =AF12*Y12/1000 -> 0 | AI12: =T12-AH12 -> 0 | AJ12: =(S12-AG12) -> 0 | AK12: =IF(AJ12>0,Z12*AA12,0) -> 0 | AL12: =AJ12/478.332 -> 0
A13: =IF(UC_DADOS!$B$2=0,"",UC_DADOS!$B$2) -> #N/A | J13: =(H13*I13)/1000 -> 0 | M13: =L13*N13*O13 -> 0 | P13: 21.25 | R13: =N13*P13*Q13/765 -> 0 | S13: =(J13*M13)/1000 -> 0 | T13: =J13*R13 -> 0 | U13: {=IF(F13="Ruim",IFERROR(INDEX('EQUIPAMENTOS_EFICIENTES (BDD)'!O:O,MATCH(1,('EQUIPAMENTOS_EFICIENTES (BDD)'!O:O=D13)*('EQUIPAMENTOS_EFICIENTES (BDD)'!T:T=E13),0)),""),D13)} -> 0 | V13: =E13 -> 0 | W13: {=IF(F13="Ruim",IFERROR(INDEX('EQUIPAMENTOS_EFICIENTES (BDD)'!Q:Q,MATCH(1,('EQUIPAMENTOS_EFICIENTES (BDD)'!O:O=D13)*('EQUIPAMENTOS_EFICIENTES (BDD)'!T:T=E13),0)),H13),H13)} -> 0 | X13: {=IF(F13="Ruim",IFERROR(INDEX('EQUIPAMENTOS_EFICIENTES (BDD)'!S:S,MATCH(1,('EQUIPAMENTOS_EFICIENTES (BDD)'!O:O=D13)*('EQUIPAMENTOS_EFICIENTES (BDD)'!T:T=E13),0)),I13),I13)} -> 0 | Y13: =(X13*W13)/1000 -> 0 | Z13: =K13 -> 0 | AA13: {=IF(F13="Ruim",IFERROR(INDEX('EQUIPAMENTOS_EFICIENTES (BDD)'!U:U,MATCH(1,('EQUIPAMENTOS_EFICIENTES (BDD)'!O:O=D13)*('EQUIPAMENTOS_EFICIENTES (BDD)'!T:T=E13),0)),0),0)} -> 0 | AB13: =M13 -> 0 | AC13: =N13 -> 0 | AD13: =P13 -> 21.25 | AE13: =Q13 -> 0 | AF13: =R13 -> 0 | AG13: =(AB13*Y13)/1000 -> 0 | AH13: =AF13*Y13/1000 -> 0 | AI13: =T13-AH13 -> 0 | AJ13: =(S13-AG13) -> 0 | AK13: =IF(AJ13>0,Z13*AA13,0) -> 0 | AL13: =AJ13/478.332 -> 0
A14: =IF(UC_DADOS!$B$2=0,"",UC_DADOS!$B$2) -> #N/A | J14: =(H14*I14)/1000 -> 0 | M14: =L14*N14*O14 -> 0 | P14: 21.25 | R14: =N14*P14*Q14/765 -> 0 | S14: =(J14*M14)/1000 -> 0 | T14: =J14*R14 -> 0 | U14: {=IF(F14="Ruim",IFERROR(INDEX('EQUIPAMENTOS_EFICIENTES (BDD)'!O:O,MATCH(1,('EQUIPAMENTOS_EFICIENTES (BDD)'!O:O=D14)*('EQUIPAMENTOS_EFICIENTES (BDD)'!T:T=E14),0)),""),D14)} -> 0 | V14: =E14 -> 0 | W14: {=IF(F14="Ruim",IFERROR(INDEX('EQUIPAMENTOS_EFICIENTES (BDD)'!Q:Q,MATCH(1,('EQUIPAMENTOS_EFICIENTES (BDD)'!O:O=D14)*('EQUIPAMENTOS_EFICIENTES (BDD)'!T:T=E14),0)),H14),H14)} -> 0 | X14: {=IF(F14="Ruim",IFERROR(INDEX('EQUIPAMENTOS_EFICIENTES (BDD)'!S:S,MATCH(1,('EQUIPAMENTOS_EFICIENTES (BDD)'!O:O=D14)*('EQUIPAMENTOS_EFICIENTES (BDD)'!T:T=E14),0)),I14),I14)} -> 0 | Y14: =(X14*W14)/1000 -> 0 | Z14: =K14 -> 0 | AA14: {=IF(F14="Ruim",IFERROR(INDEX('EQUIPAMENTOS_EFICIENTES (BDD)'!U:U,MATCH(1,('EQUIPAMENTOS_EFICIENTES (BDD)'!O:O=D14)*('EQUIPAMENTOS_EFICIENTES (BDD)'!T:T=E14),0)),0),0)} -> 0 | AB14: =M14 -> 0 | AC14: =N14 -> 0 | AD14: =P14 -> 21.25 | AE14: =Q14 -> 0 | AF14: =R14 -> 0 | AG14: =(AB14*Y14)/1000 -> 0 | AH14: =AF14*Y14/1000 -> 0 | AI14: =T14-AH14 -> 0 | AJ14: =(S14-AG14) -> 0 | AK14: =IF(AJ14>0,Z14*AA14,0) -> 0 | AL14: =AJ14/478.332 -> 0
... A46: =IF(UC_DADOS!$B$2=0,"",UC_DADOS!$B$2) -> #N/A | J46: =(H46*I46)/1000 -> 0 | M46: =L46*N46*O46 -> 0 | P46: 21.25 | R46: =N46*P46*Q46/765 -> 0 | S46: =(J46*M46)/1000 -> 0 | T46: =J46*R46 -> 0 | U46: {=IF(F46="Ruim",IFERROR(INDEX('EQUIPAMENTOS_EFICIENTES (BDD)'!O:O,MATCH(1,('EQUIPAMENTOS_EFICIENTES (BDD)'!O:O=D46)*('EQUIPAMENTOS_EFICIENTES (BDD)'!T:T=E46),0)),""),D46)} -> 0 | V46: =E46 -> 0 | W46: {=IF(F46="Ruim",IFERROR(INDEX('EQUIPAMENTOS_EFICIENTES (BDD)'!Q:Q,MATCH(1,('EQUIPAMENTOS_EFICIENTES (BDD)'!O:O=D46)*('EQUIPAMENTOS_EFICIENTES (BDD)'!T:T=E46),0)),H46),H46)} -> 0 | X46: {=IF(F46="Ruim",IFERROR(INDEX('EQUIPAMENTOS_EFICIENTES (BDD)'!S:S,MATCH(1,('EQUIPAMENTOS_EFICIENTES (BDD)'!O:O=D46)*('EQUIPAMENTOS_EFICIENTES (BDD)'!T:T=E46),0)),I46),I46)} -> 0 | Y46: =(X46*W46)/1000 -> 0 | Z46: =K46 -> 0 | AA46: {=IF(F46="Ruim",IFERROR(INDEX('EQUIPAMENTOS_EFICIENTES (BDD)'!U:U,MATCH(1,('EQUIPAMENTOS_EFICIENTES (BDD)'!O:O=D46)*('EQUIPAMENTOS_EFICIENTES (BDD)'!T:T=E46),0)),0),0)} -> 0 | AB46: =M46 -> 0 | AC46: =N46 -> 0 | AD46: =P46 -> 21.25 | AE46: =Q46 -> 0 | AF46: =R46 -> 0 | AG46: =(AB46*Y46)/1000 -> 0 | AH46: =AF46*Y46/1000 -> 0 | AI46: =T46-AH46 -> 0 | AJ46: =(S46-AG46) -> 0 | AK46: =IF(AJ46>0,Z46*AA46,0) -> 0 | AL46: =AJ46/478.332 -> 0
D47: TOTAL | J47: =SUBTOTAL(9,J3:J46) -> 0 | K47: =SUBTOTAL(9,K3:K46) -> 0 | S47: =SUBTOTAL(9,S3:S46) -> 0 | T47: =SUBTOTAL(9,T3:T46) -> 0 | Y47: =SUBTOTAL(9,Y3:Y46) -> 0 | Z47: =SUM(Z3:Z46) -> 0 | AA47: =SUBTOTAL(9,AA3:AA46) -> 0 | AG47: =SUBTOTAL(9,AG3:AG46) -> 0 | AH47: =SUBTOTAL(9,AH3:AH46) -> 0 | AI47: =SUM(AI3:AI46) -> 0 | AJ47: =SUM(AJ3:AJ46) -> 0 | AK47: =SUM(AK3:AK46) -> 0 | AL47: =SUM(AL3:AL46) -> 0

Sheet Sistemas Outros
A1: Unidade Consumidora | D1: SITUAÇÃO ATUAL | S1: SISTEMA PROPOSTO | AF1: RESULTADOS ESPERADOS
A2: Unidade consumidora (Número da conta contrato) | B2: Pavimento | C2: Descrição do sistema | D2: Tipo de equipamento / tecnologia | E2: Potência nominal do equipamento (W) | F2: Quantidade | G2: Potência instalada (kW) | H2: Fator de Utilização | I2: Potência média utilizada (kW) | J2: Funcionamento (h/dia) | K2: Meses no ano, de utilização do Sistema | L2: Dias no mês, de utilização do Sistema | M2: Dias úteis no mês, de utilização do Sistema | N2: Funcionamento (h/ano) | O2: Horas por dia, de utilização do Sistema no horário de Ponta | P2: Fator de coincidência na ponta | Q2: Energia consumida (MWh/ano) | R2: Demanda média na ponta (kW) | S2: Tipo de equipamento / tecnologia | T2: Potência nominal do equipamento (W) | U2: Quantidade | V2: Potência instalada (kW) | W2: Fator de Utilização | X2: Funcionamento (h/ano) | Y2: Meses no ano, de utilização do Sistema no horário de Ponta (meses) | Z2: Dias úteis no mês, de utilização do Sistema no horário de Ponta (dias) | AA2: Horas por dia, de utilização do Sistema no horário de Ponta (horas) | AB2: Potência média na ponta (W) | AC2: Fator de coincidência na ponta | AD2: Energia consumida (MWh/ano) | AE2: Demanda média na ponta (kW) | AF2: Redução de demanda na ponta (kW) | AG2: Energia economizada (MWh/ano) | AH2: Redução de consumo proposto em relação ao consumo total da UC (%)
A3: =IF(UC_DADOS!$B$2=0,"",UC_DADOS!$B$2) -> #N/A | G3: =(E3*F3)/1000 -> 0 | H3: 1 | I3: =(G3*H3) -> 0 | M3: 21.25 | N3: =J3*K3*L3 -> 0 | P3: =N3*O3*M3/765 -> 0 | Q3: =(I3*N3)/1000 -> 0 | R3: =P3*I3 -> 0
A4: =IF(UC_DADOS!$B$2=0,"",UC_DADOS!$B$2) -> #N/A | G4: =(E4*F4)/1000 -> 0 | H4: 1 | I4: =(G4*H4) -> 0 | M4: 21.25 | N4: =J4*K4*L4 -> 0 | P4: =N4*O4*M4/765 -> 0 | Q4: =(I4*N4)/1000 -> 0 | R4: =P4*I4 -> 0
A5: =IF(UC_DADOS!$B$2=0,"",UC_DADOS!$B$2) -> #N/A | G5: =(E5*F5)/1000 -> 0 | H5: 1 | I5: =(G5*H5) -> 0 | M5: 21.25 | N5: =J5*K5*L5 -> 0 | P5: =N5*O5*M5/765 -> 0 | Q5: =(I5*N5)/1000 -> 0 | R5: =P5*I5 -> 0
A6: =IF(UC_DADOS!$B$2=0,"",UC_DADOS!$B$2) -> #N/A | G6: =(E6*F6)/1000 -> 0 | H6: 1 | I6: =(G6*H6) -> 0 | M6: 21.25 | N6: =J6*K6*L6 -> 0 | P6: =N6*O6*M6/765 -> 0 | Q6: =(I6*N6)/1000 -> 0 | R6: =P6*I6 -> 0
A7: =IF(UC_DADOS!$B$2=0,"",UC_DADOS!$B$2) -> #N/A | G7: =(E7*F7)/1000 -> 0 | H7: 1 | I7: =(G7*H7) -> 0 | M7: 21.25 | N7: =J7*K7*L7 -> 0 | P7: =N7*O7*M7/765 -> 0 | Q7: =(I7*N7)/1000 -> 0 | R7: =P7*I7 -> 0
A8: =IF(UC_DADOS!$B$2=0,"",UC_DADOS!$B$2) -> #N/A | G8: =(E8*F8)/1000 -> 0 | H8: 1 | I8: =(G8*H8) -> 0 | M8: 21.25 | N8: =J8*K8*L8 -> 0 | P8: =N8*O8*M8/765 -> 0 | Q8: =(I8*N8)/1000 -> 0 | R8: =P8*I8 -> 0
A9: =IF(UC_DADOS!$B$2=0,"",UC_DADOS!$B$2) -> #N/A | G9: =(E9*F9)/1000 -> 0 | H9: 1 | I9: =(G9*H9) -> 0 | M9: 21.25 | N9: =J9*K9*L9 -> 0 | P9: =N9*O9*M9/765 -> 0 | Q9: =(I9*N9)/1000 -> 0 | R9: =P9*I9 -> 0
A10: =IF(UC_DADOS!$B$2=0,"",UC_DADOS!$B$2) -> #N/A | G10: =(E10*F10)/1000 -> 0 | H10: 1 | I10: =(G10*H10) -> 0 | M10: 21.25 | N10: =J10*K10*L10 -> 0 | P10: =N10*O10*M10/765 -> 0 | Q10: =(I10*N10)/1000 -> 0 | R10: =P10*I10 -> 0
A11: =IF(UC_DADOS!$B$2=0,"",UC_DADOS!$B$2) -> #N/A | G11: =(E11*F11)/1000 -> 0 | H11: 1 | I11: =(G11*H11) -> 0 | M11: 21.25 | N11: =J11*K11*L11 -> 0 | P11: =N11*O11*M11/765 -> 0 | Q11: =(I11*N11)/1000 -> 0 | R11: =P11*I11 -> 0
A12: =IF(UC_DADOS!$B$2=0,"",UC_DADOS!$B$2) -> #N/A | G12: =(E12*F12)/1000 -> 0 | H12: 1 | I12: =(G12*H12) -> 0 | M12: 21.25 | N12: =J12*K12*L12 -> 0 | P12: =N12*O12*M12/765 -> 0 | Q12: =(I12*N12)/1000 -> 0 | R12: =P12*I12 -> 0
A13: =IF(UC_DADOS!$B$2=0,"",UC_DADOS!$B$2) -> #N/A | G13: =(E13*F13)/1000 -> 0 | H13: 1 | I13: =(G13*H13) -> 0 | M13: 21.25 | N13: =J13*K13*L13 -> 0 | P13: =N13*O13*M13/765 -> 0 | Q13: =(I13*N13)/1000 -> 0 | R13: =P13*I13 -> 0
A14: =IF(UC_DADOS!$B$2=0,"",UC_DADOS!$B$2) -> #N/A | G14: =(E14*F14)/1000 -> 0 | H14: 1 | I14: =(G14*H14) -> 0 | M14: 21.25 | N14: =J14*K14*L14 -> 0 | P14: =N14*O14*M14/765 -> 0 | Q14: =(I14*N14)/1000 -> 0 | R14: =P14*I14 -> 0
... A52: =IF(UC_DADOS!$B$2=0,"",UC_DADOS!$B$2) -> #N/A | G52: =(E52*F52)/1000 -> 0 | H52: 1 | I52: =(G52*H52) -> 0 | M52: 21.25 | N52: =J52*K52*L52 -> 0 | P52: =N52*O52*M52/765 -> 0 | Q52: =(I52*N52)/1000 -> 0 | R52: =P52*I52 -> 0
F53: =SUM(F3:F52) -> 0 | G53: =SUM(G3:G52) -> 0 | J53: =SUM(J3:J52) -> 0 | Q53: =SUM(Q3:Q52) -> 0 | R53: =SUM(R3:R52) -> 0

Sheet Sistemas de Motor
C1: SITUAÇÃO ATUAL | R1: SISTEMA PROPOSTO | AF1: RESULTADOS ESPERADOS
A2: Unidade consumidora (Número da conta contrato) | B2: Descrição do sistema | C2: Potência do motor (cv) | D2: Carregamento | E2: Rendimento nominal (%) | F2: Rendimento no ponto de carregamento (%) | G2: Quantidade | H2: Potência instalada (kW) | I2: Potência média utilizada (kW) | J2: Funcionamento (h/dia) | K2: Funcionamento (h/ano) | L2: Meses no ano, de utilização do Sistema | M2: Dias úteis no mês, de utilização do Sistema | N2: Horas por dia, de utilização do Sistema no horário de Ponta (horas) | O2: Fator de coincidência na ponta | P2: Energia consumida (MWh/ano) | Q2: Demanda média na ponta (kW) | R2: Potência do motor (cv) | S2: Carregamento | T2: Rendimento nominal (%) | U2: Rendimento no ponto de carregamento (%) | V2: Quantidade | W2: Potência instalada (kW) | X2: Potência média utilizada (kW) | Y2: Funcionamento (h/ano) | Z2: Meses no ano, de utilização do Sistema no horário de Ponta (meses) | AA2: Dias úteis no mês, de utilização do Sistema no horário de Ponta (dias) | AB2: Horas por dia, de utilização do Sistema no horário de Ponta (horas) | AC2: Fator de coincidência na ponta | AD2: Energia consumida (MWh/ano) | AE2: Demanda média na ponta (kW) | AF2: Redução de demanda na ponta (kW) | AG2: Energia economizada (MWh/ano) | AH2: Redução de consumo proposto em relação ao consumo total da UC (%)
A3: =IF(UC_DADOS!$B$2=0,"",UC_DADOS!$B$2) -> #N/A | H3: =C3*0.736*G3 -> 0 | I3: =H3*D3 -> 0 | K3: =J3*L3*M3 -> 0 | O3: =L3*M3*N3/765 -> 0 | P3: =(K3*I3)/1000 -> 0 | Q3: =O3*I3 -> 0 | V3: =G3 -> 0 | W3: =R3*V3*0.736 -> 0 | X3: =W3*S3 -> 0 | Y3: =K3 -> 0 | Z3: =L3 -> 0 | AA3: =M3 -> 0 | AB3: =N3 -> 0 | AC3: =Z3*AA3*AB3/765 -> 0 | AD3: =(Y3*X3)/1000 -> 0 | AE3: =AC3*X3 -> 0 | AF3: =AE3-Q3 -> 0 | AG3: =P3-AD3 -> 0 | AH3: =AG3/1000 -> 0
A4: =IF(UC_DADOS!$B$2=0,"",UC_DADOS!$B$2) -> #N/A | H4: =C4*0.736*G4 -> 0 | I4: =H4*D4 -> 0 | K4: =J4*L4*M4 -> 0 | O4: =L4*M4*N4/765 -> 0 | P4: =(K4*I4)/1000 -> 0 | Q4: =O4*I4 -> 0 | V4: =G4 -> 0 | W4: =R4*V4*0.736 -> 0 | X4: =W4*S4 -> 0 | Y4: =K4 -> 0 | Z4: =L4 -> 0 | AA4: =M4 -> 0 | AB4: =N4 -> 0 | AC4: =Z4*AA4*AB4/765 -> 0 | AD4: =(Y4*X4)/1000 -> 0 | AE4: =AC4*X4 -> 0 | AF4: =AE4-Q4 -> 0 | AG4: =P4-AD4 -> 0 | AH4: =AG4/1000 -> 0
A5: =IF(UC_DADOS!$B$2=0,"",UC_DADOS!$B$2) -> #N/A | H5: =C5*0.736*G5 -> 0 | I5: =H5*D5 -> 0 | K5: =J5*L5*M5 -> 0 | O5: =L5*M5*N5/765 -> 0 | P5: =(K5*I5)/1000 -> 0 | Q5: =O5*I5 -> 0 | V5: =G5 -> 0 | W5: =R5*V5*0.736 -> 0 | X5: =W5*S5 -> 0 | Y5: =K5 -> 0 | Z5: =L5 -> 0 | AA5: =M5 -> 0 | AB5: =N5 -> 0 | AC5: =Z5*AA5*AB5/765 -> 0 | AD5: =(Y5*X5)/1000 -> 0 | AE5: =AC5*X5 -> 0 | AF5: =AE5-Q5 -> 0 | AG5: =P5-AD5 -> 0 | AH5: =AG5/1000 -> 0
A6: =IF(UC_DADOS!$B$2=0,"",UC_DADOS!$B$2) -> #N/A | H6: =C6*0.736*G6 -> 0 | I6: =H6*D6 -> 0 | K6: =J6*L6*M6 -> 0 | O6: =L6*M6*N6/765 -> 0 | P6: =(K6*I6)/1000 -> 0 | Q6: =O6*I6 -> 0 | V6: =G6 -> 0 | W6: =R6*V6*0.736 -> 0 | X6: =W6*S6 -> 0 | Y6: =K6 -> 0 | Z6: =L6 -> 0 | AA6: =M6 -> 0 | AB6: =N6 -> 0 | AC6: =Z6*AA6*AB6/765 -> 0 | AD6: =(Y6*X6)/1000 -> 0 | AE6: =AC6*X6 -> 0 | AF6: =AE6-Q6 -> 0 | AG6: =P6-AD6 -> 0 | AH6: =AG6/1000 -> 0
A7: =IF(UC_DADOS!$B$2=0,"",UC_DADOS!$B$2) -> #N/A | H7: =C7*0.736*G7 -> 0 | I7: =H7*D7 -> 0 | K7: =J7*L7*M7 -> 0 | O7: =L7*M7*N7/765 -> 0 | P7: =(K7*I7)/1000 -> 0 | Q7: =O7*I7 -> 0 | V7: =G7 -> 0 | W7: =R7*V7*0.736 -> 0 | X7: =W7*S7 -> 0 | Y7: =K7 -> 0 | Z7: =L7 -> 0 | AA7: =M7 -> 0 | AB7: =N7 -> 0 | AC7: =Z7*AA7*AB7/765 -> 0 | AD7: =(Y7*X7)/1000 -> 0 | AE7: =AC7*X7 -> 0 | AF7: =AE7-Q7 -> 0 | AG7: =P7-AD7 -> 0 | AH7: =AG7/1000 -> 0
A8: =IF(UC_DADOS!$B$2=0,"",UC_DADOS!$B$2) -> #N/A | H8: =C8*0.736*G8 -> 0 | I8: =H8*D8 -> 0 | K8: =J8*L8*M8 -> 0 | O8: =L8*M8*N8/765 -> 0 | P8: =(K8*I8)/1000 -> 0 | Q8: =O8*I8 -> 0 | V8: =G8 -> 0 | W8: =R8*V8*0.736 -> 0 | X8: =W8*S8 -> 0 | Y8: =K8 -> 0 | Z8: =L8 -> 0 | AA8: =M8 -> 0 | AB8: =N8 -> 0 | AC8: =Z8*AA8*AB8/765 -> 0 | AD8: =(Y8*X8)/1000 -> 0 | AE8: =AC8*X8 -> 0 | AF8: =AE8-Q8 -> 0 | AG8: =P8-AD8 -> 0 | AH8: =AG8/1000 -> 0
A9: =IF(UC_DADOS!$B$2=0,"",UC_DADOS!$B$2) -> #N/A | H9: =C9*0.736*G9 -> 0 | I9: =H9*D9 -> 0 | K9: =J9*L9*M9 -> 0 | O9: =L9*M9*N9/765 -> 0 | P9: =(K9*I9)/1000 -> 0 | Q9: =O9*I9 -> 0 | V9: =G9 -> 0 | W9: =R9*V9*0.736 -> 0 | X9: =W9*S9 -> 0 | Y9: =K9 -> 0 | Z9: =L9 -> 0 | AA9: =M9 -> 0 | AB9: =N9 -> 0 | AC9: =Z9*AA9*AB9/765 -> 0 | AD9: =(Y9*X9)/1000 -> 0 | AE9: =AC9*X9 -> 0 | AF9: =AE9-Q9 -> 0 | AG9: =P9-AD9 -> 0 | AH9: =AG9/1000 -> 0
A10: =IF(UC_DADOS!$B$2=0,"",UC_DADOS!$B$2) -> #N/A | H10: =C10*0.736*G10 -> 0 | I10: =H10*D10 -> 0 | K10: =J10*L10*M10 -> 0 | O10: =L10*M10*N10/765 -> 0 | P10: =(K10*I10)/1000 -> 0 | Q10: =O10*I10 -> 0 | V10: =G10 -> 0 | W10: =R10*V10*0.736 -> 0 | X10: =W10*S10 -> 0 | Y10: =K10 -> 0 | Z10: =L10 -> 0 | AA10: =M10 -> 0 | AB10: =N10 -> 0 | AC10: =Z10*AA10*AB10/765 -> 0 | AD10: =(Y10*X10)/1000 -> 0 | AE10: =AC10*X10 -> 0 | AF10: =AE10-Q10 -> 0 | AG10: =P10-AD10 -> 0 | AH10: =AG10/1000 -> 0
A11: =IF(UC_DADOS!$B$2=0,"",UC_DADOS!$B$2) -> #N/A | H11: =C11*0.736*G11 -> 0 | I11: =H11*D11 -> 0 | K11: =J11*L11*M11 -> 0 | O11: =L11*M11*N11/765 -> 0 | P11: =(K11*I11)/1000 -> 0 | Q11: =O11*I11 -> 0 | V11: =G11 -> 0 | W11: =R11*V11*0.736 -> 0 | X11: =W11*S11 -> 0 | Y11: =K11 -> 0 | Z11: =L11 -> 0 | AA11: =M11 -> 0 | AB11: =N11 -> 0 | AC11: =Z11*AA11*AB11/765 -> 0 | AD11: =(Y11*X11)/1000 -> 0 | AE11: =AC11*X11 -> 0 | AF11: =AE11-Q11 -> 0 | AG11: =P11-AD11 -> 0 | AH11: =AG11/1000 -> 0
A12: =IF(UC_DADOS!$B$2=0,"",UC_DADOS!$B$2) -> #N/A | H12: =C12*0.736*G12 -> 0 | I12: =H12*D12 -> 0 | K12: =J12*L12*M12 -> 0 | O12: =L12*M12*N12/765 -> 0 | P12: =(K12*I12)/1000 -> 0 | Q12: =O12*I12 -> 0 | V12: =G12 -> 0 | W12: =R12*V12*0.736 -> 0 | X12: =W12*S12 -> 0 | Y12: =K12 -> 0 | Z12: =L12 -> 0 | AA12: =M12 -> 0 | AB12: =N12 -> 0 | AC12: =Z12*AA12*AB12/765 -> 0 | AD12: =(Y12*X12)/1000 -> 0 | AE12: =AC12*X12 -> 0 | AF12: =AE12-Q12 -> 0 | AG12: =P12-AD12 -> 0 | AH12: =AG12/1000 -> 0
A13: =IF(UC_DADOS!$B$2=0,"",UC_DADOS!$B$2) -> #N/A | H13: =C13*0.736*G13 -> 0 | I13: =H13*D13 -> 0 | K13: =J13*L13*M13 -> 0 | O13: =L13*M13*N13/765 -> 0 | P13: =(K13*I13)/1000 -> 0 | Q13: =O13*I13 -> 0 | V13: =G13 -> 0 | W13: =R13*V13*0.736 -> 0 | X13: =W13*S13 -> 0 | Y13: =K13 -> 0 | Z13: =L13 -> 0 | AA13: =M13 -> 0 | AB13: =N13 -> 0 | AC13: =Z13*AA13*AB13/765 -> 0 | AD13: =(Y13*X13)/1000 -> 0 | AE13: =AC13*X13 -> 0 | AF13: =AE13-Q13 -> 0 | AG13: =P13-AD13 -> 0 | AH13: =AG13/1000 -> 0
A14: =IF(UC_DADOS!$B$2=0,"",UC_DADOS!$B$2) -> #N/A | H14: =C14*0.736*G14 -> 0 | I14: =H14*D14 -> 0 | K14: =J14*L14*M14 -> 0 | O14: =L14*M14*N14/765 -> 0 | P14: =(K14*I14)/1000 -> 0 | Q14: =O14*I14 -> 0 | V14: =G14 -> 0 | W14: =R14*V14*0.736 -> 0 | X14: =W14*S14 -> 0 | Y14: =K14 -> 0 | Z14: =L14 -> 0 | AA14: =M14 -> 0 | AB14: =N14 -> 0 | AC14: =Z14*AA14*AB14/765 -> 0 | AD14: =(Y14*X14)/1000 -> 0 | AE14: =AC14*X14 -> 0 | AF14: =AE14-Q14 -> 0 | AG14: =P14-AD14 -> 0 | AH14: =AG14/1000 -> 0
... A58: =IF(UC_DADOS!$B$2=0,"",UC_DADOS!$B$2) -> #N/A | H58: =C58*0.736*G58 -> 0 | I58: =H58*D58 -> 0 | K58: =J58*L58*M58 -> 0 | O58: =L58*M58*N58/765 -> 0 | P58: =(K58*I58)/1000 -> 0 | Q58: =O58*I58 -> 0 | V58: =G58 -> 0 | W58: =R58*V58*0.736 -> 0 | X58: =W58*S58 -> 0 | Y58: =K58 -> 0 | Z58: =L58 -> 0 | AA58: =M58 -> 0 | AB58: =N58 -> 0 | AC58: =Z58*AA58*AB58/765 -> 0 | AD58: =(Y58*X58)/1000 -> 0 | AE58: =AC58*X58 -> 0 | AF58: =AE58-Q58 -> 0 | AG58: =P58-AD58 -> 0 | AH58: =AG58/1000 -> 0
B59: TOTAL | C59: =SUM(C3:C58) -> 0 | G59: =SUM(G3:G58) -> 0 | H59: =SUM(H3:H58) -> 0 | I59: =SUM(I3:I58) -> 0 | P59: =SUM(P3:P58) -> 0 | Q59: =SUM(Q3:Q58) -> 0 | R59: =SUM(R3:R58) -> 0 | V59: =SUM(V3:V58) -> 0 | W59: =SUM(W3:W58) -> 0 | X59: =SUM(X3:X58) -> 0 | AD59: =SUM(AD3:AD58) -> 0 | AE59: =SUM(AE3:AE58) -> 0 | AF59: =SUM(AF3:AF58) -> 0 | AG59: =SUM(AG3:AG58) -> 0 | AH59: =SUM(AH3:AH58) -> 0

Sheet TABELAS_RESUMO
A1: Uso Final | B1: Medida Proposta | C1: Economia (MWh/ano) | D1: Redução de demanda (kW) | E1: Investimento (R$) | F1: Prioridade
A2: iluminação | B2: Substituição por LED e sensores de presença
A3: Climatização | B3: Troca de aparelhos de ar-condicionado e automação
A4: Motores | B4: Substituição por motores de alto rendimento
A5: Refrigeração | B5: Substituição de equipamentos antigos
A6: Aquecimento de água | B6: Instalação de sistema solar térmico
A7: Fotovoltaico | B7: Implantação de sistema de geração distribuída
A10: Uso final | B10: Medida Proposta | C10: Economia (MWh/ano) | D10: Invest. Total (R$) | E10: PB (Anos)
A12: Iluminação | B12: Substituição por LED e sensores | E12: =IFERROR(IF(D12="","",D12/(C12*'Análise Econômica'!E4)),"")
A13: Climatização | B13: Troca de aparelhos de ar-condicionado e automação | E13: =IFERROR(IF(D13="","",D13/(C13*'Análise Econômica'!E4)),"")
A14: Motores | B14: Substituição por motores de alto rendimento | E14: =IFERROR(IF(D14="","",D14/(C14*'Análise Econômica'!E4)),"")
A15: Refrigeração | B15: Troca de refrigeradores comerciais ineficientes | E15: =IFERROR(IF(D15="","",D15/(C15*'Análise Econômica'!E4)),"")
A16: Geração fotovoltaica | B16: Sistema conectado à rede (GD) | E16: =IFERROR(IF(D16="","",D16/(C16*'Análise Econômica'!E4)),"")
A17: Total | E17: =IFERROR(IF(D17=0,"",D17/(C17*'Análise Econômica'!E4)),"")

Sheet TABELAS_RESUMO_2
C3: Sistema de Iluminação | G3: Sistema de Refrigeração
C4: Sistema Atual | G4: Sistema Atual
C5: O sistema composto por luminárias LED, porém sem automação para acionamento e desligamento programado. | G5: Sistemas de Refrigeração com baixo índice de eficiência energética e com estado de conservação insatisfatório
C6: Potência Total (kW) | D6: ='Sistemas de Iluminação'!J96 -> 0 | G6: Potência Total (kW) | H6: ='Sistemas de Refrigeração'!J47 -> 0
C7: Consumo de Energia Anual (MWh) | D7: ='Sistemas de Iluminação'!R96 -> 0 | G7: Consumo de Energia Anual (MWh) | H7: ='Sistemas de Refrigeração'!S47 -> 0
C8: Despesa Mensal com Energia Elétrica | D8: =(D7*'Análise Econômica'!E4)/12 -> #VALUE! | G8: Despesa Mensal com Energia Elétrica | H8: =(H7*'Análise Econômica'!E4)/12 -> #VALUE!
C9: Sistema Proposto | G9: Sistema Proposto
C10: Instalação da automação para acionamento e desligamento programado. | G10: Instalação de Sistemas de Refrigeração com alto índice de eficiência energética
C11: Potência Total (kW) | D11: =D6 -> 0 | G11: Potência Total (kW) | H11: ='Sistemas de Refrigeração'!Y47 -> 0
C12: Consumo de Energia Anual (MWh) | D12: =D7*(1-'Análise Econômica'!K4) -> 0 | G12: Consumo de Energia Anual (MWh) | H12: ='Sistemas de Refrigeração'!AG47 -> 0
C13: Despesa mensal com Energia Elétrica | D13: =(D12*'Análise Econômica'!E4)/12 -> #VALUE! | G13: Despesa mensal com Energia Elétrica | H13: =(H12*'Análise Econômica'!E4)/12 -> #VALUE!
C14: Resultados Previstos | G14: Resultados Previstos
C15: Redução de Demanda (kW) | D15: =D6-D11 -> 0 | G15: Redução de Demanda (kW) | H15: =H6-H11 -> 0
C16: Redução do Consumo de Energia Anual (MWh) | D16: =D7-D12 -> 0 | G16: Redução do Consumo de Energia Anual (MWh) | H16: =H7-H12 -> 0
C17: Redução Percentual do Consumo de Energia % | D17: =D16/D7 -> #DIV/0! | G17: Redução Percentual do Consumo de Energia % | H17: =H16/H7 -> #DIV/0!
C18: Economia Mensal na Fatura de Energia | D18: =D8-D13 -> #VALUE! | G18: Economia Mensal na Fatura de Energia | H18: =H8-H13 -> #VALUE!
C19: Investimento Necessário Estimado | D19: =-'Análise Econômica'!B39 -> 299.9 | G19: Investimento Necessário Estimado | H19: ='Análise Econômica'!B59 -> 0
C23: Sistema de Condicionamento Ambiental | G23: BESS
C24: Sistema Atual | G24: Sistema Atual
C25: Sistemas de Condicionamento Ambiental com baixo índice de eficiência energética
C26: Potência Total (kW) | D26: ='Sistemas de Cond. Ambiental'!L45 -> 0 | G26: Potência Total (kW)
C27: Consumo de Energia Anual (MWh) | D27: ='Sistemas de Cond. Ambiental'!T45 -> 0 | G27: Consumo de Energia Anual (MWh)
C28: Despesa Mensal com Energia Elétrica | D28: =(D27*'Análise Econômica'!E4)/12 -> #VALUE! | G28: Despesa Mensal com Energia Elétrica
C29: Sistema Proposto | G29: Sistema Proposto
C30: Instalação de Sistemas de Condicionamento Ambiental com alto índice de eficiência energética
C31: Potência Total (kW) | D31: ='Sistemas de Cond. Ambiental'!AD45 -> 0 | G31: Potência Total (kW)
C32: Consumo de Energia Anual (MWh) | D32: ='Sistemas de Cond. Ambiental'!AK45 -> 0 | G32: Consumo de Energia Anual (MWh)
C33: Despesa mensal com Energia Elétrica | D33: =(D32*'Análise Econômica'!E4)/12 -> #VALUE! | G33: Despesa mensal com Energia Elétrica
C34: Resultados Previstos | G34: Resultados Previstos
C35: Redução de Demanda (kW) | D35: =D26-D31 -> 0 | G35: Redução de Demanda (kW)
C36: Redução do Consumo de Energia Anual (MWh) | D36: =D27-D32 -> 0 | G36: Redução do Consumo de Energia Anual (MWh)
C37: Redução Percentual do Consumo de Energia % | D37: =D36/D27 -> #DIV/0! | G37: Redução Percentual do Consumo de Energia %
C38: Economia Mensal na Fatura de Energia | D38: =D28-D33 -> #VALUE! | G38: Economia Mensal na Fatura de Energia
C39: Investimento Necessário Estimado | D39: ='Análise Econômica'!Q29 -> 0 | G39: Investimento Necessário Estimado
C43: Sistema de Condicionamento Ambiental | G43: Setorização da Medição
C44: Sistema Atual | G44: Sistema Atual
C45: Sistemas de Condicionamento Ambiental sem automação para acionamento e desligamento programado e com baixo índice de eficiência energética | G45: Uma única medição para um complexo com diversas unidades consumidoras
C46: Potência Total (kW) | D46: ='Sistemas de Cond. Ambiental'!L45 -> 0 | G46: Potência Total (kW)
C47: Consumo de Energia Anual (MWh) | D47: ='Sistemas de Cond. Ambiental'!T45 -> 0 | G47: Consumo de Energia Anual (MWh)
C48: Despesa Mensal com Energia Elétrica | D48: =(D47*'Análise Econômica'!E4)/12 -> #VALUE! | G48: Despesa Mensal com Energia Elétrica
C49: Sistema Proposto | G49: Sistema Proposto
C50: Instalação de Sistemas de Condicionamento Ambiental com alto índice de eficiência energética e com automação para acionamento e desligamento programado. | G50: Instalação de uma medição para cada unidade consumidora presente no complexo
C51: Potência Total (kW) | D51: ='Sistemas de Cond. Ambiental'!AD45 -> 0 | G51: Potência Total (kW)
C52: Consumo de Energia Anual (MWh) | D52: ='Sistemas de Cond. Ambiental'!AR45 -> 0 | G52: Consumo de Energia Anual (MWh)
C53: Despesa mensal com Energia Elétrica | D53: =(D52*'Análise Econômica'!E4)/12 -> #VALUE! | G53: Despesa mensal com Energia Elétrica
C54: Resultados Previstos | G54: Resultados Previstos
C55: Redução de Demanda (kW) | D55: =D46-D51 -> 0 | G55: Redução de Demanda (kW)
C56: Redução do Consumo de Energia Anual (MWh) | D56: =D47-D52 -> 0 | G56: Redução do Consumo de Energia Anual (MWh)
C57: Redução Percentual do Consumo de Energia % | D57: =D56/D47 -> #DIV/0! | G57: Redução Percentual do Consumo de Energia %
C58: Economia Mensal na Fatura de Energia | D58: =D48-D53 -> #VALUE! | G58: Economia Mensal na Fatura de Energia
C59: Investimento Necessário Estimado | D59: ='Análise Econômica'!B29 -> 0 | G59: Investimento Necessário Estimado
C63: Sistema de Condicionamento Ambiental | G63: Sistemas com Motores
C64: Sistema Atual | G64: Sistema Atual
C65: Sistemas de Condicionamento Ambiental sem automação para acionamento e desligamento programado
C66: Potência Total (kW) | D66: ='Sistemas de Cond. Ambiental'!L45 -> 0 | G66: Potência Total (kW)
C67: Consumo de Energia Anual (MWh) | D67: ='Sistemas de Cond. Ambiental'!T45 -> 0 | G67: Consumo de Energia Anual (MWh)
C68: Despesa Mensal com Energia Elétrica | D68: =(D67*'Análise Econômica'!E4)/12 -> #VALUE! | G68: Despesa Mensal com Energia Elétrica
C69: Sistema Proposto | G69: Sistema Proposto
C70: Instalação da automação para acionamento e desligamento programado.
C71: Potência Total (kW) | D71: ='Sistemas de Cond. Ambiental'!L45 -> 0 | G71: Potência Total (kW)
C72: Consumo de Energia Anual (MWh) | D72: ='Sistemas de Cond. Ambiental'!AQ45 -> 0 | G72: Consumo de Energia Anual (MWh)
C73: Despesa mensal com Energia Elétrica | D73: =(D72*'Análise Econômica'!E4)/12 -> #VALUE! | G73: Despesa mensal com Energia Elétrica
C74: Resultados Previstos | G74: Resultados Previstos
C75: Redução de Demanda (kW) | D75: =D66-D71 -> 0 | G75: Redução de Demanda (kW)
C76: Redução do Consumo de Energia Anual (MWh) | D76: =D67-D72 -> 0 | G76: Redução do Consumo de Energia Anual (MWh)
C77: Redução Percentual do Consumo de Energia % | D77: =D76/D67 -> #DIV/0! | G77: Redução Percentual do Consumo de Energia %
C78: Economia Mensal na Fatura de Energia | D78: =D68-D73 -> #VALUE! | G78: Economia Mensal na Fatura de Energia
C79: Investimento Necessário Estimado | D79: ='Análise Econômica'!AF29 -> 0 | G79: Investimento Necessário Estimado

Sheet CONSUMO_EQP
A1: Distribuição do Consumo | B1: (kWh) | C1: (%)
A2: Iluminação | B2: {=IFERROR(LOOKUP(2,1/ISNUMBER('Sistemas de Iluminação'!R:R),'Sistemas de Iluminação'!R:R),0)} -> 0 | C2: =(B2/$B$7)*100 -> #DIV/0!
A3: Climatização | B3: {=IFERROR(LOOKUP(2,1/ISNUMBER('Sistemas de Cond. Ambiental'!T:T),'Sistemas de Cond. Ambiental'!T:T),0)} -> 0 | C3: =(B3/$B$7)*100 -> #DIV/0!
A4: Sistemas Motrizes | B4: {=IFERROR(LOOKUP(2,1/ISNUMBER('Sistemas de Motor'!P:P),'Sistemas de Motor'!P:P),0)} -> 0 | C4: =(B4/$B$7)*100 -> #DIV/0!
A5: Refrigeração | B5: {=IFERROR(LOOKUP(2,1/ISNUMBER('Sistemas de Refrigeração'!S:S),'Sistemas de Refrigeração'!S:S),0)} -> 0 | C5: =(B5/$B$7)*100 -> #DIV/0!
A6: Outros | B6: {=IFERROR(LOOKUP(2,1/ISNUMBER('Sistemas Outros'!Q:Q),'Sistemas Outros'!Q:Q),0)} -> 0 | C6: =(B6/$B$7)*100 -> #DIV/0!
A7: Total | B7: =SUM(B2:B6) -> 0 | C7: =(B7/$B$7)*100 -> #DIV/0!

Sheet Análise Econômica
A2: Premissas | D2: Custo Un. do Mwh | G2: Custos Operacionais | J2: Redução de Consmo (Automação do Sistema)
A3: Descrição | B3: Alíquotas | D3: Metodologia | E3: R$/MWh | G3: Mão de obra - Substituição | H3: 712.5 | J3: Metodologia | K3: Economia (%)
A4: IRPJ e CSSL | B4: 0 | D4: Direta | E4: {=(MEDIAN(_xlfn._xlws.FILTER(FATURAS!AQ2:AQ13,FATURAS!AQ2:AQ13>0))*_xlfn.XLOOKUP(MAX(FATURAS!M2:M13),FATURAS!M2:M13,FATURAS!BR2:BR13)+MEDIAN(_xlfn._xlws.FILTER(FATURAS!AR2:AR13,FATURAS!AR2:AR13>0))*_xlfn.XLOOKUP(MAX(FATURAS!M2:M13),FATURAS!M2:M13,FATURAS!BS2:BS13)+IF(ISNUMBER(_xlfn.XLOOKUP(MAX(FATURAS!M2:M13),FATURAS!M2:M13,FATURAS!BZ2:BZ13)),MEDIAN(_xlfn._xlws.FILTER(FATURAS!BA2:BA13,FATURAS!BA2:BA13>0))*_xlfn.XLOOKUP(MAX(FATURAS!M2:M13),FATURAS!M2:M13,FATURAS!BZ2:BZ13)+MEDIAN(_xlfn._xlws.FILTER(FATURAS!BB2:BB13,FATURAS!BB2:BB13>0))*_xlfn.XLOOKUP(MAX(FATURAS!M2:M13),FATURAS!M2:M13,FATURAS!CA2:CA13),MEDIAN(_xlfn._xlws.FILTER(FATURAS!AZ2:AZ13,FATURAS!AZ2:AZ13>0))*_xlfn.XLOOKUP(MAX(FATURAS!M2:M13),FATURAS!M2:M13,FATURAS!BV2:BV13)))/(MEDIAN(_xlfn._xlws.FILTER(FATURAS!AQ2:AQ13,FATURAS!AQ2:AQ13>0))+MEDIAN(_xlfn._xlws.FILTER(FATURAS!AR2:AR13,FATURAS!AR2:AR13>0)))*1000} -> #VALUE! | G4: Mão de obra - Intalação completa | H4: 1462.5 | J4: Enermatch | K4: 0.1
A5: TMA a.a. | B5: 0.15 | D5: Indireta | E5: =(_xlfn.XLOOKUP(MAX(FATURAS!M2:M13),FATURAS!M2:M13,FATURAS!AF2:AF13)*_xlfn.XLOOKUP(MAX(FATURAS!M2:M13),FATURAS!M2:M13,FATURAS!CG2:CG13)+IF(ISNUMBER(_xlfn.XLOOKUP(MAX(FATURAS!M2:M13),FATURAS!M2:M13,FATURAS!BZ2:BZ13)),_xlfn.XLOOKUP(MAX(FATURAS!M2:M13),FATURAS!M2:M13,FATURAS!BA2:BA13)*_xlfn.XLOOKUP(MAX(FATURAS!M2:M13),FATURAS!M2:M13,FATURAS!BZ2:BZ13)+_xlfn.XLOOKUP(MAX(FATURAS!M2:M13),FATURAS!M2:M13,FATURAS!BB2:BB13)*_xlfn.XLOOKUP(MAX(FATURAS!M2:M13),FATURAS!M2:M13,FATURAS!CA2:CA13),_xlfn.XLOOKUP(MAX(FATURAS!M2:M13),FATURAS!M2:M13,FATURAS!AZ2:AZ13)*_xlfn.XLOOKUP(MAX(FATURAS!M2:M13),FATURAS!M2:M13,FATURAS!BV2:BV13)))/_xlfn.XLOOKUP(MAX(FATURAS!M2:M13),FATURAS!M2:M13,FATURAS!AF2:AF13)*1000 -> #N/A | G5: Aquisição do Equipamento + Software (P/ Ponto) | H5: 179.9
G6: Mensalidade de Software (P/ Ponto) | H6: 9.9 | J6: Sistemas de Iluminação
J7: Contagem de Pontos | K7: {=COUNTA(_xlfn.UNIQUE(_xlfn._xlws.FILTER('Sistemas de Iluminação'!B4:B1048576,'Sistemas de Iluminação'!B4:B1048576<>"","")))} -> 1
J8: Mão de obra | K8: 120
D9: Fator de correção
D10: Faturas | E10: =UC_DADOS!G50 -> 0
D11: Levantamento | E11: ='Sistemas de Cond. Ambiental'!T45+'Sistemas de Iluminação'!R96+'Sistemas de Refrigeração'!S47+'Sistemas de Motor'!P59+'Sistemas de Aquecimento de Água'!N11+'Sistemas Outros'!Q53 -> 0
D12: Fator | E12: =E10/E11 -> #DIV/0! | AR12: OPÇÃO RECOMENDADA — Cond. Ambiental
D13: =IF(AND(B4>=0.9,B4<=1.1),"✓ OK — Fator próximo de 1", IF(AND(B4>=0.8,B4<=1.2),"⚠ Aceitável — revisar horários se possível", IF(B4<0.8,"❌ Levantamento SUPERIOR às faturas — REDUZIR horas de operação dos equipamentos", "❌ Levantamento INFERIOR às faturas — AUMENTAR horas de operação dos equipamentos"))) -> ❌ Levantamento SUPERIOR às faturas — REDUZIR horas de operação dos equipamentos | AR13: Indicador | AS13: T1 — Subst. + Automação | AT13: T2 — Substituição | AU13: T3 — Automação (sem troca) | AV13: Solução escolhida: | AW13: =IF(C32=MAX(C32,R32,AG32),"T1 — Combinado (Substituição + Automação)",IF(R32=MAX(C32,R32,AG32),"T2 — Substituição (com mão de obra)","T3 — Automação (sem troca)")) -> #VALUE!
AR14: Investimento (R$) | AS14: =-B24 -> 0 | AT14: =-Q24 -> 0 | AU14: =-AF24 -> 0 | AV14: Investimento Total: | AW14: =IF(C32=MAX(C32,R32,AG32),-B24,IF(R32=MAX(C32,R32,AG32),-Q24,-AF24)) -> #VALUE!
AR15: Economia Anual (R$/ano) | AS15: =C25 -> #VALUE! | AT15: =R25 -> #VALUE! | AU15: =AG25 -> #VALUE! | AV15: Economia Anual de Energia: | AW15: =IF(C32=MAX(C32,R32,AG32),C25,IF(R32=MAX(C32,R32,AG32),R25,AG25)) -> #VALUE!
AR16: VPL — 10 anos (R$) | AS16: =C32 -> #VALUE! | AT16: =R32 -> #VALUE! | AU16: =AG32 -> #VALUE! | AV16: VPL (10 anos, TMA 15% a.a.): | AW16: =MAX(C32,R32,AG32) -> #VALUE!
AR17: TIR (% a.a.) | AS17: =C30 -> N/A | AT17: =R30 -> N/A | AU17: =AG30 -> N/A | AV17: RBC (Razão Benefício/Custo): | AW17: =IF(C32=MAX(C32,R32,AG32),C31,IF(R32=MAX(C32,R32,AG32),R31,AG31)) -> #VALUE!
AR18: RBC (Razão Benefício/Custo) | AS18: =C31 -> #VALUE! | AT18: =R31 -> #VALUE! | AU18: =AG31 -> #VALUE! | AV18: Payback Simples: | AW18: =IF(C32=MAX(C32,R32,AG32),C33,IF(R32=MAX(C32,R32,AG32),R33,AG33)) -> #VALUE!
AR19: Payback Simples (anos) | AS19: =C33 -> #VALUE! | AT19: =R33 -> #VALUE! | AU19: =AG33 -> #VALUE! | AV19: Justificativa: | AW19: Maior VPL absoluto entre as três opções avaliadas
AR20: VPL da opção escolhida: | AS20: =IF(C32=MAX(C32,R32,AG32),"T1 — Combinado (Substituição + Automação)",IF(R32=MAX(C32,R32,AG32),"T2 — Substituição (com mão de obra)","T3 — Automação (sem troca)")) -> #VALUE!
A22: Sistema de Cond. Ambiental - Combinado (Substituição + Automação) | P22: Sistema de Cond. Ambiental - Com mão de obra | AE22: Sistema de Cond. Ambiental - Sistema Automatizado (sem troca)
A23: Ano | B23: 0 | C23: 1 | D23: 2 | E23: 3 | F23: 4 | G23: 5 | H23: 6 | I23: 7 | J23: 8 | K23: 9 | L23: 10 | P23: Ano | Q23: 0 | R23: 1 | S23: 2 | T23: 3 | U23: 4 | V23: 5 | W23: 6 | X23: 7 | Y23: 8 | Z23: 9 | AA23: 10 | AE23: Ano | AF23: 0 | AG23: 1 | AH23: 2 | AI23: 3 | AJ23: 4 | AK23: 5 | AL23: 6 | AM23: 7 | AN23: 8 | AO23: 9 | AP23: 10
A24: Investimento : | B24: {=-(SUMPRODUCT(('Sistemas de Cond. Ambiental'!C3:C932<>"")*'Sistemas de Cond. Ambiental'!AO3:AO932)+(H3*SUMPRODUCT(('Sistemas de Cond. Ambiental'!C3:C932<>"")*('Sistemas de Cond. Ambiental'!AN3:AN932<>0)*'Sistemas de Cond. Ambiental'!AA3:AA932))+(H5*SUMPRODUCT(('Sistemas de Cond. Ambiental'!C3:C932<>"")*'Sistemas de Cond. Ambiental'!I3:I932))+(H6*12*SUMPRODUCT(('Sistemas de Cond. Ambiental'!C3:C932<>"")*'Sistemas de Cond. Ambiental'!I3:I932)))} -> 0 | C24: =-($H$6*12*SUMPRODUCT(('Sistemas de Cond. Ambiental'!C3:C932<>"")*'Sistemas de Cond. Ambiental'!I3:I932)) -> 0 | D24: =-($H$6*12*SUMPRODUCT(('Sistemas de Cond. Ambiental'!C3:C932<>"")*'Sistemas de Cond. Ambiental'!I3:I932)) -> 0 | E24: =-($H$6*12*SUMPRODUCT(('Sistemas de Cond. Ambiental'!C3:C932<>"")*'Sistemas de Cond. Ambiental'!I3:I932)) -> 0 | F24: =-($H$6*12*SUMPRODUCT(('Sistemas de Cond. Ambiental'!C3:C932<>"")*'Sistemas de Cond. Ambiental'!I3:I932)) -> 0 | G24: =-($H$6*12*SUMPRODUCT(('Sistemas de Cond. Ambiental'!C3:C932<>"")*'Sistemas de Cond. Ambiental'!I3:I932)) -> 0 | H24: =-($H$6*12*SUMPRODUCT(('Sistemas de Cond. Ambiental'!C3:C932<>"")*'Sistemas de Cond. Ambiental'!I3:I932)) -> 0 | I24: =-($H$6*12*SUMPRODUCT(('Sistemas de Cond. Ambiental'!C3:C932<>"")*'Sistemas de Cond. Ambiental'!I3:I932)) -> 0 | J24: =-($H$6*12*SUMPRODUCT(('Sistemas de Cond. Ambiental'!C3:C932<>"")*'Sistemas de Cond. Ambiental'!I3:I932)) -> 0 | K24: =-($H$6*12*SUMPRODUCT(('Sistemas de Cond. Ambiental'!C3:C932<>"")*'Sistemas de Cond. Ambiental'!I3:I932)) -> 0 | L24: =-($H$6*12*SUMPRODUCT(('Sistemas de Cond. Ambiental'!C3:C932<>"")*'Sistemas de Cond. Ambiental'!I3:I932)) -> 0 | P24: Investimento : | Q24: {=-(SUMPRODUCT(('Sistemas de Cond. Ambiental'!C3:C932<>"")*'Sistemas de Cond. Ambiental'!AO3:AO932)+(H3*SUMPRODUCT(('Sistemas de Cond. Ambiental'!C3:C932<>"")*('Sistemas de Cond. Ambiental'!AN3:AN932<>0)*'Sistemas de Cond. Ambiental'!AA3:AA932)))} -> 0 | R24: 0 | S24: 0 | T24: 0 | U24: 0 | V24: 0 | W24: 0 | X24: 0 | Y24: 0 | Z24: 0 | AA24: 0 | AE24: Investimento : | AF24: =-((SUMPRODUCT(('Sistemas de Cond. Ambiental'!C3:C932<>"")*'Sistemas de Cond. Ambiental'!I3:I932)*H5)+(H6*12*SUMPRODUCT(('Sistemas de Cond. Ambiental'!C3:C932<>"")*'Sistemas de Cond. Ambiental'!I3:I932))) -> 0 | AG24: =-($H$6*12*SUMPRODUCT(('Sistemas de Cond. Ambiental'!C3:C932<>"")*'Sistemas de Cond. Ambiental'!I3:I932)) -> 0 | AH24: =-($H$6*12*SUMPRODUCT(('Sistemas de Cond. Ambiental'!C3:C932<>"")*'Sistemas de Cond. Ambiental'!I3:I932)) -> 0 | AI24: =-($H$6*12*SUMPRODUCT(('Sistemas de Cond. Ambiental'!C3:C932<>"")*'Sistemas de Cond. Ambiental'!I3:I932)) -> 0 | AJ24: =-($H$6*12*SUMPRODUCT(('Sistemas de Cond. Ambiental'!C3:C932<>"")*'Sistemas de Cond. Ambiental'!I3:I932)) -> 0 | AK24: =-($H$6*12*SUMPRODUCT(('Sistemas de Cond. Ambiental'!C3:C932<>"")*'Sistemas de Cond. Ambiental'!I3:I932)) -> 0 | AL24: =-($H$6*12*SUMPRODUCT(('Sistemas de Cond. Ambiental'!C3:C932<>"")*'Sistemas de Cond. Ambiental'!I3:I932)) -> 0 | AM24: =-($H$6*12*SUMPRODUCT(('Sistemas de Cond. Ambiental'!C3:C932<>"")*'Sistemas de Cond. Ambiental'!I3:I932)) -> 0 | AN24: =-($H$6*12*SUMPRODUCT(('Sistemas de Cond. Ambiental'!C3:C932<>"")*'Sistemas de Cond. Ambiental'!I3:I932)) -> 0 | AO24: =-($H$6*12*SUMPRODUCT(('Sistemas de Cond. Ambiental'!C3:C932<>"")*'Sistemas de Cond. Ambiental'!I3:I932)) -> 0 | AP24: =-($H$6*12*SUMPRODUCT(('Sistemas de Cond. Ambiental'!C3:C932<>"")*'Sistemas de Cond. Ambiental'!I3:I932)) -> 0
A25: Redução de Custos de Energia: | B25: 0 | C25: {=(SUMPRODUCT(('Sistemas de Cond. Ambiental'!C3:C932<>"")*'Sistemas de Cond. Ambiental'!AN3:AN932)+(SUMPRODUCT(('Sistemas de Cond. Ambiental'!C3:C932<>"")*'Sistemas de Cond. Ambiental'!T3:T932)-SUMPRODUCT(('Sistemas de Cond. Ambiental'!C3:C932<>"")*'Sistemas de Cond. Ambiental'!AN3:AN932))*$K$4)*$E$4} -> #VALUE! | D25: =C25 -> #VALUE! | E25: =D25 -> #VALUE! | F25: =E25 -> #VALUE! | G25: =F25 -> #VALUE! | H25: =G25 -> #VALUE! | I25: =H25 -> #VALUE! | J25: =I25 -> #VALUE! | K25: =J25 -> #VALUE! | L25: =K25 -> #VALUE! | P25: Redução de Custos de Energia: | Q25: 0 | R25: =SUMPRODUCT(('Sistemas de Cond. Ambiental'!C3:C932<>"")*'Sistemas de Cond. Ambiental'!AN3:AN932)*'Análise Econômica'!E4 -> #VALUE! | S25: =R25 -> #VALUE! | T25: =S25 -> #VALUE! | U25: =T25 -> #VALUE! | V25: =U25 -> #VALUE! | W25: =V25 -> #VALUE! | X25: =W25 -> #VALUE! | Y25: =X25 -> #VALUE! | Z25: =Y25 -> #VALUE! | AA25: =Z25 -> #VALUE! | AE25: Redução de Custos de Energia: | AF25: 0 | AG25: =SUMPRODUCT(('Sistemas de Cond. Ambiental'!C3:C932<>"")*'Sistemas de Cond. Ambiental'!T3:T932)*$K$4*$E$4 -> #VALUE! | AH25: =AG25 -> #VALUE! | AI25: =AH25 -> #VALUE! | AJ25: =AI25 -> #VALUE! | AK25: =AJ25 -> #VALUE! | AL25: =AK25 -> #VALUE! | AM25: =AL25 -> #VALUE! | AN25: =AM25 -> #VALUE! | AO25: =AN25 -> #VALUE! | AP25: =AO25 -> #VALUE!
A26: Fluxo de Caixa: | B26: =SUM(B24:B25) -> 0 | C26: =SUM(C24:C25) -> #VALUE! | D26: =SUM(D24:D25) -> #VALUE! | E26: =SUM(E24:E25) -> #VALUE! | F26: =SUM(F24:F25) -> #VALUE! | G26: =SUM(G24:G25) -> #VALUE! | H26: =SUM(H24:H25) -> #VALUE! | I26: =SUM(I24:I25) -> #VALUE! | ... L26: =SUM(L24:L25) -> #VALUE! | P26: Fluxo de Caixa: | Q26: =SUM(Q24:Q25) -> 0 | R26: =SUM(R24:R25) -> #VALUE! | S26: =SUM(S24:S25) -> #VALUE! | T26: =SUM(T24:T25) -> #VALUE! | U26: =SUM(U24:U25) -> #VALUE! | V26: =SUM(V24:V25) -> #VALUE! | W26: =SUM(W24:W25) -> #VALUE! | X26: =SUM(X24:X25) -> #VALUE! | ... AA26: =SUM(AA24:AA25) -> #VALUE! | AE26: Fluxo de Caixa: | AF26: =SUM(AF24:AF25) -> 0 | AG26: =SUM(AG24:AG25) -> #VALUE! | AH26: =SUM(AH24:AH25) -> #VALUE! | AI26: =SUM(AI24:AI25) -> #VALUE! | AJ26: =SUM(AJ24:AJ25) -> #VALUE! | AK26: =SUM(AK24:AK25) -> #VALUE! | AL26: =SUM(AL24:AL25) -> #VALUE! | AM26: =SUM(AM24:AM25) -> #VALUE! | ... AP26: =SUM(AP24:AP25) -> #VALUE!
B28: =B26/(1+$B$5)^(B23) -> 0 | C28: =C26/(1+$B$5)^(C23)+B28 -> #VALUE! | D28: =D26/(1+$B$5)^(D23)+C28 -> #VALUE! | E28: =E26/(1+$B$5)^(E23)+D28 -> #VALUE! | F28: =F26/(1+$B$5)^(F23)+E28 -> #VALUE! | G28: =G26/(1+$B$5)^(G23)+F28 -> #VALUE! | H28: =H26/(1+$B$5)^(H23)+G28 -> #VALUE! | I28: =I26/(1+$B$5)^(I23)+H28 -> #VALUE! | J28: =J26/(1+$B$5)^(J23)+I28 -> #VALUE! | ... L28: =L26/(1+$B$5)^(L23)+K28 -> #VALUE! | Q28: =Q26/(1+$B$5)^(Q23) -> 0 | R28: =R26/(1+$B$5)^(R23)+Q28 -> #VALUE! | S28: =S26/(1+$B$5)^(S23)+R28 -> #VALUE! | T28: =T26/(1+$B$5)^(T23)+S28 -> #VALUE! | U28: =U26/(1+$B$5)^(U23)+T28 -> #VALUE! | V28: =V26/(1+$B$5)^(V23)+U28 -> #VALUE! | W28: =W26/(1+$B$5)^(W23)+V28 -> #VALUE! | X28: =X26/(1+$B$5)^(X23)+W28 -> #VALUE! | Y28: =Y26/(1+$B$5)^(Y23)+X28 -> #VALUE! | ... AA28: =AA26/(1+$B$5)^(AA23)+Z28 -> #VALUE! | AF28: =AF26/(1+$B$5)^(AF23) -> 0 | AG28: =AG26/(1+$B$5)^(AG23)+AF28 -> #VALUE! | AH28: =AH26/(1+$B$5)^(AH23)+AG28 -> #VALUE! | AI28: =AI26/(1+$B$5)^(AI23)+AH28 -> #VALUE! | AJ28: =AJ26/(1+$B$5)^(AJ23)+AI28 -> #VALUE! | AK28: =AK26/(1+$B$5)^(AK23)+AJ28 -> #VALUE! | AL28: =AL26/(1+$B$5)^(AL23)+AK28 -> #VALUE! | AM28: =AM26/(1+$B$5)^(AM23)+AL28 -> #VALUE! | AN28: =AN26/(1+$B$5)^(AN23)+AM28 -> #VALUE! | ... AP28: =AP26/(1+$B$5)^(AP23)+AO28 -> #VALUE!
B29: {=(SUMPRODUCT(('Sistemas de Cond. Ambiental'!C3:C932<>"")*'Sistemas de Cond. Ambiental'!AO3:AO932)+(H3*SUMPRODUCT(('Sistemas de Cond. Ambiental'!C3:C932<>"")*('Sistemas de Cond. Ambiental'!AN3:AN932<>0)*'Sistemas de Cond. Ambiental'!AA3:AA932))+(H5*SUMPRODUCT(('Sistemas de Cond. Ambiental'!C3:C932<>"")*'Sistemas de Cond. Ambiental'!I3:I932))+(H6*12*SUMPRODUCT(('Sistemas de Cond. Ambiental'!C3:C932<>"")*'Sistemas de Cond. Ambiental'!I3:I932)))} -> 0 | Q29: {=(SUMPRODUCT(('Sistemas de Cond. Ambiental'!C3:C932<>"")*'Sistemas de Cond. Ambiental'!AO3:AO932)+(H3*SUMPRODUCT(('Sistemas de Cond. Ambiental'!C3:C932<>"")*('Sistemas de Cond. Ambiental'!AN3:AN932<>0)*'Sistemas de Cond. Ambiental'!AA3:AA932)))} -> 0 | AF29: {=((SUMPRODUCT(('Sistemas de Cond. Ambiental'!C3:C932<>"")*'Sistemas de Cond. Ambiental'!I3:I932)*H5)+(H6*12*SUMPRODUCT(('Sistemas de Cond. Ambiental'!C3:C932<>"")*'Sistemas de Cond. Ambiental'!I3:I932)))} -> 0 | AG29: {=($H$6*12*SUMPRODUCT(('Sistemas de Cond. Ambiental'!C3:C932<>"")*'Sistemas de Cond. Ambiental'!I3:I932))} -> 0 | AH29: {=($H$6*12*SUMPRODUCT(('Sistemas de Cond. Ambiental'!C3:C932<>"")*'Sistemas de Cond. Ambiental'!I3:I932))} -> 0 | AI29: {=($H$6*12*SUMPRODUCT(('Sistemas de Cond. Ambiental'!C3:C932<>"")*'Sistemas de Cond. Ambiental'!I3:I932))} -> 0 | AJ29: {=($H$6*12*SUMPRODUCT(('Sistemas de Cond. Ambiental'!C3:C932<>"")*'Sistemas de Cond. Ambiental'!I3:I932))} -> 0 | AK29: {=($H$6*12*SUMPRODUCT(('Sistemas de Cond. Ambiental'!C3:C932<>"")*'Sistemas de Cond. Ambiental'!I3:I932))} -> 0 | AL29: {=($H$6*12*SUMPRODUCT(('Sistemas de Cond. Ambiental'!C3:C932<>"")*'Sistemas de Cond. Ambiental'!I3:I932))} -> 0 | AM29: {=($H$6*12*SUMPRODUCT(('Sistemas de Cond. Ambiental'!C3:C932<>"")*'Sistemas de Cond. Ambiental'!I3:I932))} -> 0 | AN29: {=($H$6*12*SUMPRODUCT(('Sistemas de Cond. Ambiental'!C3:C932<>"")*'Sistemas de Cond. Ambiental'!I3:I932))} -> 0 | AO29: {=($H$6*12*SUMPRODUCT(('Sistemas de Cond. Ambiental'!C3:C932<>"")*'Sistemas de Cond. Ambiental'!I3:I932))} -> 0 | AP29: {=($H$6*12*SUMPRODUCT(('Sistemas de Cond. Ambiental'!C3:C932<>"")*'Sistemas de Cond. Ambiental'!I3:I932))} -> 0 | AQ29: =SUM(AF29:AP29) -> 0
B30: TIR ===> | C30: =IFERROR(IRR(B26:L26),"N/A") -> N/A | Q30: TIR ===> | R30: =IFERROR(IRR(Q26:AA26),"N/A") -> N/A | AF30: TIR ===> | AG30: =IFERROR(IRR(AF26:AP26),"N/A") -> N/A
B31: RBC ===> | C31: =C32/-B28 -> #VALUE! | Q31: RBC ===> | R31: =R32/-Q28 -> #VALUE! | AF31: RBC ===> | AG31: =AG32/-AF28 -> #VALUE!
B32: VPL ===> | C32: =B26+NPV($B$5,C26:L26) -> #VALUE! | Q32: VPL ===> | R32: =Q26+NPV($B$5,R26:AA26) -> #VALUE! | AF32: VPL ===> | AG32: =AF26+NPV($B$5,AG26:AP26) -> #VALUE!
B33: PBS ===> | C33: =(-1*B24)/C26 -> #VALUE! | D33: ano | Q33: PBS ===> | R33: =(-1*Q24)/R26 -> #VALUE! | S33: ano | AF33: PBS ===> | AG33: =(-1*AF24)/AG26 -> #VALUE! | AH33: ano
B34: ECONOMIA (MWh/ano) ===> | C34: =C25/$E$4 -> #VALUE! | Q34: ECONOMIA (MWh/ano) ===> | R34: =R25/$E$4 -> #VALUE! | AF34: ECONOMIA (MWh/ano) ===> | AG34: =AG25/$E$4 -> #VALUE!
A37: Iluminação - Sistema Automatizado (sem troca) | P37: Motores | AE37: Setorização da Medição
A38: Ano | B38: 0 | C38: 1 | D38: 2 | E38: 3 | F38: 4 | G38: 5 | H38: 6 | I38: 7 | J38: 8 | K38: 9 | L38: 10 | P38: Ano | Q38: 0 | R38: 1 | S38: 2 | T38: 3 | U38: 4 | V38: 5 | W38: 6 | X38: 7 | Y38: 8 | Z38: 9 | AA38: 10 | AE38: Ano | AF38: 0 | AG38: 1 | AH38: 2 | AI38: 3 | AJ38: 4 | AK38: 5 | AL38: 6 | AM38: 7 | AN38: 8 | AO38: 9 | AP38: 10
A39: Investimento : | B39: =-($K$7*($H$5+$K$8)) -> -299.9 | C39: =-($H$6*12*$K$7) -> -118.8 | D39: =-($H$6*12*$K$7) -> -118.8 | E39: =-($H$6*12*$K$7) -> -118.8 | F39: =-($H$6*12*$K$7) -> -118.8 | G39: =-($H$6*12*$K$7) -> -118.8 | H39: =-($H$6*12*$K$7) -> -118.8 | I39: =-($H$6*12*$K$7) -> -118.8 | J39: =-($H$6*12*$K$7) -> -118.8 | ... L39: =-($H$6*12*$K$7) -> -118.8 | P39: Investimento : | Q39: =-((W5*(COUNTA('Sistemas de Iluminação'!T:T)-1))+(W6*12*(COUNTA('Sistemas de Iluminação'!T:T)-1))) -> 0 | R39: =-($H$6*12*(COUNTA('Sistemas de Iluminação'!$C:$C)-1)) -> 0 | S39: =-($H$6*12*(COUNTA('Sistemas de Iluminação'!$C:$C)-1)) -> 0 | T39: =-($H$6*12*(COUNTA('Sistemas de Iluminação'!$C:$C)-1)) -> 0 | U39: =-($H$6*12*(COUNTA('Sistemas de Iluminação'!$C:$C)-1)) -> 0 | V39: =-($H$6*12*(COUNTA('Sistemas de Iluminação'!$C:$C)-1)) -> 0 | W39: =-($H$6*12*(COUNTA('Sistemas de Iluminação'!$C:$C)-1)) -> 0 | X39: =-($H$6*12*(COUNTA('Sistemas de Iluminação'!$C:$C)-1)) -> 0 | Y39: =-($H$6*12*(COUNTA('Sistemas de Iluminação'!$C:$C)-1)) -> 0 | ... AA39: =-($H$6*12*(COUNTA('Sistemas de Iluminação'!$C:$C)-1)) -> 0 | AE39: Investimento : | AF39: =-((AL5*(COUNTA('Sistemas de Iluminação'!AI:AI)-1))+(AL6*12*(COUNTA('Sistemas de Iluminação'!AI:AI)-1))) -> 0 | AG39: =-($H$6*12*(COUNTA('Sistemas de Iluminação'!$C:$C)-1)) -> 0 | AH39: =-($H$6*12*(COUNTA('Sistemas de Iluminação'!$C:$C)-1)) -> 0 | AI39: =-($H$6*12*(COUNTA('Sistemas de Iluminação'!$C:$C)-1)) -> 0 | AJ39: =-($H$6*12*(COUNTA('Sistemas de Iluminação'!$C:$C)-1)) -> 0 | AK39: =-($H$6*12*(COUNTA('Sistemas de Iluminação'!$C:$C)-1)) -> 0 | AL39: =-($H$6*12*(COUNTA('Sistemas de Iluminação'!$C:$C)-1)) -> 0 | AM39: =-($H$6*12*(COUNTA('Sistemas de Iluminação'!$C:$C)-1)) -> 0 | AN39: =-($H$6*12*(COUNTA('Sistemas de Iluminação'!$C:$C)-1)) -> 0 | ... AP39: =-($H$6*12*(COUNTA('Sistemas de Iluminação'!$C:$C)-1)) -> 0
A40: Redução de Custos de Energia: | B40: 0 | C40: =SUMPRODUCT(('Sistemas de Iluminação'!C4:C853<>"")*'Sistemas de Iluminação'!R4:R853)*$K$4*$E$4 -> #VALUE! | D40: =C40 -> #VALUE! | E40: =C40 -> #VALUE! | F40: =C40 -> #VALUE! | G40: =C40 -> #VALUE! | H40: =C40 -> #VALUE! | I40: =C40 -> #VALUE! | J40: =C40 -> #VALUE! | K40: =C40 -> #VALUE! | L40: =C40 -> #VALUE! | P40: Redução de Custos de Energia: | Q40: 0 | R40: =SUMPRODUCT(('Sistemas de Iluminação'!T4:T853<>"")*'Sistemas de Iluminação'!AG4:AG853)*$K$4*$E$4 -> #VALUE! | S40: =R40 -> #VALUE! | T40: =R40 -> #VALUE! | U40: =R40 -> #VALUE! | V40: =R40 -> #VALUE! | W40: =R40 -> #VALUE! | X40: =R40 -> #VALUE! | Y40: =R40 -> #VALUE! | Z40: =R40 -> #VALUE! | AA40: =R40 -> #VALUE! | AE40: Redução de Custos de Energia: | AF40: 0 | AG40: =SUMPRODUCT(('Sistemas de Iluminação'!AI4:AI853<>"")*'Sistemas de Iluminação'!AV4:AV853)*$K$4*$E$4 -> #VALUE! | AH40: =AG40 -> #VALUE! | AI40: =AG40 -> #VALUE! | AJ40: =AG40 -> #VALUE! | AK40: =AG40 -> #VALUE! | AL40: =AG40 -> #VALUE! | AM40: =AG40 -> #VALUE! | AN40: =AG40 -> #VALUE! | AO40: =AG40 -> #VALUE! | AP40: =AG40 -> #VALUE!
A41: Fluxo de Caixa: | B41: =SUM(B39:B40) -> -299.9 | C41: =SUM(C39:C40) -> #VALUE! | D41: =SUM(D39:D40) -> #VALUE! | E41: =SUM(E39:E40) -> #VALUE! | F41: =SUM(F39:F40) -> #VALUE! | G41: =SUM(G39:G40) -> #VALUE! | H41: =SUM(H39:H40) -> #VALUE! | I41: =SUM(I39:I40) -> #VALUE! | ... L41: =SUM(L39:L40) -> #VALUE! | P41: Fluxo de Caixa: | Q41: =SUM(Q39:Q40) -> 0 | R41: =SUM(R39:R40) -> #VALUE! | S41: =SUM(S39:S40) -> #VALUE! | T41: =SUM(T39:T40) -> #VALUE! | U41: =SUM(U39:U40) -> #VALUE! | V41: =SUM(V39:V40) -> #VALUE! | W41: =SUM(W39:W40) -> #VALUE! | X41: =SUM(X39:X40) -> #VALUE! | ... AA41: =SUM(AA39:AA40) -> #VALUE! | AE41: Fluxo de Caixa: | AF41: =SUM(AF39:AF40) -> 0 | AG41: =SUM(AG39:AG40) -> #VALUE! | AH41: =SUM(AH39:AH40) -> #VALUE! | AI41: =SUM(AI39:AI40) -> #VALUE! | AJ41: =SUM(AJ39:AJ40) -> #VALUE! | AK41: =SUM(AK39:AK40) -> #VALUE! | AL41: =SUM(AL39:AL40) -> #VALUE! | AM41: =SUM(AM39:AM40) -> #VALUE! | ... AP41: =SUM(AP39:AP40) -> #VALUE!
B43: =B41/(1+$B$5)^(B38) -> -299.9 | C43: =C41/(1+$B$5)^(C38)+B43 -> #VALUE! | D43: =D41/(1+$B$5)^(D38)+C43 -> #VALUE! | E43: =E41/(1+$B$5)^(E38)+D43 -> #VALUE! | F43: =F41/(1+$B$5)^(F38)+E43 -> #VALUE! | G43: =G41/(1+$B$5)^(G38)+F43 -> #VALUE! | H43: =H41/(1+$B$5)^(H38)+G43 -> #VALUE! | I43: =I41/(1+$B$5)^(I38)+H43 -> #VALUE! | J43: =J41/(1+$B$5)^(J38)+I43 -> #VALUE! | ... L43: =L41/(1+$B$5)^(L38)+K43 -> #VALUE! | Q43: =Q41/(1+$B$5)^(Q38) -> 0 | R43: =R41/(1+$B$5)^(R38)+Q43 -> #VALUE! | S43: =S41/(1+$B$5)^(S38)+R43 -> #VALUE! | T43: =T41/(1+$B$5)^(T38)+S43 -> #VALUE! | U43: =U41/(1+$B$5)^(U38)+T43 -> #VALUE! | V43: =V41/(1+$B$5)^(V38)+U43 -> #VALUE! | W43: =W41/(1+$B$5)^(W38)+V43 -> #VALUE! | X43: =X41/(1+$B$5)^(X38)+W43 -> #VALUE! | Y43: =Y41/(1+$B$5)^(Y38)+X43 -> #VALUE! | ... AA43: =AA41/(1+$B$5)^(AA38)+Z43 -> #VALUE! | AF43: =AF41/(1+$B$5)^(AF38) -> 0 | AG43: =AG41/(1+$B$5)^(AG38)+AF43 -> #VALUE! | AH43: =AH41/(1+$B$5)^(AH38)+AG43 -> #VALUE! | AI43: =AI41/(1+$B$5)^(AI38)+AH43 -> #VALUE! | AJ43: =AJ41/(1+$B$5)^(AJ38)+AI43 -> #VALUE! | AK43: =AK41/(1+$B$5)^(AK38)+AJ43 -> #VALUE! | AL43: =AL41/(1+$B$5)^(AL38)+AK43 -> #VALUE! | AM43: =AM41/(1+$B$5)^(AM38)+AL43 -> #VALUE! | AN43: =AN41/(1+$B$5)^(AN38)+AM43 -> #VALUE! | ... AP43: =AP41/(1+$B$5)^(AP38)+AO43 -> #VALUE!
B45: TIR ===> | C45: =IFERROR(IRR(B41:L41),"N/A") -> N/A | Q45: TIR ===> | R45: =IFERROR(IRR(Q41:AA41),"N/A") -> N/A | AF45: TIR ===> | AG45: =IFERROR(IRR(AF41:AP41),"N/A") -> N/A
B46: RBC ===> | C46: =C47/-B43 -> #VALUE! | Q46: RBC ===> | R46: =R47/-Q43 -> #VALUE! | AF46: RBC ===> | AG46: =AG47/-AF43 -> #VALUE!
B47: VPL ===> | C47: =B41+NPV($B$5,C41:L41) -> #VALUE! | Q47: VPL ===> | R47: =Q41+NPV($B$5,R41:AA41) -> #VALUE! | AF47: VPL ===> | AG47: =AF41+NPV($B$5,AG41:AP41) -> #VALUE!
B48: PBS ===> | C48: =(-1*B39)/C41 -> #VALUE! | D48: ano | Q48: PBS ===> | R48: =(-1*Q39)/R41 -> #VALUE! | S48: ano | AF48: PBS ===> | AG48: =(-1*AF39)/AG41 -> #VALUE! | AH48: ano
B49: ECONOMIA (MWh/ano) ===> | C49: =C40/$E$4 -> #VALUE! | Q49: ECONOMIA (MWh/ano) ===> | R49: =R40/$E$4 -> #VALUE! | AF49: ECONOMIA (MWh/ano) ===> | AG49: =AG40/$E$4 -> #VALUE!
A52: Sistema de Refrigeração - Sbstituição | P52: BESS
A53: Ano | B53: 0 | C53: 1 | D53: 2 | E53: 3 | F53: 4 | G53: 5 | H53: 6 | I53: 7 | J53: 8 | K53: 9 | L53: 10 | P53: Ano | Q53: 0 | R53: 1 | S53: 2 | T53: 3 | U53: 4 | V53: 5 | W53: 6 | X53: 7 | Y53: 8 | Z53: 9 | AA53: 10
A54: Investimento : | B54: =-SUMPRODUCT(('Sistemas de Refrigeração'!C3:C1021<>"")*'Sistemas de Refrigeração'!AK3:AK1021) -> 0 | C54: 0 | D54: 0 | E54: 0 | F54: 0 | G54: 0 | H54: 0 | I54: 0 | J54: 0 | K54: 0 | L54: 0 | P54: Investimento : | Q54: =-SUMPRODUCT(('Sistemas de Refrigeração'!T3:T1021<>"")*'Sistemas de Refrigeração'!AZ3:AZ1021) -> 0 | R54: 0 | S54: 0 | T54: 0 | U54: 0 | V54: 0 | W54: 0 | X54: 0 | Y54: 0 | Z54: 0 | AA54: 0
A55: Redução de Custos de Energia: | B55: 0 | C55: {=SUMPRODUCT(('Sistemas de Refrigeração'!C3:C1021<>"")*'Sistemas de Refrigeração'!AJ3:AJ1021)*$E$4} -> #VALUE! | D55: =C55 -> #VALUE! | E55: =C55 -> #VALUE! | F55: =C55 -> #VALUE! | G55: =C55 -> #VALUE! | H55: =C55 -> #VALUE! | I55: =C55 -> #VALUE! | J55: =C55 -> #VALUE! | K55: =C55 -> #VALUE! | L55: =C55 -> #VALUE! | P55: Redução de Custos de Energia: | Q55: 0 | R55: {=SUMPRODUCT(('Sistemas de Refrigeração'!T3:T1021<>"")*'Sistemas de Refrigeração'!AY3:AY1021)*$E$4} -> #VALUE! | S55: =R55 -> #VALUE! | T55: =R55 -> #VALUE! | U55: =R55 -> #VALUE! | V55: =R55 -> #VALUE! | W55: =R55 -> #VALUE! | X55: =R55 -> #VALUE! | Y55: =R55 -> #VALUE! | Z55: =R55 -> #VALUE! | AA55: =R55 -> #VALUE!
A56: Fluxo de Caixa: | B56: =SUM(B54:B55) -> 0 | C56: =SUM(C54:C55) -> #VALUE! | D56: =SUM(D54:D55) -> #VALUE! | E56: =SUM(E54:E55) -> #VALUE! | F56: =SUM(F54:F55) -> #VALUE! | G56: =SUM(G54:G55) -> #VALUE! | H56: =SUM(H54:H55) -> #VALUE! | I56: =SUM(I54:I55) -> #VALUE! | ... L56: =SUM(L54:L55) -> #VALUE! | P56: Fluxo de Caixa: | Q56: =SUM(Q54:Q55) -> 0 | R56: =SUM(R54:R55) -> #VALUE! | S56: =SUM(S54:S55) -> #VALUE! | T56: =SUM(T54:T55) -> #VALUE! | U56: =SUM(U54:U55) -> #VALUE! | V56: =SUM(V54:V55) -> #VALUE! | W56: =SUM(W54:W55) -> #VALUE! | X56: =SUM(X54:X55) -> #VALUE! | ... AA56: =SUM(AA54:AA55) -> #VALUE!
B58: =B56/(1+$B$5)^(B53) -> 0 | C58: =C56/(1+$B$5)^(C53)+B58 -> #VALUE! | D58: =D56/(1+$B$5)^(D53)+C58 -> #VALUE! | E58: =E56/(1+$B$5)^(E53)+D58 -> #VALUE! | F58: =F56/(1+$B$5)^(F53)+E58 -> #VALUE! | G58: =G56/(1+$B$5)^(G53)+F58 -> #VALUE! | H58: =H56/(1+$B$5)^(H53)+G58 -> #VALUE! | I58: =I56/(1+$B$5)^(I53)+H58 -> #VALUE! | J58: =J56/(1+$B$5)^(J53)+I58 -> #VALUE! | ... L58: =L56/(1+$B$5)^(L53)+K58 -> #VALUE! | Q58: =Q56/(1+$B$5)^(Q53) -> 0 | R58: =R56/(1+$B$5)^(R53)+Q58 -> #VALUE! | S58: =S56/(1+$B$5)^(S53)+R58 -> #VALUE! | T58: =T56/(1+$B$5)^(T53)+S58 -> #VALUE! | U58: =U56/(1+$B$5)^(U53)+T58 -> #VALUE! | V58: =V56/(1+$B$5)^(V53)+U58 -> #VALUE! | W58: =W56/(1+$B$5)^(W53)+V58 -> #VALUE! | X58: =X56/(1+$B$5)^(X53)+W58 -> #VALUE! | Y58: =Y56/(1+$B$5)^(Y53)+X58 -> #VALUE! | ... AA58: =AA56/(1+$B$5)^(AA53)+Z58 -> #VALUE!
B59: {=SUMPRODUCT(('Sistemas de Refrigeração'!C3:C1021<>"")*'Sistemas de Refrigeração'!AK3:AK1021)} -> 0 | Q59: {=SUMPRODUCT(('Sistemas de Refrigeração'!T3:T1021<>"")*'Sistemas de Refrigeração'!AZ3:AZ1021)} -> 0
B60: TIR ===> | C60: =IFERROR(IRR(B56:L56),"N/A") -> N/A | Q60: TIR ===> | R60: =IFERROR(IRR(Q56:AA56),"N/A") -> N/A
B61: RBC ===> | C61: =C62/-B58 -> #VALUE! | Q61: RBC ===> | R61: =R62/-Q58 -> #VALUE!
B62: VPL ===> | C62: =B56+NPV($B$5,C56:L56) -> #VALUE! | Q62: VPL ===> | R62: =Q56+NPV($B$5,R56:AA56) -> #VALUE!
B63: PBS ===> | C63: =(-1*B54)/C56 -> #VALUE! | D63: ano | Q63: PBS ===> | R63: =(-1*Q54)/R56 -> #VALUE! | S63: ano
B64: ECONOMIA (MWh/ano) ===> | C64: =C55/$E$4 -> #VALUE! | Q64: ECONOMIA (MWh/ano) ===> | R64: =R55/$E$4 -> #VALUE!

Sheet EQUIPAMENTOS_EFICIENTES (BDD)
A1: Tipo_Uso | B1: Tipo_Equipamento | C1: Potência | D1: Preço | F1: Tipo_Uso | G1: Tipo_Equipamento | H1: Classificação Inmetro | I1: Potência | J1: EER (W/W) | K1: Preço (R$) | L1: Referência | N1: Tipo_Uso | O1: Tipo_Equipamento | P1: Capacidade (L) | Q1: Potência (W) | R1: Consumo (kWh/mês) | S1: FU | T1: Porte | U1: Preço (R$) | V1: Referência | X1: Deconto da Automação
A2: Iluminação | F2: Condicionamento Ambiental | G2: Split Hi-Wall | H2: A | I2: 9000 | J2: 8.3 | K2: 3300 | L2: FTKP09S5VL | N2: Refrigeração | O2: Geladeira | P2: 240 | Q2: 110 | R2: 23.3 | S2: 0.3 | T2: Pequeno | U2: 1799 | V2: Electrolux RE31 | X2: 0.15
F3: Condicionamento Ambiental | G3: Split Hi-Wall | H3: A | I3: 12000 | J3: 8.3 | K3: 3583 | L3: FTKP12S5VL | N3: Refrigeração | O3: Geladeira | P3: 347 | Q3: 155 | R3: 34.8 | S3: 0.3 | T3: Médio | U3: 2735.79 | V3: Midea MD-RT468MTA
F4: Condicionamento Ambiental | G4: Split Hi-Wall | H4: A | I4: 18000 | J4: 7.6 | K4: 3603.46 | L4: FTKP18S5VL | N4: Refrigeração | O4: Geladeira | P4: 400 | Q4: 170 | R4: 37 | S4: 0.3 | T4: Grande | U4: 2629 | V4: Electrolux IB45 Inverter
F5: Condicionamento Ambiental | G5: Split Hi-Wall | H5: A | I5: 22000 | J5: 6.8 | K5: 5680.05 | L5: Fujitsu Airstage ASBA22KPCA | N5: Refrigeração | O5: Freezer Horizontal | P5: 309 | Q5: 98 | R5: 28.1 | S5: 0.4 | T5: Pequeno | U5: 2310.75 | V5: Consul CHA31
F6: Condicionamento Ambiental | G6: Split Hi-Wall | H6: A | I6: 24000 | J6: 8.3 | K6: 5721 | L6: FTKP24S5VL | N6: Refrigeração | O6: Freezer Horizontal | P6: 400 | Q6: 110 | R6: 31.3 | S6: 0.4 | T6: Médio | U6: 3762.92 | V6: Electrolux H440
F7: Condicionamento Ambiental | G7: Split Hi-Wall | H7: A | I7: 30000 | J7: 8.49 | K7: 5500 | L7: Elgin Eco Inverter II | N7: Refrigeração | O7: Freezer Horizontal | P7: 513 | Q7: 125 | R7: 35.6 | S7: 0.4 | T7: Grande | U7: 3499 | V7: Electrolux HI550 Inverter
F8: Condicionamento Ambiental | G8: Split Piso Teto | H8: A | I8: 18000 | J8: 6.5 | K8: 6200 | L8: Fujitsu Airstage Premium ABBH18KRTA/AOBH18KBTB | N8: Refrigeração | O8: Freezer Vertical | P8: 162 | Q8: 95 | R8: 22.7 | S8: 0.4 | T8: Pequeno | U8: 2200 | V8: Electrolux FEI19 Inverter
F9: Condicionamento Ambiental | G9: Split Piso Teto | H9: A | I9: 24000 | J9: 7.85 | K9: 8934.78 | L9: Teto Inverter Fujitsu Airstage Premium (ABBH24KRTA/AOBH24KBTB) | N9: Refrigeração | O9: Freezer Vertical | P9: 234 | Q9: 137 | R9: 32.9 | S9: 0.4 | T9: Médio | U9: 2949 | V9: Electrolux FEI27 Inverter
F10: Condicionamento Ambiental | G10: Split Piso Teto | H10: A | I10: 30000 | J10: 6.51 | K10: 9666 | L10: Teto Inverter Fujitsu Airstage Premium (ABBH30KRTA/AOBH30KBTB) | N10: Refrigeração | O10: Freezer Vertical | P10: 400 | Q10: 180 | R10: 48 | S10: 0.4 | T10: Grande | U10: 4999 | V10: Metalfrio VN44
F11: Condicionamento Ambiental | G11: Split Piso Teto | H11: A | I11: 36000 | J11: 5.61 | K11: 8299 | L11: GULD36ZD1/A-S / GULD36W1/NHA-S | N11: Refrigeração | O11: Frigobar | P11: 80 | Q11: 65 | R11: 19 | S11: 0.3 | T11: Pequeno | U11: 1300 | V11: Consul CRC08
F12: Condicionamento Ambiental | G12: Split Piso Teto | H12: A | I12: 48000 | J12: 5.81 | K12: 11655.06 | L12: EASMPT48000F | N12: Refrigeração | O12: Bebedouro | P12: 50 | Q12: 180 | R12: 18 | S12: 0.5 | T12: Médio | U12: 2100 | V12: Frisbel B50 Inox
F13: Condicionamento Ambiental | G13: Split Piso Teto | H13: A | I13: 57000 | J13: 5.57 | K13: 13297.11 | L13: ED020N2550 / CF090W2530
F14: Condicionamento Ambiental | G14: Split Piso Teto | H14: A | I14: 60000 | J14: 5.5 | K14: 10076.67 | L14: Inverter Connect AUV-60UR2RNCAE
F15: Condicionamento Ambiental | G15: Split Cassete | H15: A | I15: 24000 | J15: 6.1 | K15: 11999 | L15: Fujitsu Airstage Cassete R32 (AUBH24KRTA)
F16: Condicionamento Ambiental | G16: Split Cassete | H16: A | I16: 30000 | J16: 5.8 | K16: 14039 | L16: Daikin SkyAir FCQ30KVL Inverter
F17: Condicionamento Ambiental | G17: Split Cassete | H17: A | I17: 36000 | J17: 5.5 | K17: 15864.05 | L17: Daikin SkyAir FCQ36KVL Inverter
F18: Condicionamento Ambiental | G18: Split Cassete | H18: A | I18: 48000 | J18: 5.4 | K18: 17748 | L18: Daikin SkyAir FCQ48KVL Inverter
F19: Condicionamento Ambiental | G19: Split Cassete | H19: A | I19: 60000 | J19: 5.2 | K19: 17749.8 | L19: Daikin SkyAir Inverter (sob consulta)

Sheet Sistemas de Aquecimento de Água
A1: Unidade Consumidora | C1: DADOS DO COLETOR | K1: DADOS DO RESERVATÓRIO | Q1: DADOS DO PROJETO | AA1: FATOR DE COINCIDÊNCIA NA PONTA | AD1: RESULTADOS ESPERADOS
A2: Unidade consumidora (Número da conta contrato) | B2: Descrição do sistema | C2: Fabricante coletor solar | D2: Marca e modelo do coletor solar | E2: Área externa (m²) | F2: Produção média mensal de energia (kWh/mês) | G2: Eficiência energética (%) | H2: Produção média mensal de energia por área coletora (kWh/m2×mês) | I2: Área coletora por unidade consumidora (m²) | J2: Número de coletores solares | K2: Fabricante do reservatório térmico | L2: Modelo do reservatório térmico | M2: Volume do reservatório térmico (L) | N2: Perda específica energética mensal (kWh/mês/L) | O2: Volume de água quente consumida (L) | P2: Número mínimo de reservatórios com apoio elétrico | Q2: Número médio de chuveiros por UC | R2: Potência máxima típica dos chuveiros utilizados (W) | S2: Potência média do aquecimento auxiliar | T2: Fator de coincidência na ponta | U2: Fração solar | V2: Nº médio de banhos/dia | W2: Tempo médio de banho (min) | X2: Vazão típica do chuveiro (L/min) | Y2: Cidade de referência | Z2: Fator de correção | AA2: Número médio de banhos na ponta | AB2: Tempo médio de banho (min) | AC2: Número de chuveiros por unidade consumidora | AD2: Redução de demanda na ponta (kW) | AE2: Energia economizada (MWh/ano) | AF2: Redução de consumo proposto em relação ao consumo total da UC (%)
A3: =IF(UC_DADOS!$B$2=0,"",UC_DADOS!$B$2) -> #N/A | I3: =J3*E3 -> 0
A4: =IF(UC_DADOS!$B$2=0,"",UC_DADOS!$B$2) -> #N/A | I4: =J4*E4 -> 0
A5: =IF(UC_DADOS!$B$2=0,"",UC_DADOS!$B$2) -> #N/A | I5: =J5*E5 -> 0
A6: =IF(UC_DADOS!$B$2=0,"",UC_DADOS!$B$2) -> #N/A | I6: =J6*E6 -> 0
A7: =IF(UC_DADOS!$B$2=0,"",UC_DADOS!$B$2) -> #N/A | I7: =J7*E7 -> 0
A8: =IF(UC_DADOS!$B$2=0,"",UC_DADOS!$B$2) -> #N/A | I8: =J8*E8 -> 0
A9: =IF(UC_DADOS!$B$2=0,"",UC_DADOS!$B$2) -> #N/A | I9: =J9*E9 -> 0
A10: =IF(UC_DADOS!$B$2=0,"",UC_DADOS!$B$2) -> #N/A | I10: =J10*E10 -> 0
A11: =IF(UC_DADOS!$B$2=0,"",UC_DADOS!$B$2) -> #N/A | I11: =J11*E11 -> 0
A12: =IF(UC_DADOS!$B$2=0,"",UC_DADOS!$B$2) -> #N/A | I12: =J12*E12 -> 0
A13: =IF(UC_DADOS!$B$2=0,"",UC_DADOS!$B$2) -> #N/A | I13: =J13*E13 -> 0
A14: =IF(UC_DADOS!$B$2=0,"",UC_DADOS!$B$2) -> #N/A | I14: =J14*E14 -> 0
... A100: =IF(UC_DADOS!$B$2=0,"",UC_DADOS!$B$2) -> #N/A | I100: =J100*E100 -> 0

Sheet Sistemas Solar Fotovoltaico
A1: Unidade Consumidora | C1: SISTEMA PROPOSTO | M1: RESULTADOS ESPERADOS
A2: Unidade consumidora (Número da conta contrato) | B2: Descrição do sistema | C2: Tipo de equipamento / tecnologia | D2: Potência nominal do sistema (W) | E2: Quantidade | F2: Potência instalada de geração (kW) | G2: Funcionamento (h/dia) | H2: Dias de funcionamento do sistema, em um ano (dia/ano) | I2: Funcionamento (h/ano) | J2: Meses no ano, de funcionamento do Sistema no horário de Ponta (meses) | K2: Dias úteis no mês, de funcionamento do Sistema no horário de Ponta (dias) | L2: Horas por dia, de funcionamento do Sistema no horário de Ponta (horas) | M2: Demanda atendida na ponta (kW) | N2: Demanda atendida fora de ponta (kW) | O2: Energia gerada na ponta (MWh/ano) | P2: Energia gerada fora de ponta (MWh/ano) | Q2: Energia gerada total (MWh/ano) | R2: Redução de consumo proposto em relação ao consumo total da UC (%)
A3: =IF(UC_DADOS!$B$2=0,"",UC_DADOS!$B$2) -> #N/A
A4: =IF(UC_DADOS!$B$2=0,"",UC_DADOS!$B$2) -> #N/A
A5: =IF(UC_DADOS!$B$2=0,"",UC_DADOS!$B$2) -> #N/A
A6: =IF(UC_DADOS!$B$2=0,"",UC_DADOS!$B$2) -> #N/A
A7: =IF(UC_DADOS!$B$2=0,"",UC_DADOS!$B$2) -> #N/A
A8: =IF(UC_DADOS!$B$2=0,"",UC_DADOS!$B$2) -> #N/A
A9: =IF(UC_DADOS!$B$2=0,"",UC_DADOS!$B$2) -> #N/A
A10: =IF(UC_DADOS!$B$2=0,"",UC_DADOS!$B$2) -> #N/A
A11: =IF(UC_DADOS!$B$2=0,"",UC_DADOS!$B$2) -> #N/A
A12: =IF(UC_DADOS!$B$2=0,"",UC_DADOS!$B$2) -> #N/A
A13: =IF(UC_DADOS!$B$2=0,"",UC_DADOS!$B$2) -> #N/A
A14: =IF(UC_DADOS!$B$2=0,"",UC_DADOS!$B$2) -> #N/A
... A100: =IF(UC_DADOS!$B$2=0,"",UC_DADOS!$B$2) -> #N/A
